Workbook
Name City: Sheet2!$B$2:$B$20
Name Day_Wise_Exursion: 'Day Wise Exursion'!$B$2:$B$32
Name Header: Sheet2!$J$21:$FJ$21
Name MYName: IF(INDEX(Sheet2!$J$22:$FJ$28,0,MATCH(Summary!XFD1,Header,0))=0,"",INDEX(Sheet2!$J$22:$FJ$28,0,MATCH(Summary!XFD1,Header,0)))
Name Type: INDEX(Sheet2!$J$22:$FJ$27,0,MATCH(Summary!$E11,Header,0))

Sheet Summary
D1: https://rateonclick.com/rate
H2: Address: - Shop No. 210, 2nd Floor, Pratap Complex, Metro Gate Number 3, near Munirka, Baba Gangnath Market, Munirka, New Delhi, Delhi 110067 Phone: +91-9870229792, +91-9910987264 Email: info@ghumofiroo.com
D6: Char Dham Deluxe Plus Packages
D7: =IF(AND(F17<>"", H17<>""), "For " & TEXT(LEFT(F17, FIND(" ", H17)-1), "00") & " Nights " & TEXT(LEFT(H17, FIND(" ", H17)-1), "00") & " Days", "") -> For 06 Nights 07 Days
D8: Travel Itinerary
D9: Welcome to Ghumo Firoo!
D11: This is Navin Kumar Mishra, and I will be working with you to plan your trip to Char Dham.
D13: Please find below details for your trip and feel free to call me at +91-9910987264.
D15: Query Details
D16: #Booking Code | F16: Q/25/979949 | H16: Total Guests | K16: 3 | N16: Occupancy Type | O16: Triple
D17: Trip Duration | F17: =(H37-G37)&" "&"Nights" -> 6 Nights | H17: =DAY(H37-G37)+1&" "&"Days" -> 7 Days | J17: =O17 -> No Extra Bed | K17: =IF(O16="Double", MOD(K16,2),IF(O16="Triple", MOD(K16,3),IF(O16="Quad", MOD(K16,4), 0))) -> 0 | N17: Passanger Type | O17: No Extra Bed
D18: Pick Up City | E18: Delhi | F18: Drop City | H18: Delhi | J18: Start Date | K18: =G37 -> 46184
D19: Destination Covered | F19: {=_xlfn.TEXTJOIN(", ", TRUE, _xlfn.UNIQUE(_xlfn._xlws.FILTER(D26:D36, D26:D36<>"")))} -> Sonprayag, Kedarnath, Pipalkoti, Badarinath, Rudraprayag | J19: End Date | K19: =H37 -> 46190 | N19: Cab Type | O19: Ertiga 7 Seater
D20: चार धाम यात्रा 2026 – आस्था की ओर एक कदम, घूमो फिरो ट्रैवल्स के साथ।
N21: Markup | O21: 0.01
N22: Cost of Markup | O22: =V37*O21 -> 721.5
D24: ="Package Name: Char Dham " &IF(COUNTIF(E26:E36,"Premium")=COUNTA(E26:E36),"Premium Package",IF(COUNTIF(E26:E36,"Standard")=COUNTA(E26:E36),"Standard Package",IF(COUNTIF(E26:E36,"Budget")=COUNTA(E26:E36),"Budget Package","Mix Package"))) -> Package Name: Char Dham Mix Package | O24: 1 Night/Day Price | T24: Total Price
D25: City | E25: Hotel Category | F25: Hotel Name | G25: Check-In | H25: Check-Out | I25: Nights | J25: Cab Type | K25: Meal Plan | L25: Rooms | M25: Total Guests | N25: Extra Passanger | O25: Double | P25: Triple | Q25: Quad | R25: =IF(O17="NA", "Cost Not Applicable", "Cost of " & O17) -> Cost of No Extra Bed | S25: Transfer Cost | T25: Total Room Price | U25: =IF(O17="NA", "Cost Not Applicable", "Total Cost of " & O17) -> Total Cost of No Extra Bed | V25: Total Price | W25: Advance | X25: Balance
A26: =IF(F26="","",F26&"-"&E26&"-"&$O$16&" "&$K26) -> Kailashpati Resort -Standard-Triple MAP | B26: =IF(F26="","",F26&"-"&$O$17&"-"&$O$16&" "&$K26) -> Kailashpati Resort -No Extra Bed-Triple MAP | D26: Sonprayag | E26: Standard | F26: Kailashpati Resort | G26: =IF(ISNUMBER($G$37), $G$37, "") -> 46184 | H26: =IF(I26=0, "", G26 + I26) -> 46185 | I26: 1 | J26: =IF(F26="","",$O$19) -> Ertiga 7 Seater | K26: MAP | L26: =IF(F26="","",FLOOR($K$16/IF($O$16="Double",2,IF($O$16="Triple",3,4)),1)) -> 1 | M26: =IF(F26="","",$K$16) -> 3 | N26: =IF(F26="","",$K$17) -> 0 | O26: =IFERROR(IF(F26="","",IF($O$16="Double",VLOOKUP($A26,Price[],2,0),"")),0) | P26: =IFERROR(IF(F26="","",IF($O$16="Triple",VLOOKUP($A26,Price[],2,0),"")),0) -> 4200 | Q26: =IFERROR(IF(G26="","",IF($O$16="Quad",VLOOKUP($A26,Price[],2,0),"")),0) | R26: =IFERROR(IF(F26="","",VLOOKUP($B26,Extra_fare_price[#All],2,0)),0) -> 0 | S26: =IF(OR($O$19="",D26="",I26=""),"",I26 *IF(AND($E$18<>"",$H$18<>""),IF($E$18=$H$18,VLOOKUP($O$19, Price!$J:$L, MATCH(TRIM($E$18), Price!$J$1:$L$1, 0), FALSE),""),IF($E$18<>"",VLOOKUP($O$19, Price!$J:$L, MATCH(TRIM($E$18), Price!$J$1:$L$1, 0), FALSE),IF($H$18<>"",VLOOKUP($O$19, Price!$J:$L, MATCH(TRIM($H$18), Price!$J$1:$L$1, 0), FALSE),"")))) -> 5300 | T26: =IF(F26="","",SUM(O26:Q26)*I26*L26) -> 4200 | U26: =IF(F26="","",R26*I26) -> 0 | V26: =IF(AND(S26="",T26="", U26=""), "", SUM(S26:U26)) -> 9500 | W26: 6500 | X26: =IF(V26="","",V26-W26) -> 3000 | Y26: =IF(V26 = (S26 +T26 + U26), "✅", "❌") -> ✅ | Z26: 6500 | AA26: =Z26-W26 -> 0
A27: =IF(F27="","",F27&"-"&E27&"-"&$O$16&" "&$K27) -> Bagwari House -Budget-Triple EP | B27: =IF(F27="","",F27&"-"&$O$17&"-"&$O$16&" "&$K27) -> Bagwari House -No Extra Bed-Triple EP | D27: Kedarnath | E27: Budget | F27: Bagwari House | G27: =IF(F27="","",IF(ISNUMBER(H26), H26, "")) -> 46185 | H27: =IF(I27=0, "", G27 + I27) -> 46186 | I27: 1 | J27: =IF(F27="","",$O$19) -> Ertiga 7 Seater | K27: EP | L27: =IF(F27="","",FLOOR($K$16/IF($O$16="Double",2,IF($O$16="Triple",3,4)),1)) -> 1 | M27: =IF(F27="","",$K$16) -> 3 | N27: =IF(F27="","",$K$17) -> 0 | O27: =IFERROR(IF(F27="","",IF($O$16="Double",VLOOKUP($A27,Price[],2,0),"")),0) | P27: =IFERROR(IF(F27="","",IF($O$16="Triple",VLOOKUP($A27,Price[],2,0),"")),0) -> 7200 | Q27: =IFERROR(IF(G27="","",IF($O$16="Quad",VLOOKUP($A27,Price[],2,0),"")),0) | R27: =IFERROR(IF(F27="","",VLOOKUP($B27,Extra_fare_price[#All],2,0)),0) -> 0 | S27: =IF(OR($O$19="",D27="",I27=""),"",I27 *IF(AND($E$18<>"",$H$18<>""),IF($E$18=$H$18,VLOOKUP($O$19, Price!$J:$L, MATCH(TRIM($E$18), Price!$J$1:$L$1, 0), FALSE),""),IF($E$18<>"",VLOOKUP($O$19, Price!$J:$L, MATCH(TRIM($E$18), Price!$J$1:$L$1, 0), FALSE),IF($H$18<>"",VLOOKUP($O$19, Price!$J:$L, MATCH(TRIM($H$18), Price!$J$1:$L$1, 0), FALSE),"")))) -> 5300 | T27: =IF(F27="","",SUM(O27:Q27)*I27*L27) -> 7200 | U27: =IF(F27="","",R27*I27) -> 0 | V27: =IF(AND(S27="",T27="", U27=""), "", SUM(S27:U27)) -> 12500 | W27: 10000 | X27: =IF(V27="","",V27-W27) -> 2500 | Y27: =IF(V27 = (S27 +T27 + U27), "✅", "❌") -> ✅ | Z27: 10000 | AA27: =Z27-W27 -> 0
A28: =IF(F28="","",F28&"-"&E28&"-"&$O$16&" "&$K28) -> Kailashpati Resort -Standard-Triple MAP | B28: =IF(F28="","",F28&"-"&$O$17&"-"&$O$16&" "&$K28) -> Kailashpati Resort -No Extra Bed-Triple MAP | D28: Sonprayag | E28: Standard | F28: Kailashpati Resort | G28: =IF(F28="","",IF(ISNUMBER(H27), H27, "")) -> 46186 | H28: =IF(I28=0, "", G28 + I28) -> 46187 | I28: 1 | J28: =IF(F28="","",$O$19) -> Ertiga 7 Seater | K28: MAP | L28: =IF(F28="","",FLOOR($K$16/IF($O$16="Double",2,IF($O$16="Triple",3,4)),1)) -> 1 | M28: =IF(F28="","",$K$16) -> 3 | N28: =IF(F28="","",$K$17) -> 0 | O28: =IFERROR(IF(F28="","",IF($O$16="Double",VLOOKUP($A28,Price[],2,0),"")),0) | P28: =IFERROR(IF(F28="","",IF($O$16="Triple",VLOOKUP($A28,Price[],2,0),"")),0) -> 4200 | Q28: =IFERROR(IF(G28="","",IF($O$16="Quad",VLOOKUP($A28,Price[],2,0),"")),0) | R28: =IFERROR(IF(F28="","",VLOOKUP($B28,Extra_fare_price[#All],2,0)),0) -> 0 | S28: =IF(OR($O$19="",D28="",I28=""),"",I28 *IF(AND($E$18<>"",$H$18<>""),IF($E$18=$H$18,VLOOKUP($O$19, Price!$J:$L, MATCH(TRIM($E$18), Price!$J$1:$L$1, 0), FALSE),""),IF($E$18<>"",VLOOKUP($O$19, Price!$J:$L, MATCH(TRIM($E$18), Price!$J$1:$L$1, 0), FALSE),IF($H$18<>"",VLOOKUP($O$19, Price!$J:$L, MATCH(TRIM($H$18), Price!$J$1:$L$1, 0), FALSE),"")))) -> 5300 | T28: =IF(F28="","",SUM(O28:Q28)*I28*L28) -> 4200 | U28: =IF(F28="","",R28*I28) -> 0 | V28: =IF(AND(S28="",T28="", U28=""), "", SUM(S28:U28)) -> 9500 | W28: 6000 | X28: =IF(V28="","",V28-W28) -> 3500 | Y28: =IF(V28 = (S28 +T28 + U28), "✅", "❌") -> ✅ | Z28: 6000 | AA28: =Z28-W28 -> 0 | AB28: P
A29: =IF(F29="","",F29&"-"&E29&"-"&$O$16&" "&$K29) -> Hotel Le Meadows -Premium-Triple MAP | B29: =IF(F29="","",F29&"-"&$O$17&"-"&$O$16&" "&$K29) -> Hotel Le Meadows -No Extra Bed-Triple MAP | D29: Pipalkoti | E29: Premium | F29: Hotel Le Meadows | G29: =IF(F29="","",IF(ISNUMBER(H28), H28, "")) -> 46187 | H29: =IF(I29=0, "", G29 + I29) -> 46188 | I29: 1 | J29: =IF(F29="","",$O$19) -> Ertiga 7 Seater | K29: MAP | L29: =IF(F29="","",FLOOR($K$16/IF($O$16="Double",2,IF($O$16="Triple",3,4)),1)) -> 1 | M29: =IF(F29="","",$K$16) -> 3 | N29: =IF(F29="","",$K$17) -> 0 | O29: =IFERROR(IF(F29="","",IF($O$16="Double",VLOOKUP($A29,Price[],2,0),"")),0) | P29: =IFERROR(IF(F29="","",IF($O$16="Triple",VLOOKUP($A29,Price[],2,0),"")),0) -> 7400 | Q29: =IFERROR(IF(G29="","",IF($O$16="Quad",VLOOKUP($A29,Price[],2,0),"")),0) | R29: =IFERROR(IF(F29="","",VLOOKUP($B29,Extra_fare_price[#All],2,0)),0) -> 0 | S29: =IF(OR($O$19="",D29="",I29=""),"",I29 *IF(AND($E$18<>"",$H$18<>""),IF($E$18=$H$18,VLOOKUP($O$19, Price!$J:$L, MATCH(TRIM($E$18), Price!$J$1:$L$1, 0), FALSE),""),IF($E$18<>"",VLOOKUP($O$19, Price!$J:$L, MATCH(TRIM($E$18), Price!$J$1:$L$1, 0), FALSE),IF($H$18<>"",VLOOKUP($O$19, Price!$J:$L, MATCH(TRIM($H$18), Price!$J$1:$L$1, 0), FALSE),"")))) -> 5300 | T29: =IF(F29="","",SUM(O29:Q29)*I29*L29) -> 7400 | U29: =IF(F29="","",R29*I29) -> 0 | V29: =IF(AND(S29="",T29="", U29=""), "", SUM(S29:U29)) -> 12700 | W29: 5000 | X29: =IF(V29="","",V29-W29) -> 7700 | Y29: =IF(V29 = (S29 +T29 + U29), "✅", "❌") -> ✅ | Z29: 5000 | AA29: =Z29-W29 -> 0
A30: =IF(F30="","",F30&"-"&E30&"-"&$O$16&" "&$K30) -> Hotel New Urvashi-Premium-Triple MAP | B30: =IF(F30="","",F30&"-"&$O$17&"-"&$O$16&" "&$K30) -> Hotel New Urvashi-No Extra Bed-Triple MAP | D30: Badarinath | E30: Premium | F30: Hotel New Urvashi | G30: =IF(F30="","",IF(ISNUMBER(H29), H29, "")) -> 46188 | H30: =IF(I30=0, "", G30 + I30) -> 46189 | I30: 1 | J30: =IF(F30="","",$O$19) -> Ertiga 7 Seater | K30: MAP | L30: =IF(F30="","",FLOOR($K$16/IF($O$16="Double",2,IF($O$16="Triple",3,4)),1)) -> 1 | M30: =IF(F30="","",$K$16) -> 3 | N30: =IF(F30="","",$K$17) -> 0 | O30: =IFERROR(IF(F30="","",IF($O$16="Double",VLOOKUP($A30,Price[],2,0),"")),0) | P30: =IFERROR(IF(F30="","",IF($O$16="Triple",VLOOKUP($A30,Price[],2,0),"")),0) -> 7000 | Q30: =IFERROR(IF(G30="","",IF($O$16="Quad",VLOOKUP($A30,Price[],2,0),"")),0) | R30: =IFERROR(IF(F30="","",VLOOKUP($B30,Extra_fare_price[#All],2,0)),0) -> 0 | S30: =IF(OR($O$19="",D30="",I30=""),"",I30 *IF(AND($E$18<>"",$H$18<>""),IF($E$18=$H$18,VLOOKUP($O$19, Price!$J:$L, MATCH(TRIM($E$18), Price!$J$1:$L$1, 0), FALSE),""),IF($E$18<>"",VLOOKUP($O$19, Price!$J:$L, MATCH(TRIM($E$18), Price!$J$1:$L$1, 0), FALSE),IF($H$18<>"",VLOOKUP($O$19, Price!$J:$L, MATCH(TRIM($H$18), Price!$J$1:$L$1, 0), FALSE),"")))) -> 5300 | T30: =IF(F30="","",SUM(O30:Q30)*I30*L30) -> 7000 | U30: =IF(F30="","",R30*I30) -> 0 | V30: =IF(AND(S30="",T30="", U30=""), "", SUM(S30:U30)) -> 12300 | W30: 6000 | X30: =IF(V30="","",V30-W30) -> 6300 | Y30: =IF(V30 = (S30 +T30 + U30), "✅", "❌") -> ✅ | Z30: 6000 | AA30: =Z30-W30 -> 0
A31: =IF(F31="","",F31&"-"&E31&"-"&$O$16&" "&$K31) -> Hotel Mandakini Deluxe Rooms-Standard-Triple MAP | B31: =IF(F31="","",F31&"-"&$O$17&"-"&$O$16&" "&$K31) -> Hotel Mandakini Deluxe Rooms-No Extra Bed-Triple MAP | D31: Rudraprayag | E31: Standard | F31: Hotel Mandakini Deluxe Rooms | G31: =IF(F31="","",IF(ISNUMBER(H30), H30, "")) -> 46189 | H31: =IF(I31=0, "", G31 + I31) -> 46190 | I31: 1 | J31: =IF(F31="","",$O$19) -> Ertiga 7 Seater | K31: MAP | L31: =IF(F31="","",FLOOR($K$16/IF($O$16="Double",2,IF($O$16="Triple",3,4)),1)) -> 1 | M31: =IF(F31="","",$K$16) -> 3 | N31: =IF(F31="","",$K$17) -> 0 | O31: =IFERROR(IF(F31="","",IF($O$16="Double",VLOOKUP($A31,Price[],2,0),"")),0) | P31: =IFERROR(IF(F31="","",IF($O$16="Triple",VLOOKUP($A31,Price[],2,0),"")),0) -> 5050 | Q31: =IFERROR(IF(G31="","",IF($O$16="Quad",VLOOKUP($A31,Price[],2,0),"")),0) | R31: =IFERROR(IF(F31="","",VLOOKUP($B31,Extra_fare_price[#All],2,0)),0) -> 0 | S31: =IF(OR($O$19="",D31="",I31=""),"",I31 *IF(AND($E$18<>"",$H$18<>""),IF($E$18=$H$18,VLOOKUP($O$19, Price!$J:$L, MATCH(TRIM($E$18), Price!$J$1:$L$1, 0), FALSE),""),IF($E$18<>"",VLOOKUP($O$19, Price!$J:$L, MATCH(TRIM($E$18), Price!$J$1:$L$1, 0), FALSE),IF($H$18<>"",VLOOKUP($O$19, Price!$J:$L, MATCH(TRIM($H$18), Price!$J$1:$L$1, 0), FALSE),"")))) -> 5300 | T31: =IF(F31="","",SUM(O31:Q31)*I31*L31) -> 5050 | U31: =IF(F31="","",R31*I31) -> 0 | V31: =IF(AND(S31="",T31="", U31=""), "", SUM(S31:U31)) -> 10350 | W31: 5600 | X31: =IF(V31="","",V31-W31) -> 4750 | Y31: =IF(V31 = (S31 +T31 + U31), "✅", "❌") -> ✅ | Z31: 5600 | AA31: =Z31-W31 -> 0
A32: =IF(F32="","",F32&"-"&E32&"-"&$O$16&" "&$K32) | B32: =IF(F32="","",F32&"-"&$O$17&"-"&$O$16&" "&$K32) | G32: =IF(F32="","",IF(ISNUMBER(H31), H31, "")) | H32: =IF(I32=0, "", G32 + I32) | J32: =IF(F32="","",$O$19) | L32: =IF(F32="","",FLOOR($K$16/IF($O$16="Double",2,IF($O$16="Triple",3,4)),1)) | M32: =IF(F32="","",$K$16) | N32: =IF(F32="","",$K$17) | O32: =IFERROR(IF(F32="","",IF($O$16="Double",VLOOKUP($A32,Price[],2,0),"")),0) | P32: =IFERROR(IF(F32="","",IF($O$16="Triple",VLOOKUP($A32,Price[],2,0),"")),0) | Q32: =IFERROR(IF(G32="","",IF($O$16="Quad",VLOOKUP($A32,Price[],2,0),"")),0) | R32: =IFERROR(IF(F32="","",VLOOKUP($B32,Extra_fare_price[#All],2,0)),0) | S32: =IF(OR($O$19="",D32="",I32=""),"",I32 *IF(AND($E$18<>"",$H$18<>""),IF($E$18=$H$18,VLOOKUP($O$19, Price!$J:$L, MATCH(TRIM($E$18), Price!$J$1:$L$1, 0), FALSE),""),IF($E$18<>"",VLOOKUP($O$19, Price!$J:$L, MATCH(TRIM($E$18), Price!$J$1:$L$1, 0), FALSE),IF($H$18<>"",VLOOKUP($O$19, Price!$J:$L, MATCH(TRIM($H$18), Price!$J$1:$L$1, 0), FALSE),"")))) | T32: =IF(F32="","",SUM(O32:Q32)*I32*L32) | U32: =IF(F32="","",R32*I32) | V32: =IF(AND(S32="",T32="", U32=""), "", SUM(S32:U32)) | W32: 8500 | X32: =IF(V32="","",V32-W32) | Y32: =IF(V32 = (S32 +T32 + U32), "✅", "❌") -> #VALUE! | Z32: 8500 | AA32: =Z32-W32 -> 0
A33: =IF(F33="","",F33&"-"&E33&"-"&$O$16&" "&$K33) | B33: =IF(F33="","",F33&"-"&$O$17&"-"&$O$16&" "&$K33) | G33: =IF(F33="","",IF(ISNUMBER(H32), H32, "")) | H33: =IF(I33=0, "", G33 + I33) | J33: =IF(F33="","",$O$19) | L33: =IF(F33="","",FLOOR($K$16/IF($O$16="Double",2,IF($O$16="Triple",3,4)),1)) | M33: =IF(F33="","",$K$16) | N33: =IF(F33="","",$K$17) | O33: =IFERROR(IF(F33="","",IF($O$16="Double",VLOOKUP($A33,Price[],2,0),"")),0) | P33: =IFERROR(IF(F33="","",IF($O$16="Triple",VLOOKUP($A33,Price[],2,0),"")),0) | Q33: =IFERROR(IF(G33="","",IF($O$16="Quad",VLOOKUP($A33,Price[],2,0),"")),0) | R33: =IFERROR(IF(F33="","",VLOOKUP($B33,Extra_fare_price[#All],2,0)),0) | S33: =IF(OR($O$19="",D33="",I33=""),"",I33 *IF(AND($E$18<>"",$H$18<>""),IF($E$18=$H$18,VLOOKUP($O$19, Price!$J:$L, MATCH(TRIM($E$18), Price!$J$1:$L$1, 0), FALSE),""),IF($E$18<>"",VLOOKUP($O$19, Price!$J:$L, MATCH(TRIM($E$18), Price!$J$1:$L$1, 0), FALSE),IF($H$18<>"",VLOOKUP($O$19, Price!$J:$L, MATCH(TRIM($H$18), Price!$J$1:$L$1, 0), FALSE),"")))) | T33: =IF(F33="","",SUM(O33:Q33)*I33*L33) | U33: =IF(F33="","",R33*I33) | V33: =IF(AND(S33="",T33="", U33=""), "", SUM(S33:U33)) | W33: 1001 | X33: =IF(V33="","",V33-W33) | Y33: =IF(V33 = (S33 +T33 + U33), "✅", "❌") -> #VALUE! | Z33: 4800 | AA33: =Z33-W33 -> 3799
A34: =IF(F34="","",F34&"-"&E34&"-"&$O$16&" "&$K34) | B34: =IF(F34="","",F34&"-"&$O$17&"-"&$O$16&" "&$K34) | G34: =IF(F34="","",IF(ISNUMBER(H33), H33, "")) | H34: =IF(I34=0, "", G34 + I34) | J34: =IF(F34="","",$O$19) | L34: =IF(F34="","",FLOOR($K$16/IF($O$16="Double",2,IF($O$16="Triple",3,4)),1)) | M34: =IF(F34="","",$K$16) | N34: =IF(F34="","",$K$17) | O34: =IFERROR(IF(F34="","",IF($O$16="Double",VLOOKUP($A34,Price[],2,0),"")),0) | P34: =IFERROR(IF(F34="","",IF($O$16="Triple",VLOOKUP($A34,Price[],2,0),"")),0) | Q34: =IFERROR(IF(G34="","",IF($O$16="Quad",VLOOKUP($A34,Price[],2,0),"")),0) | R34: =IFERROR(IF(F34="","",VLOOKUP($B34,Extra_fare_price[#All],2,0)),0) | S34: =IF(OR($O$19="",D34="",I34=""),"",I34 *IF(AND($E$18<>"",$H$18<>""),IF($E$18=$H$18,VLOOKUP($O$19, Price!$J:$L, MATCH(TRIM($E$18), Price!$J$1:$L$1, 0), FALSE),""),IF($E$18<>"",VLOOKUP($O$19, Price!$J:$L, MATCH(TRIM($E$18), Price!$J$1:$L$1, 0), FALSE),IF($H$18<>"",VLOOKUP($O$19, Price!$J:$L, MATCH(TRIM($H$18), Price!$J$1:$L$1, 0), FALSE),"")))) | T34: =IF(F34="","",SUM(O34:Q34)*I34*L34) | U34: =IF(F34="","",R34*I34) | V34: =IF(AND(S34="",T34="", U34=""), "", SUM(S34:U34)) | W34: 2501 | X34: =IF(V34="","",V34-W34) | Y34: =IF(V34 = (S34 +T34 + U34), "✅", "❌") -> #VALUE! | Z34: 22200 | AA34: =Z34-W34 -> 19699
A35: =IF(F35="","",F35&"-"&E35&"-"&$O$16&" "&$K35) | B35: =IF(F35="","",F35&"-"&$O$17&"-"&$O$16&" "&$K35) | G35: =IF(F35="","",IF(ISNUMBER(H34), H34, "")) | H35: =IF(I35=0, "", G35 + I35) | J35: =IF(F35="","",$O$19) | L35: =IF(F35="","",FLOOR($K$16/IF($O$16="Double",2,IF($O$16="Triple",3,4)),1)) | M35: =IF(F35="","",$K$16) | N35: =IF(F35="","",$K$17) | O35: =IFERROR(IF(F35="","",IF($O$16="Double",VLOOKUP($A35,Price[],2,0),"")),0) | P35: =IFERROR(IF(F35="","",IF($O$16="Triple",VLOOKUP($A35,Price[],2,0),"")),0) | Q35: =IFERROR(IF(G35="","",IF($O$16="Quad",VLOOKUP($A35,Price[],2,0),"")),0) | R35: =IFERROR(IF(F35="","",VLOOKUP($B35,Extra_fare_price[#All],2,0)),0) | S35: =IF(OR($O$19="",D35="",I35=""),"",I35 *IF(AND($E$18<>"",$H$18<>""),IF($E$18=$H$18,VLOOKUP($O$19, Price!$J:$L, MATCH(TRIM($E$18), Price!$J$1:$L$1, 0), FALSE),""),IF($E$18<>"",VLOOKUP($O$19, Price!$J:$L, MATCH(TRIM($E$18), Price!$J$1:$L$1, 0), FALSE),IF($H$18<>"",VLOOKUP($O$19, Price!$J:$L, MATCH(TRIM($H$18), Price!$J$1:$L$1, 0), FALSE),"")))) | T35: =IF(F35="","",SUM(O35:Q35)*I35*L35) | U35: =IF(F35="","",R35*I35) | V35: =IF(AND(S35="",T35="", U35=""), "", SUM(S35:U35)) | W35: 1501 | X35: =IF(V35="","",V35-W35) | Y35: =IF(V35 = (S35 +T35 + U35), "✅", "❌") -> #VALUE! | Z35: 37000 | AA35: =Z35-W35 -> 35499
A36: =IF(F36="","",F36&"-"&E36&"-"&$O$16&" "&$K36) | B36: =IF(F36="","",F36&"-"&$O$17&"-"&$O$16&" "&$K36) | G36: =IF(F36="","",IF(ISNUMBER(H35), H35, "")) | J36: =IF(F36="","",$O$19) | L36: =IF(F36="","",FLOOR($K$16/IF($O$16="Double",2,IF($O$16="Triple",3,4)),1)) | M36: =IF(F36="","",$K$16) | N36: =IF(F36="","",$K$17) | O36: =IFERROR(IF(F36="","",IF($O$16="Double",VLOOKUP($A36,Price[],2,0),"")),0) | P36: =IFERROR(IF(F36="","",IF($O$16="Triple",VLOOKUP($A36,Price[],2,0),"")),0) | Q36: =IFERROR(IF(G36="","",IF($O$16="Quad",VLOOKUP($A36,Price[],2,0),"")),0) | R36: =IFERROR(IF(F36="","",VLOOKUP($B36,Extra_fare_price[#All],2,0)),0) | S36: =IF(OR($O$19="",D36="",I36=""),"",I36 *IF(AND($E$18<>"",$H$18<>""),IF($E$18=$H$18,VLOOKUP($O$19, Price!$J:$L, MATCH(TRIM($E$18), Price!$J$1:$L$1, 0), FALSE),""),IF($E$18<>"",VLOOKUP($O$19, Price!$J:$L, MATCH(TRIM($E$18), Price!$J$1:$L$1, 0), FALSE),IF($H$18<>"",VLOOKUP($O$19, Price!$J:$L, MATCH(TRIM($H$18), Price!$J$1:$L$1, 0), FALSE),"")))) | T36: =IF(F36="","",SUM(O36:Q36)*I36*L36) | V36: =IF(AND(S36="",T36="", U36=""), "", SUM(S36:U36)) | X36: =IF(V36="","",V36-W36) | Y36: =IF(V36 = (S36 +T36 + U36), "✅", "❌") -> #VALUE!
D37: Total Duration of Stay | G37: 46184 | H37: =IF(AND(ISNUMBER(G37), ISNUMBER(I37)), G37 + I37, "") -> 46190 | I37: =SUM(I26:I36) -> 6 | O37: =SUM(O26:O36) -> 0 | P37: =SUM(P26:P36) -> 35050 | Q37: =SUM(Q26:Q36) -> 0 | R37: =SUM(R26:R36) -> 0 | S37: {=S26*VALUE(INDEX(_xlfn.TEXTSPLIT(H17, " "), 1))} -> 37100 | T37: =SUM(T26:T36) -> 35050 | U37: =SUM(U26:U36) -> 0 | V37: =SUM(S37:U37) -> 72150 | W37: =SUM(W26:W36) -> 52603 | X37: =SUM(X26:X36) -> 27750 | Y37: =IF(V37 = (S37 +T37 + U37), "✅", "❌") -> ✅ | Z37: =SUM(Z26:Z36) -> 111600 | AA37: =SUM(AA26:AA36) -> 58997
N38: Total Cost | O38: =IF(O37=0, "",O37/2) | P38: =IF(P37=0, "",P37/3) -> 11683.333 | Q38: =IF(Q37=0, "",Q37/4) | R38: =SUM(S37:U37) -> 72150 | U38: =IF(V37 = (S37+T37 + U37), "✅", "❌") -> ✅ | Z38: =V41-Z37 -> 19400
D39: Package Price Details | AB39: =AB38-AB37-AB28-AB27-AB26 -> #VALUE! | AC39: =AC38-AC37-AC28-AC27-AC26 -> 0
D40: Pax Type | F40: Total Guest | H40: Cost Per Guest Per Night | K40: Grand Total Cost | N40: Total Cost
D41: Total Adult or Child | F41: =K16-K17 -> 3 | H41: =(K41/F41)/$I$37 -> 4048.4167 | K41: =(N41*$O$21)+N41 -> 72871.5 | N41: =(S37/$F$43)*F41+T37 -> 72150 | V41: 131000 | W41: 20001 | X41: =V41-W41 -> 110999
D42: Cost of Extra Adult Passenger/Child | F42: =$K$17 -> 0 | H42: =IF(F42=0, 0, K42/F42/$I$37) -> 0 | K42: =(N42*$O$21)+N42 -> 0 | N42: =(S37/$F$43)*F42+U37 -> 0
D43: Final Package Amount | F43: =SUM(F41:F42) -> 3 | H43: =K43/(F43*$I$37) -> 4048.4167 | K43: =K41+K42 -> 72871.5 | N43: =N41+N42 -> 72150
D44: Per Passenger Cost | H44: =K43/F43 -> 24290.5 | N44: =K43-N43 -> 721.5
D46: Packages Inclusion | H46: Packages Exclusion
D47: =IF(I37<>"","1. " & TEXT(I37,"00") & " nights’ stay at the hotels specified in the itinerary.","") -> 1. 06 nights’ stay at the hotels specified in the itinerary. | H47: 1. Extra Meals, Drinks & things not mentioned in including.
D48: =IF(COUNTA(K26:K36)=0, "", "2. Meals included: " & TEXT((COUNTIF(K26:K36,"CP")+COUNTIF(K26:K36,"MAP")+COUNTIF(K26:K36,"AP"))*I26,"00") & " breakfast" & IF(COUNTIF(K26:K36,"AP")>0, ", " & TEXT(COUNTIF(K26:K36,"AP")*I26, "00") & " lunch", "") & IF((COUNTIF(K26:K36,"MAP")+COUNTIF(K26:K36,"AP"))>0, " and " & TEXT((COUNTIF(K26:K36,"MAP")+COUNTIF(K26:K36,"AP"))*I26,"00") & " dinner", "") & IF(COUNTIF(K26:K36,"EP")=COUNTA(K26:K36), "No meals", "") & ", as per the selected meal plan.") -> 2. Meals included: 05 breakfast and 05 dinner, as per the selected meal plan. | H48: 2. Guide / Entry Fees / Cable Car / Ropeway
D49: {=_xlfn.LET(_xlpm.list, _xlfn._xlws.FILTER(Q16:Q22,(Q16:Q22<>"")*(Q16:Q22<>"NA"),""),_xlpm.n,SUMPRODUCT(--(_xlpm.list<>"")),_xlpm.veh, O19,IF(OR(_xlpm.veh="",_xlpm.veh="NA"),"","3. All transfers and sightseeing as per the itinerary" & IF(_xlpm.n=0,"", " (" & IF(_xlpm.n=1, INDEX(_xlpm.list,1),_xlfn.TEXTJOIN(", ",TRUE,INDEX(_xlpm.list,_xlfn.SEQUENCE(_xlpm.n-1))) & " and " & INDEX(_xlpm.list,_xlpm.n) ) & ")" ) & " by " & _xlpm.veh & ". Air-conditioned vehicle provided in non-hill areas only." ) )} -> 3. All transfers and sightseeing as per the itinerary by Ertiga 7 Seater. Air-conditioned vehicle provided in non-hill areas only. | H49: 3. Adventure activities: Rafting / Bungy / Paragliding / Rope Activities / Boat Ride / Jungle Safari.
D50: {=_xlfn.LET( _xlpm.activity, Q16, _xlpm.desc, IF(OR(_xlpm.activity="", _xlpm.activity="NA"), "", _xlfn.XLOOKUP(TRIM(_xlpm.activity), TRIM(#REF!),#REF!, "")), IF(_xlpm.desc="", "", "4. " & _xlpm.desc) )} | H50: 4. Air / Train / Helicopter Tickets unless mentioned.
D51: {=_xlfn.LET( _xlpm.activity, Q17, _xlpm.desc, IF(OR(_xlpm.activity="", _xlpm.activity="NA"), "", _xlfn.XLOOKUP(TRIM(_xlpm.activity), TRIM(#REF!),#REF!, "")), IF(_xlpm.desc="", "", "5. " & _xlpm.desc) )} | H51: 5. Horse / Porter etc for Trekking.
D52: {=_xlfn.LET( _xlpm.activity, Q18, _xlpm.desc, IF(OR(_xlpm.activity="", _xlpm.activity="NA"), "", _xlfn.XLOOKUP(TRIM(_xlpm.activity), TRIM(#REF!),#REF!, "")), IF(_xlpm.desc="", "", "5. " & _xlpm.desc) )} | H52: 6. Travel & Medical Insurance.
D53: {=_xlfn.LET( _xlpm.activity, Q19, _xlpm.desc, IF(OR(_xlpm.activity="", _xlpm.activity="NA"), "", _xlfn.XLOOKUP(TRIM(_xlpm.activity), TRIM(#REF!),#REF!, "")), IF(_xlpm.desc="", "", "5. " & _xlpm.desc) )}
D54: {=_xlfn.LET( _xlpm.activity, Q20, _xlpm.desc, IF(OR(_xlpm.activity="", _xlpm.activity="NA"), "", _xlfn.XLOOKUP(TRIM(_xlpm.activity), TRIM(#REF!),#REF!, "")), IF(_xlpm.desc="", "", "5. " & _xlpm.desc) )}
D55: {=_xlfn.LET( _xlpm.activity, Q21, _xlpm.desc, IF(OR(_xlpm.activity="", _xlpm.activity="NA"), "", _xlfn.XLOOKUP(TRIM(_xlpm.activity), TRIM(#REF!),#REF!, "")), IF(_xlpm.desc="", "", "5. " & _xlpm.desc) )}
D56: {=_xlfn.LET( _xlpm.activity, Q22, _xlpm.desc, IF(OR(_xlpm.activity="", _xlpm.activity="NA"), "", _xlfn.XLOOKUP(TRIM(_xlpm.activity), TRIM(#REF!),#REF!, "")), IF(_xlpm.desc="", "", "5. " & _xlpm.desc) )}
D57: KINDLY NOTE ALL THE PICK UP IS ON SIC BASIS & LOCATION ARE (Baga, Calangute, Candolim & Arpora)
D58: FOLLOWING YOUR DAY WISE SCHEDULED ITINERARY FOR THIS TOUR.
D60: Day 1: | E60: Transfers from Bhuj to Rann Utsav – The Tent City, Dhordo
D62: =_xlfn.XLOOKUP(E$60,'Day Wise Exursion'!$B:$B,'Day Wise Exursion'!$C:$C) -> #N/A
D64: Day 2: | E64: Kala Dungar & Sunrise Point
D66: =_xlfn.XLOOKUP(E$64,'Day Wise Exursion'!$B:$B,'Day Wise Exursion'!$C:$C) -> #N/A
D68: Day 3: | E68: Departure & Bhuj Sightseeing
D70: =_xlfn.XLOOKUP(E$68,'Day Wise Exursion'!$B:$B,'Day Wise Exursion'!$C:$C) -> #N/A
D72: Day 4: | E72: Kala Dungar & Sunrise Point
D74: =_xlfn.XLOOKUP(E$72,'Day Wise Exursion'!$B:$B,'Day Wise Exursion'!$C:$C) -> #N/A
D76: Day 5:
D78: =_xlfn.XLOOKUP(E$76,'Day Wise Exursion'!$B:$B,'Day Wise Exursion'!$C:$C) -> 0
D80: Day 6:
D82: =_xlfn.XLOOKUP(E$80,'Day Wise Exursion'!$B:$B,'Day Wise Exursion'!$C:$C) -> 0
D84: Day 7:
D86: =_xlfn.XLOOKUP(E$84,'Day Wise Exursion'!$B:$B,'Day Wise Exursion'!$C:$C) -> 0
D88: Day 8:
D90: =_xlfn.XLOOKUP(E$88,'Day Wise Exursion'!$B:$B,'Day Wise Exursion'!$C:$C) -> 0
D92: Day 9:
D94: =_xlfn.XLOOKUP(E$92,'Day Wise Exursion'!$B:$B,'Day Wise Exursion'!$C:$C) -> 0
D96: Day 10:
D98: =_xlfn.XLOOKUP(E$96,'Day Wise Exursion'!$B:$B,'Day Wise Exursion'!$C:$C) -> 0
D100: Terms and Conditions for Sale of Tour Packages
D102: 1. All quotations provided by the company are subject to availability of hotel rooms/cruise cabins, services and/or flights at the time of processing the reservation. At the time of reservation, the prices might change without prior notice.
D104: 2. All services provided by the Company are subject to full realization of payment before departure.
D106: 3. Bookings for Travel inside 30 Days or sooner 100% Full payment required.
D108: 4. This quote is valid till 48 hours of issuance date
D110: Terms and Conditions

Sheet Raw
B2: Destination | C2: Key | D2: Hotel Code | E2: Hotel / Resort Name | F2: Room Type | G2: Double EP | H2: Double CP | I2: Double MAP | J2: Triple EP | K2: Triple CP | L2: Triple MAP | M2: Quad EP | N2: Quad CP | O2: Quad MAP
B3: Janki Chatti | C3: =B3&F3 -> Janki ChattiBudget | E3: Hotel Santosh | F3: =IF(I3<=2500,"Budget",IF(I3<=4000,"Standard","Premium")) -> Budget | G3: 2000 | I3: 2500 | J3: 2500 | L3: 3500 | M3: 3500 | O3: 5000 | Q3: Price | R3: Remark
B4: Janki Chatti | C4: =B4&F4 -> Janki ChattiBudget | E4: Gaurav Hotel | F4: =IF(I4<=2500,"Budget",IF(I4<=4000,"Standard","Premium")) -> Budget | Q4: 2000-2500 | R4: Budget
B5: Janki Chatti | C5: =B5&F5 -> Janki ChattiBudget | E5: Buransh Homestay | F5: =IF(I5<=2500,"Budget",IF(I5<=4000,"Standard","Premium")) -> Budget | Q5: 2500-4000 | R5: Standard
B6: Janki Chatti | C6: =B6&F6 -> Janki ChattiStandard | E6: AP Residency | F6: =IF(I6<=2500,"Budget",IF(I6<=4000,"Standard","Premium")) -> Standard | G6: 2500 | H6: 2700 | I6: 3200 | J6: 3200 | K6: 3400 | L6: 3900 | M6: 4100 | N6: 4300 | O6: 4800 | Q6: 4000 | R6: Premium
B7: Janki Chatti | C7: =B7&F7 -> Janki ChattiPremium | E7: Blessings Resort Family Cottages (Mountain view with private balcony) | F7: =IF(I7<=2500,"Budget",IF(I7<=4000,"Standard","Premium")) -> Premium | G7: 5000 | H7: 6200 | I7: 7000 | J7: 6800 | K7: 8300 | L7: 9500 | M7: 8600 | N7: 10400 | O7: 12000
B8: Janki Chatti | C8: =B8&F8 -> Janki ChattiPremium | E8: Blessings Resort Deluxe Cottages (Mountain view with private balcony) | F8: =IF(I8<=2500,"Budget",IF(I8<=4000,"Standard","Premium")) -> Premium | G8: 5500 | H8: 6200 | I8: 7000 | J8: 7300 | K8: 8300 | L8: 9500 | M8: 9100 | N8: 10400 | O8: 12000
B9: Janki Chatti | C9: =B9&F9 -> Janki ChattiPremium | E9: Blessings Resort Luxury Cottages (Mountain & River view with private balcony) | F9: =IF(I9<=2500,"Budget",IF(I9<=4000,"Standard","Premium")) -> Premium | G9: 8000 | H9: 9500 | I9: 12000 | J9: 9800 | K9: 11600 | L9: 14500 | M9: 11600 | N9: 13700 | O9: 17000
B10: Janki Chatti | C10: =B10&F10 -> Janki ChattiPremium | E10: Yamunotri Cottages (Classic) | F10: =IF(I10<=2500,"Budget",IF(I10<=4000,"Standard","Premium")) -> Premium | G10: 3480 | H10: 4740 | I10: 6000
B11: Janki Chatti | C11: =B11&F11 -> Janki ChattiPremium | E11: Yamunotri Cottages (Luxury Pine) | F11: =IF(I11<=2500,"Budget",IF(I11<=4000,"Standard","Premium")) -> Premium | G11: 5265 | H11: 6525 | I11: 7785
B12: Janki Chatti | C12: =B12&F12 -> Janki ChattiStandard | E12: Hotel Laxmi Palace | F12: =IF(I12<=2500,"Budget",IF(I12<=4000,"Standard","Premium")) -> Standard | G12: 2600 | H12: 2800 | I12: 3200 | J12: 2700 | K12: 3000 | L12: 3600 | M12: 3600 | N12: 4000 | O12: 4800
B13: Kedarnath | C13: =B13&F13 -> KedarnathPremium | E13: Rudra Camp Kedarnath | F13: =IF(I13<=2500,"Budget",IF(I13<=4000,"Standard","Premium")) -> Premium | I13: 6500 | L13: 7500 | O13: 8000
B14: Kedarnath | C14: =B14&F14 -> KedarnathBudget | E14: Rudra Hotel | F14: =IF(I14<=2500,"Budget",IF(I14<=4000,"Standard","Premium")) -> Budget | J14: 7500 | M14: 15000
B15: Kedarnath | C15: =B15&F15 -> KedarnathBudget | E15: Hotel New Pandey Inn | F15: =IF(I15<=2500,"Budget",IF(I15<=4000,"Standard","Premium")) -> Budget | G15: 1200 | H15: 1600 | I15: 2000 | J15: 1800 | K15: 2400 | L15: 3000 | M15: 2400 | O15: 4000
B16: Kedarnath | C16: =B16&F16 -> KedarnathPremium | E16: Parmeshwari Kedarnath (Only 20mts Kedarnath Temple) | F16: =IF(I16<=2500,"Budget",IF(I16<=4000,"Standard","Premium")) -> Premium | I16: 7000 | L16: 10500 | O16: 12500
B17: Janki Chatti | C17: =B17&F17 -> Janki ChattiBudget | E17: Blessings Resort Dormitory | F17: =IF(I17<=2500,"Budget",IF(I17<=4000,"Standard","Premium")) -> Budget | G17: 1200 | H17: 1600 | I17: 2400 | J17: 1800 | K17: 2400 | L17: 3600 | M17: 2400 | N17: 3200 | O17: 4800
B18: Uttarkashi | C18: =B18&F18 -> UttarkashiStandard | E18: Hotel Ankit Palace | F18: =IF(I18<=2500,"Budget",IF(I18<=4000,"Standard","Premium")) -> Standard | G18: 2000 | H18: 2500 | I18: 3000 | J18: 3000 | K18: 3500 | L18: 4000 | M18: 4500 | N18: 4500 | O18: 5000
B19: Uttarkashi | C19: =B19&F19 -> UttarkashiStandard | E19: Hotel Sravasti | F19: =IF(I19<=2500,"Budget",IF(I19<=4000,"Standard","Premium")) -> Standard | G19: 2500 | H19: 3000 | I19: 3600 | J19: 3400 | K19: 4000 | L19: 4800 | O19: 5500
B20: Uttarkashi | C20: =B20&F20 -> UttarkashiBudget | E20: Hotel maharishi | F20: =IF(I20<=2500,"Budget",IF(I20<=4000,"Standard","Premium")) -> Budget
B21: Uttarkashi | C21: =B21&F21 -> UttarkashiPremium | E21: Shivlinga Resort Deluxe Non AC | F21: =IF(I21<=2500,"Budget",IF(I21<=4000,"Standard","Premium")) -> Premium | G21: 5800 | H21: 6400 | I21: 7700 | J21: 3700 | K21: 4000 | L21: 5200 | M21: 4000 | N21: 4400 | O21: 6000
B22: Uttarkashi | C22: =B22&F22 -> UttarkashiStandard | E22: Maa Saraswati Hotel | F22: =IF(I22<=2500,"Budget",IF(I22<=4000,"Standard","Premium")) -> Standard | G22: 2400 | H22: 2800 | I22: 3200 | J22: 3000 | K22: 3600 | L22: 4200 | M22: 3600 | N22: 4400 | O22: 5200
B23: Uttarkashi | C23: =B23&F23 -> UttarkashiStandard | E23: Hotel Sahaj Villa | F23: =IF(I23<=2500,"Budget",IF(I23<=4000,"Standard","Premium")) -> Standard | G23: 2500 | H23: 2800 | I23: 3500 | J23: 3300 | K23: 3750 | L23: 4800 | M23: 4000 | N23: 4600 | O23: 6000
B24: Uttarkashi | C24: =B24&F24 -> UttarkashiBudget | E24: Osho Zenganga Commune | F24: =IF(I24<=2500,"Budget",IF(I24<=4000,"Standard","Premium")) -> Budget | G24: 1400 | I24: 2000 | J24: 2500 | L24: 3000 | M24: 3500 | O24: 4000
B25: Uttarkashi | C25: =B25&F25 -> UttarkashiStandard | E25: Hotel Narayan Palace | F25: =IF(I25<=2500,"Budget",IF(I25<=4000,"Standard","Premium")) -> Standard | G25: 2500 | H25: 2900 | I25: 3500 | J25: 3300 | K25: 3900 | L25: 4800 | M25: 4100 | N25: 4900 | O25: 6100
B26: Sonprayag | C26: =B26&F26 -> SonprayagBudget | E26: Shri Narayan Touris Lodge & Chandica Hotel | F26: =IF(I26<=2500,"Budget",IF(I26<=4000,"Standard","Premium")) -> Budget | G26: 600 | I26: 850
B27: Sonprayag | C27: =B27&F27 -> SonprayagStandard | E27: Kailashpati Resort | F27: =IF(I27<=2500,"Budget",IF(I27<=4000,"Standard","Premium")) -> Standard | G27: 2800 | I27: 3400 | J27: 3300 | L27: 4200
B28: Sitapur | C28: =B28&F28 -> SitapurStandard | E28: Hotel Blue Pine | F28: =IF(I28<=2500,"Budget",IF(I28<=4000,"Standard","Premium")) -> Standard | G28: 2200 | I28: 3000 | J28: 3000 | L28: 4200 | M28: 4100 | O28: 5600
B29: Sitapur | C29: =B29&F29 -> SitapurPremium | E29: Phulwari Resort Swiss Cottage | F29: =IF(I29<=2500,"Budget",IF(I29<=4000,"Standard","Premium")) -> Premium | G29: 3500 | H29: 4000 | I29: 4800 | J29: 4500 | K29: 5250 | L29: 5700
B30: Sitapur | C30: =B30&F30 -> SitapurStandard | E30: Namami Gange | F30: =IF(I30<=2500,"Budget",IF(I30<=4000,"Standard","Premium")) -> Standard | G30: 2500 | H30: 2900 | I30: 3200 | J30: 3000 | K30: 3600 | L30: 3900 | M30: 3600 | N30: 4400 | O30: 4800
B31: Sitapur | C31: =B31&F31 -> SitapurStandard | E31: Abhishek Hotel | F31: =IF(I31<=2500,"Budget",IF(I31<=4000,"Standard","Premium")) -> Standard | G31: 3100 | H31: 3300 | I31: 3500 | J31: 3500 | K31: 3700 | L31: 3900 | M31: 4300 | N31: 4500 | O31: 4700
B32: Sitapur | C32: =B32&F32 -> SitapurBudget | E32: Shiv Manohar | F32: =IF(I32<=2500,"Budget",IF(I32<=4000,"Standard","Premium")) -> Budget | G32: 2000 | I32: 2500 | J32: 2500 | L32: 3200 | M32: 3000 | O32: 4000
B33: Rudraprayag | C33: =B33&F33 -> RudraprayagStandard | E33: Hotel Battalion 10 Non Ac Deluxe | F33: =IF(I33<=2500,"Budget",IF(I33<=4000,"Standard","Premium")) -> Standard | G33: 2400 | I33: 3200 | J33: 3300 | L33: 4400 | M33: 4000 | O33: 5200
B34: Rudraprayag | C34: =B34&F34 -> RudraprayagStandard | E34: Hotel Battalion 10 AC Super Deluxe | F34: =IF(I34<=2500,"Budget",IF(I34<=4000,"Standard","Premium")) -> Standard | G34: 3000 | I34: 3800 | J34: 3900 | L34: 5000 | M34: 4600 | O34: 5800
B35: Rudraprayag | C35: =B35&F35 -> RudraprayagPremium | E35: Hotel Battalion 10 AC Premimum | F35: =IF(I35<=2500,"Budget",IF(I35<=4000,"Standard","Premium")) -> Premium | G35: 3600 | I35: 4400
B36: Rudraprayag | C36: =B36&F36 -> RudraprayagPremium | E36: Hotel Blue Orchid | F36: =IF(I36<=2500,"Budget",IF(I36<=4000,"Standard","Premium")) -> Premium | G36: 3500 | H36: 4200 | I36: 5000 | J36: 4600 | K36: 5000 | L36: 6000 | M36: 5000 | N36: 5800 | O36: 7000
B37: Pipalkoti | C37: =B37&F37 -> PipalkotiPremium | E37: Hotel Vinayak Superior Room | F37: =IF(I37<=2500,"Budget",IF(I37<=4000,"Standard","Premium")) -> Premium | G37: 3000 | H37: 3400 | I37: 4200 | J37: 3500 | K37: 4100 | L37: 5300 | M37: 5600 | N37: 6400 | O37: 8000
B38: Pipalkoti | C38: =B38&F38 -> PipalkotiPremium | E38: Hotel Vinayak Executive Room | F38: =IF(I38<=2500,"Budget",IF(I38<=4000,"Standard","Premium")) -> Premium | G38: 3500 | H38: 3900 | I38: 4700 | M38: 5600 | N38: 6400 | O38: 8000
B39: Pipalkoti | C39: =B39&F39 -> PipalkotiStandard | E39: Hotel Comfort INN | F39: =IF(I39<=2500,"Budget",IF(I39<=4000,"Standard","Premium")) -> Standard | I39: 3500 | L39: 4500 | O39: 5600
B40: Pipalkoti | C40: =B40&F40 -> PipalkotiStandard | E40: Hotel Ajay Palace | F40: =IF(I40<=2500,"Budget",IF(I40<=4000,"Standard","Premium")) -> Standard | G40: 2500 | I40: 3300 | J40: 3000 | L40: 4200 | M40: 4000 | O40: 5600
B41: Pipalkoti | C41: =B41&F41 -> PipalkotiStandard | E41: Ajay Palace Pipalkoti | F41: =IF(I41<=2500,"Budget",IF(I41<=4000,"Standard","Premium")) -> Standard | G41: 2500 | I41: 3200 | J41: 3000 | L41: 4200 | M41: 4000 | O41: 5600
B42: Pipalkoti | C42: =B42&F42 -> PipalkotiPremium | E42: Hotel Le Meadows | F42: =IF(I42<=2500,"Budget",IF(I42<=4000,"Standard","Premium")) -> Premium | G42: 6000 | H42: 6500 | I42: 7000 | J42: 6800 | K42: 7050 | L42: 7400
B43: Badarinath | C43: =B43&F43 -> BadarinathPremium | E43: Badri Palace | F43: =IF(I43<=2500,"Budget",IF(I43<=4000,"Standard","Premium")) -> Premium | G43: 4000 | H43: 4400 | I43: 4600 | J43: 3600 | K43: 4500 | L43: 4800 | M43: 4800 | N43: 6000 | O43: 6400
B44: Sitapur | C44: =B44&F44 -> SitapurPremium | E44: New Basera | F44: =IF(I44<=2500,"Budget",IF(I44<=4000,"Standard","Premium")) -> Premium | G44: 2940 | H44: 3360 | I44: 4043 | J44: 3675 | K44: 4200 | L44: 5330 | M44: 4725 | N44: 5460 | O44: 6930
B45: Barkot | C45: =B45&F45 -> BarkotStandard | E45: Hotel Aditya Palace | F45: =IF(I45<=2500,"Budget",IF(I45<=4000,"Standard","Premium")) -> Standard | G45: 2000 | H45: 2300 | I45: 3000 | J45: 2500 | K45: 2950 | L45: 4000 | M45: 3000
B46: Janki Chatti | C46: =B46&F46 -> Janki ChattiBudget | E46: Shiv Shakti Eco Resort | F46: =IF(I46<=2500,"Budget",IF(I46<=4000,"Standard","Premium")) -> Budget | G46: 2200 | I46: 2500 | J46: 3000 | L46: 4200 | M46: 4000 | O46: 5600
B47: Janki Chatti | C47: =B47&F47 -> Janki ChattiBudget | E47: Hotel Aakashdeep | F47: =IF(I47<=2500,"Budget",IF(I47<=4000,"Standard","Premium")) -> Budget | G47: 2000
B48: Janki Chatti | C48: =B48&F48 -> Janki ChattiBudget | E48: Gaurav Hotel | F48: =IF(I48<=2500,"Budget",IF(I48<=4000,"Standard","Premium")) -> Budget
B49: Barkot | C49: =B49&F49 -> BarkotBudget | E49: Madhuvan Guest House | F49: =IF(I49<=2500,"Budget",IF(I49<=4000,"Standard","Premium")) -> Budget | G49: 1000 | I49: 2000 | J49: 1500 | L49: 3500 | M49: 2500 | O49: 4500
B50: Barkot | C50: =B50&F50 -> BarkotStandard | E50: Hotel Pinewood (The om Hotels) | F50: =IF(I50<=2500,"Budget",IF(I50<=4000,"Standard","Premium")) -> Standard | G50: 2500 | H50: 2900 | I50: 3500 | J50: 3300 | K50: 3900 | L50: 4800 | M50: 4100 | N50: 4900 | O50: 6100
B51: Barkot | C51: =B51&F51 -> BarkotStandard | E51: Hotel Poll Star Inn (The om Hotels) | F51: =IF(I51<=2500,"Budget",IF(I51<=4000,"Standard","Premium")) -> Standard | G51: 3000 | H51: 3400 | I51: 4000 | M51: 5000 | N51: 5800 | O51: 7000
B52: Pandukeshwar | C52: =B52&F52 -> PandukeshwarStandard | E52: Hotel Raghveer | F52: =IF(I52<=2500,"Budget",IF(I52<=4000,"Standard","Premium")) -> Standard | G52: 3000 | H52: 3400 | I52: 4000 | J52: 4000 | K52: 4600 | L52: 5500 | M52: 5000 | N52: 5800 | O52: 7000
B53: Barkot | C53: =B53&F53 -> BarkotPremium | E53: Hotel Mangalam | F53: =IF(I53<=2500,"Budget",IF(I53<=4000,"Standard","Premium")) -> Premium | G53: 3500 | I53: 5000 | J53: 5000 | L53: 7000
B54: Barkot | C54: =B54&F54 -> BarkotBudget | E54: Hotel Vijay Residency | F54: =IF(I54<=2500,"Budget",IF(I54<=4000,"Standard","Premium")) -> Budget | G54: 1600 | I54: 2200 | J54: 2000 | L54: 3000 | M54: 2800 | O54: 4000
B55: Sitapur | C55: =B55&F55 -> SitapurStandard | E55: Hotel Namami Gange | F55: =IF(I55<=2500,"Budget",IF(I55<=4000,"Standard","Premium")) -> Standard | G55: 2500 | H55: 2900 | I55: 3200 | J55: 3000 | K55: 3600 | L55: 3900 | M55: 3600 | N55: 4400 | O55: 4800
B56: Badarinath | C56: =B56&F56 -> BadarinathPremium | E56: Badri Palace by Namami Gange | F56: =IF(I56<=2500,"Budget",IF(I56<=4000,"Standard","Premium")) -> Premium | G56: 4000 | H56: 4400 | I56: 4600 | J56: 3600 | K56: 4500 | L56: 4800 | M56: 4800 | N56: 6000 | O56: 6400
B57: Sitapur | C57: =B57&F57 -> SitapurBudget | E57: Hotel Shiv Manohar | F57: =IF(I57<=2500,"Budget",IF(I57<=4000,"Standard","Premium")) -> Budget | G57: 2000 | I57: 2500 | J57: 2500 | L57: 3200 | M57: 3000 | O57: 4000
B58: Pipalkoti | C58: =B58&F58 -> PipalkotiStandard | E58: Hotel Bhawani | F58: =IF(I58<=2500,"Budget",IF(I58<=4000,"Standard","Premium")) -> Standard | G58: 2500 | I58: 3200 | J58: 3200 | L58: 4250 | M58: 3600 | O58: 5000
B59: Pipalkoti | C59: =B59&F59 -> PipalkotiStandard | E59: Hotel Devlok | F59: =IF(I59<=2500,"Budget",IF(I59<=4000,"Standard","Premium")) -> Standard | G59: 2000 | I59: 2550 | J59: 2500 | L59: 3050 | M59: 3000 | O59: 3650
B60: Barkot | C60: =B60&F60 -> BarkotStandard | E60: Hotel Sunrise (Raatri Hotels) | F60: =IF(I60<=2500,"Budget",IF(I60<=4000,"Standard","Premium")) -> Standard | G60: 2500 | H60: 2800 | I60: 3200 | J60: 3500 | K60: 3800 | L60: 4400
B61: Kedarnath | C61: =B61&F61 -> KedarnathPremium | E61: Raatri Hotels | F61: =IF(I61<=2500,"Budget",IF(I61<=4000,"Standard","Premium")) -> Premium | G61: 5000 | I61: 6000 | J61: 7500 | L61: 9000 | M61: 10000 | O61: 12000
B62: Badarinath | C62: =B62&F62 -> BadarinathStandard | E62: Hotel Himgiri Badrinath | F62: =IF(I62<=2500,"Budget",IF(I62<=4000,"Standard","Premium")) -> Standard | G62: 3000 | H62: 3500 | I62: 4000 | J62: 4200 | K62: 5200 | L62: 5800 | M62: 6000 | N62: 7200 | O62: 7600
B63: Rudraprayag | C63: =B63&F63 -> RudraprayagPremium | E63: Raatri Hotel Bhanu Palace | F63: =IF(I63<=2500,"Budget",IF(I63<=4000,"Standard","Premium")) -> Premium | G63: 3500 | H63: 4000 | I63: 4800
B64: Pipalkoti | C64: =B64&F64 -> PipalkotiStandard | E64: Hotel BALBEER PALACE | F64: =IF(I64<=2500,"Budget",IF(I64<=4000,"Standard","Premium")) -> Standard | I64: 3400 | L64: 4500 | O64: 5600
B65: Rudraprayag | C65: =B65&F65 -> RudraprayagPremium | E65: Hotel Samrat Resort | F65: =IF(I65<=2500,"Budget",IF(I65<=4000,"Standard","Premium")) -> Premium | G65: 4300 | H65: 5000 | I65: 6000 | J65: 5300 | K65: 6500 | L65: 8000 | M65: 8200 | N65: 9400 | O65: 11000
B66: Uttarkashi | C66: =B66&F66 -> UttarkashiPremium | E66: Anand Ganga Ganga View Rooms | F66: =IF(I66<=2500,"Budget",IF(I66<=4000,"Standard","Premium")) -> Premium | H66: 7500 | I66: 8500 | K66: 9000 | L66: 10500 | N66: 10500 | O66: 13000
B67: Uttarkashi | C67: =B67&F67 -> UttarkashiStandard | E67: Anand Ganga | F67: =IF(I67<=2500,"Budget",IF(I67<=4000,"Standard","Premium")) -> Standard | H67: 2850 | I67: 3650 | K67: 4050 | L67: 5250
B68: Uttarkashi | C68: =B68&F68 -> UttarkashiStandard | E68: Hotel Suryansh | F68: =IF(I68<=2500,"Budget",IF(I68<=4000,"Standard","Premium")) -> Standard | G68: 3000 | H68: 3400 | I68: 4000 | J68: 4000 | K68: 4600 | L68: 5500
B69: Sitapur | C69: =B69&F69 -> SitapurPremium | E69: Hotel New Mandakini River Resort | F69: =IF(I69<=2500,"Budget",IF(I69<=4000,"Standard","Premium")) -> Premium | G69: 3500 | H69: 3800 | I69: 4500 | J69: 5000 | K69: 5400 | L69: 6000 | M69: 6200 | N69: 6600 | O69: 7200
B70: Sonprayag | C70: =B70&F70 -> SonprayagPremium | E70: Kedar Hill Resort | F70: =IF(I70<=2500,"Budget",IF(I70<=4000,"Standard","Premium")) -> Premium | G70: 2500 | H70: 3600 | I70: 4500 | J70: 2800 | K70: 4000 | L70: 5000 | M70: 3200 | N70: 4600 | O70: 5800
B71: Sitapur | C71: =B71&F71 -> SitapurPremium | E71: Shivalik Valley Resorts | F71: =IF(I71<=2500,"Budget",IF(I71<=4000,"Standard","Premium")) -> Premium | G71: 5200 | H71: 5800 | I71: 6600 | J71: 6500 | K71: 7400 | L71: 8600 | M71: 7800 | N71: 9000 | O71: 10600
B72: Sonprayag | C72: =B72&F72 -> SonprayagStandard | E72: Narayan Valley Resort | F72: =IF(I72<=2500,"Budget",IF(I72<=4000,"Standard","Premium")) -> Standard | G72: 2500 | I72: 3000 | M72: 4500
B73: Sonprayag | C73: =B73&F73 -> SonprayagStandard | E73: Neelansh Resort | F73: =IF(I73<=2500,"Budget",IF(I73<=4000,"Standard","Premium")) -> Standard | I73: 3200 | L73: 4000 | O73: 4800
B74: Sitapur | C74: =B74&F74 -> SitapurStandard | E74: Shri Narayan Resort | F74: =IF(I74<=2500,"Budget",IF(I74<=4000,"Standard","Premium")) -> Standard | G74: 2000 | I74: 2800 | J74: 2700 | L74: 3600 | M74: 3200 | O74: 4000
B75: Barkot | C75: =B75&F75 -> BarkotStandard | E75: RJ Anandam Resort | F75: =IF(I75<=2500,"Budget",IF(I75<=4000,"Standard","Premium")) -> Standard | I75: 3000 | L75: 4000 | O75: 5000
B76: Kedarnath | C76: =B76&F76 -> KedarnathPremium | E76: Marwar House Hotel | F76: =IF(I76<=2500,"Budget",IF(I76<=4000,"Standard","Premium")) -> Premium | G76: 5400 | I76: 6000 | J76: 8100 | L76: 9000 | M76: 10800 | O76: 12000
B77: Guptkashi | C77: =B77&F77 -> GuptkashiBudget | E77: Hotel Mount Hills | F77: =IF(I77<=2500,"Budget",IF(I77<=4000,"Standard","Premium")) -> Budget | L77: 3600
B78: Barkot | C78: =B78&F78 -> BarkotStandard | E78: Yamunotri Darshan Resort | F78: =IF(I78<=2500,"Budget",IF(I78<=4000,"Standard","Premium")) -> Standard | I78: 2800 | L78: 3300
B79: Barkot | C79: =B79&F79 -> BarkotStandard | E79: Hotel Om Shivaay Inn | F79: =IF(I79<=2500,"Budget",IF(I79<=4000,"Standard","Premium")) -> Standard | I79: 2800 | L79: 3300
B80: Kedarnath | C80: =B80&F80 -> KedarnathBudget | E80: BIKANER HOUSE | F80: =IF(I80<=2500,"Budget",IF(I80<=4000,"Standard","Premium")) -> Budget
B81: Chopta | C81: =B81&F81 -> ChoptaStandard | E81: Alpine Adventure Camp | F81: =IF(I81<=2500,"Budget",IF(I81<=4000,"Standard","Premium")) -> Standard | I81: 3200 | L81: 4800 | O81: 6400
B82: Joshimath | C82: =B82&F82 -> JoshimathPremium | E82: The Tattva Resort | F82: =IF(I82<=2500,"Budget",IF(I82<=4000,"Standard","Premium")) -> Premium | G82: 6510 | H82: 7245 | I82: 10266
B83: Rishikesh | C83: =B83&F83 -> RishikeshPremium | E83: DLS The Classio | F83: =IF(I83<=2500,"Budget",IF(I83<=4000,"Standard","Premium")) -> Premium | G83: 4500 | H83: 5000 | I83: 5500
B84: Chopta | C84: =B84&F84 -> ChoptaStandard | E84: paradise Adventure camp | F84: =IF(I84<=2500,"Budget",IF(I84<=4000,"Standard","Premium")) -> Standard | H84: 2400 | I84: 2800 | K84: 3000 | L84: 3600 | N84: 4000 | O84: 4800
B85: Harsil | C85: =B85&F85 -> HarsilPremium | E85: Nelangana Resort Pemium Room | F85: =IF(I85<=2500,"Budget",IF(I85<=4000,"Standard","Premium")) -> Premium | G85: 5900 | H85: 6500 | I85: 7300 | J85: 6500 | K85: 7500 | L85: 8800
B86: Harsil | C86: =B86&F86 -> HarsilPremium | E86: Prakriti Retreat Premium Room | F86: =IF(I86<=2500,"Budget",IF(I86<=4000,"Standard","Premium")) -> Premium | G86: 7000 | H86: 8200 | I86: 9600 | J86: 8800 | K86: 10600 | L86: 12700
B87: Harsil | C87: =B87&F87 -> HarsilPremium | E87: Prakriti Retreat Standard | F87: =IF(I87<=2500,"Budget",IF(I87<=4000,"Standard","Premium")) -> Premium | G87: 5000 | H87: 6200 | I87: 7600 | J87: 6800 | K87: 8600 | L87: 10700 | M87: 11000 | N87: 13400 | O87: 16200
B88: Harsil | C88: =B88&F88 -> HarsilPremium | E88: Nelangana Resort Deluxe Room | F88: =IF(I88<=2500,"Budget",IF(I88<=4000,"Standard","Premium")) -> Premium | G88: 4800 | H88: 5400 | I88: 6200 | J88: 5400 | K88: 6400 | L88: 7700
B89: Netala | C89: =B89&F89 -> NetalaPremium | E89: Hotel Bhagirathi Residency Deluxe Room | F89: =IF(I89<=2500,"Budget",IF(I89<=4000,"Standard","Premium")) -> Premium | G89: 2800 | I89: 4200 | J89: =RAW[[#This Row],[Double EP]]+1680 -> 4480
B90: Netala | C90: =B90&F90 -> NetalaPremium | E90: Hotel Bhagirathi Residency Super Deluxe Room (Non-AC) | F90: =IF(I90<=2500,"Budget",IF(I90<=4000,"Standard","Premium")) -> Premium | G90: 4000 | I90: 5100 | J90: =RAW[[#This Row],[Double EP]]+1344 -> 5344
B91: Netala | C91: =B91&F91 -> NetalaPremium | E91: Hotel Bhagirathi Residency Super Deluxe Room (AC) | F91: =IF(I91<=2500,"Budget",IF(I91<=4000,"Standard","Premium")) -> Premium | G91: 4500 | I91: 5600 | J91: =RAW[[#This Row],[Double EP]]+1344 -> 5844
B92: Harsil | C92: =B92&F92 -> HarsilPremium | E92: Hotel Royal Hillcrest | F92: =IF(I92<=2500,"Budget",IF(I92<=4000,"Standard","Premium")) -> Premium | I92: 4500 | L92: 5500
B93: Sitapur | C93: =B93&F93 -> SitapurPremium | E93: Phulwari Resort Deluxe Room | F93: =IF(I93<=2500,"Budget",IF(I93<=4000,"Standard","Premium")) -> Premium | G93: 6600 | H93: 6500 | I93: 8500 | J93: =RAW[[#This Row],[Double EP]]+1000 -> 7600 | K93: =RAW[[#This Row],[Double CP]]+1250 -> 7750 | L93: =RAW[[#This Row],[Double MAP]]+1650 -> 10150
B94: Sitapur | C94: =B94&F94 -> SitapurPremium | E94: Phulwari Resort Premium Room | F94: =IF(I94<=2500,"Budget",IF(I94<=4000,"Standard","Premium")) -> Premium | G94: 7500 | H94: 8000 | I94: 8800 | J94: =RAW[[#This Row],[Double EP]]+1000 -> 8500 | K94: =RAW[[#This Row],[Double CP]]+1250 -> 9250 | L94: =RAW[[#This Row],[Double MAP]]+1650 -> 10450
B95: Sitapur | C95: =B95&F95 -> SitapurPremium | E95: Phulwari Resort Suite Room 4 Person | F95: =IF(I95<=2500,"Budget",IF(I95<=4000,"Standard","Premium")) -> Premium | G95: 9200 | H95: 10200 | I95: 11800 | M95: 9200 | N95: 10200 | O95: 11800
B96: Sitapur | C96: =B96&F96 -> SitapurPremium | E96: Phulwari Resort Presidential Suite Room | F96: =IF(I96<=2500,"Budget",IF(I96<=4000,"Standard","Premium")) -> Premium | G96: 16000 | H96: 16500 | I96: 17500 | J96: =RAW[[#This Row],[Double EP]]+1000 -> 17000 | K96: =RAW[[#This Row],[Double CP]]+1250 -> 17750 | L96: =RAW[[#This Row],[Double MAP]]+1650 -> 19150
B97: Badarinath | C97: =B97&F97 -> BadarinathPremium | E97: Hotel Neelkanth | F97: =IF(I97<=2500,"Budget",IF(I97<=4000,"Standard","Premium")) -> Premium | I97: 5000 | L97: 6000 | O97: 8000
B98: Badarinath | C98: =B98&F98 -> BadarinathPremium | E98: Badriville Resort | F98: =IF(I98<=2500,"Budget",IF(I98<=4000,"Standard","Premium")) -> Premium | I98: 4500 | L98: 5600 | O98: 6800
B99: Badarinath | C99: =B99&F99 -> BadarinathPremium | E99: Hotel Panchvati Inn | F99: =IF(I99<=2500,"Budget",IF(I99<=4000,"Standard","Premium")) -> Premium | G99: 5500 | H99: 6000 | I99: 6500 | J99: 6500 | K99: 7000 | L99: 7500
B100: Joshimath | C100: =B100&F100 -> JoshimathPremium | E100: Hotel Panchvati Inn Deluxe | F100: =IF(I100<=2500,"Budget",IF(I100<=4000,"Standard","Premium")) -> Premium | G100: 4200 | H100: 4500 | I100: 5200 | J100: 4700 | K100: 5200 | L100: 6200 | M100: 5200 | N100: 5800 | O100: 7800
B101: Joshimath | C101: =B101&F101 -> JoshimathPremium | E101: Hotel Panchvati Inn Premium | F101: =IF(I101<=2500,"Budget",IF(I101<=4000,"Standard","Premium")) -> Premium | G101: 5800 | H101: 6000 | I101: 6200 | J101: 6200 | K101: 6800 | L101: 7500
...

Sheet Price
A1: Name | B1: Value | D1: Name | E1: Value | G1: Extra passenger | J1: Vehicle | K1: Haridwar | L1: Delhi
A2: Hotel Santosh-Budget-Key | B2: Janki ChattiBudget | D2: Hotel Santosh-Budget-Key | E2: Janki ChattiBudget | G2: Extra Adult passenger | J2: Sedan 4 Seater | K2: 4000 | L2: 4200
A3: Hotel Santosh-Budget-Double EP | B3: 2000 | D3: Hotel Santosh-Budget-Double EP | E3: 2000 | G3: Child with bed | J3: Innova | K3: 5700 | L3: 6500
A4: Hotel Santosh-Budget-Double MAP | B4: 2500 | D4: Hotel Santosh-Budget-Double MAP | E4: 2500 | G4: Child without bed | J4: Ertiga 7 Seater | K4: 4800 | L4: 5300
A5: Hotel Santosh-Budget-Triple EP | B5: 2500 | D5: Hotel Santosh-Budget-Triple EP | E5: 2500 | G5: No Extra Bed | J5: Crysta 7 Seater | K5: 6500 | L5: 7000
A6: Hotel Santosh-Budget-Triple MAP | B6: 3500 | D6: Hotel Santosh-Budget-Triple MAP | E6: 3500 | J6: Winger 12 Seater | K6: 8000 | L6: 8500
A7: Hotel Santosh-Budget-Quad EP | B7: 3500 | D7: Hotel Santosh-Budget-Quad EP | E7: 3500 | J7: Tempo 16 Seater | K7: 10000 | L7: 9500
A8: Hotel Santosh-Budget-Quad MAP | B8: 5000 | D8: Hotel Santosh-Budget-Quad MAP | E8: 5000 | J8: Tempo 20 Seater | K8: 10500 | L8: 11500
A9: Gaurav Hotel-Budget-Key | B9: Janki ChattiBudget | D9: Gaurav Hotel-Budget-Key | E9: Janki ChattiBudget | J9: Tempo 25 Seater | K9: 13500 | L9: 12500
A10: Buransh Homestay-Budget-Key | B10: Janki ChattiBudget | D10: Buransh Homestay-Budget-Key | E10: Janki ChattiBudget | J10: Urbania 12 Seater | L10: 11500
A11: AP Residency-Standard-Key | B11: Janki ChattiStandard | D11: AP Residency-Standard-Key | E11: Janki ChattiStandard | J11: Urbania 17 Seater | L11: 12000
A12: AP Residency-Standard-Double EP | B12: 2500 | D12: AP Residency-Standard-Double EP | E12: 2500 | J12: Mini Bus 27 Seater | L12: 17500
A13: AP Residency-Standard-Double CP | B13: 2700 | D13: AP Residency-Standard-Double CP | E13: 2700
A14: AP Residency-Standard-Double MAP | B14: 3200 | D14: AP Residency-Standard-Double MAP | E14: 3200
A15: AP Residency-Standard-Triple EP | B15: 3200 | D15: AP Residency-Standard-Triple EP | E15: 3200
A16: AP Residency-Standard-Triple CP | B16: 3400 | D16: AP Residency-Standard-Triple CP | E16: 3400
A17: AP Residency-Standard-Triple MAP | B17: 3900 | D17: AP Residency-Standard-Triple MAP | E17: 3900
A18: AP Residency-Standard-Quad EP | B18: 4100 | D18: AP Residency-Standard-Quad EP | E18: 4100
A19: AP Residency-Standard-Quad MAP | B19: 4800 | D19: AP Residency-Standard-Quad MAP | E19: 4800
A20: AP Residency-Standard-Quad CP | B20: 4300 | D20: AP Residency-Standard-Quad CP | E20: 4300
A21: Blessings Resort Family Cottages (Mountain view with private balcony)-Premium-Key | B21: Janki ChattiPremium | D21: Blessings Resort Family Cottages (Mountain view with private balcony)-Premium-Key | E21: Janki ChattiPremium
A22: Blessings Resort Family Cottages (Mountain view with private balcony)-Premium-Double EP | B22: 5000 | D22: Blessings Resort Family Cottages (Mountain view with private balcony)-Premium-Double EP | E22: 5000
A23: Blessings Resort Family Cottages (Mountain view with private balcony)-Premium-Double CP | B23: 6200 | D23: Blessings Resort Family Cottages (Mountain view with private balcony)-Premium-Double CP | E23: 6200
A24: Blessings Resort Family Cottages (Mountain view with private balcony)-Premium-Double MAP | B24: 7000 | D24: Blessings Resort Family Cottages (Mountain view with private balcony)-Premium-Double MAP | E24: 7000
A25: Blessings Resort Family Cottages (Mountain view with private balcony)-Premium-Triple EP | B25: 6800 | D25: Blessings Resort Family Cottages (Mountain view with private balcony)-Premium-Triple EP | E25: 6800
A26: Blessings Resort Family Cottages (Mountain view with private balcony)-Premium-Triple CP | B26: 8300 | D26: Blessings Resort Family Cottages (Mountain view with private balcony)-Premium-Triple CP | E26: 8300
A27: Blessings Resort Family Cottages (Mountain view with private balcony)-Premium-Triple MAP | B27: 9500 | D27: Blessings Resort Family Cottages (Mountain view with private balcony)-Premium-Triple MAP | E27: 9500
A28: Blessings Resort Family Cottages (Mountain view with private balcony)-Premium-Quad EP | B28: 8600 | D28: Blessings Resort Family Cottages (Mountain view with private balcony)-Premium-Quad EP | E28: 8600
A29: Blessings Resort Family Cottages (Mountain view with private balcony)-Premium-Quad MAP | B29: 12000 | D29: Blessings Resort Family Cottages (Mountain view with private balcony)-Premium-Quad MAP | E29: 12000
A30: Blessings Resort Family Cottages (Mountain view with private balcony)-Premium-Quad CP | B30: 10400 | D30: Blessings Resort Family Cottages (Mountain view with private balcony)-Premium-Quad CP | E30: 10400
A31: Blessings Resort Deluxe Cottages (Mountain view with private balcony)-Premium-Key | B31: Janki ChattiPremium | D31: Blessings Resort Deluxe Cottages (Mountain view with private balcony)-Premium-Key | E31: Janki ChattiPremium
A32: Blessings Resort Deluxe Cottages (Mountain view with private balcony)-Premium-Double EP | B32: 5500 | D32: Blessings Resort Deluxe Cottages (Mountain view with private balcony)-Premium-Double EP | E32: 5500
A33: Blessings Resort Deluxe Cottages (Mountain view with private balcony)-Premium-Double CP | B33: 6200 | D33: Blessings Resort Deluxe Cottages (Mountain view with private balcony)-Premium-Double CP | E33: 6200
A34: Blessings Resort Deluxe Cottages (Mountain view with private balcony)-Premium-Double MAP | B34: 7000 | D34: Blessings Resort Deluxe Cottages (Mountain view with private balcony)-Premium-Double MAP | E34: 7000
A35: Blessings Resort Deluxe Cottages (Mountain view with private balcony)-Premium-Triple EP | B35: 7300 | D35: Blessings Resort Deluxe Cottages (Mountain view with private balcony)-Premium-Triple EP | E35: 7300
A36: Blessings Resort Deluxe Cottages (Mountain view with private balcony)-Premium-Triple CP | B36: 8300 | D36: Blessings Resort Deluxe Cottages (Mountain view with private balcony)-Premium-Triple CP | E36: 8300
A37: Blessings Resort Deluxe Cottages (Mountain view with private balcony)-Premium-Triple MAP | B37: 9500 | D37: Blessings Resort Deluxe Cottages (Mountain view with private balcony)-Premium-Triple MAP | E37: 9500
A38: Blessings Resort Deluxe Cottages (Mountain view with private balcony)-Premium-Quad EP | B38: 9100 | D38: Blessings Resort Deluxe Cottages (Mountain view with private balcony)-Premium-Quad EP | E38: 9100
A39: Blessings Resort Deluxe Cottages (Mountain view with private balcony)-Premium-Quad MAP | B39: 12000 | D39: Blessings Resort Deluxe Cottages (Mountain view with private balcony)-Premium-Quad MAP | E39: 12000
A40: Blessings Resort Deluxe Cottages (Mountain view with private balcony)-Premium-Quad CP | B40: 10400 | D40: Blessings Resort Deluxe Cottages (Mountain view with private balcony)-Premium-Quad CP | E40: 10400
A41: Blessings Resort Luxury Cottages (Mountain & River view with private balcony)-Premium-Key | B41: Janki ChattiPremium | D41: Blessings Resort Luxury Cottages (Mountain & River view with private balcony)-Premium-Key | E41: Janki ChattiPremium
A42: Blessings Resort Luxury Cottages (Mountain & River view with private balcony)-Premium-Double EP | B42: 8000 | D42: Blessings Resort Luxury Cottages (Mountain & River view with private balcony)-Premium-Double EP | E42: 8000
A43: Blessings Resort Luxury Cottages (Mountain & River view with private balcony)-Premium-Double CP | B43: 9500 | D43: Blessings Resort Luxury Cottages (Mountain & River view with private balcony)-Premium-Double CP | E43: 9500
A44: Blessings Resort Luxury Cottages (Mountain & River view with private balcony)-Premium-Double MAP | B44: 12000 | D44: Blessings Resort Luxury Cottages (Mountain & River view with private balcony)-Premium-Double MAP | E44: 12000
A45: Blessings Resort Luxury Cottages (Mountain & River view with private balcony)-Premium-Triple EP | B45: 9800 | D45: Blessings Resort Luxury Cottages (Mountain & River view with private balcony)-Premium-Triple EP | E45: 9800
A46: Blessings Resort Luxury Cottages (Mountain & River view with private balcony)-Premium-Triple CP | B46: 11600 | D46: Blessings Resort Luxury Cottages (Mountain & River view with private balcony)-Premium-Triple CP | E46: 11600
A47: Blessings Resort Luxury Cottages (Mountain & River view with private balcony)-Premium-Triple MAP | B47: 14500 | D47: Blessings Resort Luxury Cottages (Mountain & River view with private balcony)-Premium-Triple MAP | E47: 14500
A48: Blessings Resort Luxury Cottages (Mountain & River view with private balcony)-Premium-Quad EP | B48: 11600 | D48: Blessings Resort Luxury Cottages (Mountain & River view with private balcony)-Premium-Quad EP | E48: 11600
A49: Blessings Resort Luxury Cottages (Mountain & River view with private balcony)-Premium-Quad MAP | B49: 17000 | D49: Blessings Resort Luxury Cottages (Mountain & River view with private balcony)-Premium-Quad MAP | E49: 17000
A50: Blessings Resort Luxury Cottages (Mountain & River view with private balcony)-Premium-Quad CP | B50: 13700 | D50: Blessings Resort Luxury Cottages (Mountain & River view with private balcony)-Premium-Quad CP | E50: 13700
A51: Yamunotri Cottages (Classic)-Premium-Key | B51: Janki ChattiPremium | D51: Yamunotri Cottages (Classic)-Premium-Key | E51: Janki ChattiPremium
A52: Yamunotri Cottages (Classic)-Premium-Double EP | B52: 3480 | D52: Yamunotri Cottages (Classic)-Premium-Double EP | E52: 3480
A53: Yamunotri Cottages (Classic)-Premium-Double CP | B53: 4740 | D53: Yamunotri Cottages (Classic)-Premium-Double CP | E53: 4740
A54: Yamunotri Cottages (Classic)-Premium-Double MAP | B54: 6000 | D54: Yamunotri Cottages (Classic)-Premium-Double MAP | E54: 6000
A55: Yamunotri Cottages (Luxury Pine)-Premium-Key | B55: Janki ChattiPremium | D55: Yamunotri Cottages (Luxury Pine)-Premium-Key | E55: Janki ChattiPremium
A56: Yamunotri Cottages (Luxury Pine)-Premium-Double EP | B56: 5265 | D56: Yamunotri Cottages (Luxury Pine)-Premium-Double EP | E56: 5265
A57: Yamunotri Cottages (Luxury Pine)-Premium-Double CP | B57: 6525 | D57: Yamunotri Cottages (Luxury Pine)-Premium-Double CP | E57: 6525
A58: Yamunotri Cottages (Luxury Pine)-Premium-Double MAP | B58: 7785 | D58: Yamunotri Cottages (Luxury Pine)-Premium-Double MAP | E58: 7785
A59: Hotel Laxmi Palace-Standard-Key | B59: Janki ChattiStandard | D59: Hotel Laxmi Palace-Standard-Key | E59: Janki ChattiStandard
A60: Hotel Laxmi Palace-Standard-Double EP | B60: 2600 | D60: Hotel Laxmi Palace-Standard-Double EP | E60: 2600
A61: Hotel Laxmi Palace-Standard-Double CP | B61: 2800 | D61: Hotel Laxmi Palace-Standard-Double CP | E61: 2800
A62: Hotel Laxmi Palace-Standard-Double MAP | B62: 3200 | D62: Hotel Laxmi Palace-Standard-Double MAP | E62: 3200
A63: Hotel Laxmi Palace-Standard-Triple EP | B63: 2700 | D63: Hotel Laxmi Palace-Standard-Triple EP | E63: 2700
A64: Hotel Laxmi Palace-Standard-Triple CP | B64: 3000 | D64: Hotel Laxmi Palace-Standard-Triple CP | E64: 3000
A65: Hotel Laxmi Palace-Standard-Triple MAP | B65: 3600 | D65: Hotel Laxmi Palace-Standard-Triple MAP | E65: 3600
A66: Hotel Laxmi Palace-Standard-Quad EP | B66: 3600 | D66: Hotel Laxmi Palace-Standard-Quad EP | E66: 3600
A67: Hotel Laxmi Palace-Standard-Quad MAP | B67: 4800 | D67: Hotel Laxmi Palace-Standard-Quad MAP | E67: 4800
A68: Hotel Laxmi Palace-Standard-Quad CP | B68: 4000 | D68: Hotel Laxmi Palace-Standard-Quad CP | E68: 4000
A69: Rudra Camp Kedarnath-Premium-Key | B69: KedarnathPremium | D69: Rudra Camp Kedarnath-Premium-Key | E69: KedarnathPremium
A70: Rudra Camp Kedarnath-Premium-Double MAP | B70: 6500 | D70: Rudra Camp Kedarnath-Premium-Double MAP | E70: 6500
A71: Rudra Camp Kedarnath-Premium-Triple MAP | B71: 7500 | D71: Rudra Camp Kedarnath-Premium-Triple MAP | E71: 7500
A72: Rudra Camp Kedarnath-Premium-Quad MAP | B72: 8000 | D72: Rudra Camp Kedarnath-Premium-Quad MAP | E72: 8000
A73: Rudra Hotel-Budget-Key | B73: KedarnathBudget | D73: Rudra Hotel-Budget-Key | E73: KedarnathBudget
A74: Rudra Hotel-Budget-Triple EP | B74: 7500 | D74: Rudra Hotel-Budget-Triple EP | E74: 7500
A75: Rudra Hotel-Budget-Quad EP | B75: 15000 | D75: Rudra Hotel-Budget-Quad EP | E75: 15000
A76: Hotel New Pandey Inn-Budget-Key | B76: KedarnathBudget | D76: Hotel New Pandey Inn-Budget-Key | E76: KedarnathBudget
A77: Hotel New Pandey Inn-Budget-Double EP | B77: 1200 | D77: Hotel New Pandey Inn-Budget-Double EP | E77: 1200
A78: Hotel New Pandey Inn-Budget-Double CP | B78: 1600 | D78: Hotel New Pandey Inn-Budget-Double CP | E78: 1600
A79: Hotel New Pandey Inn-Budget-Double MAP | B79: 2000 | D79: Hotel New Pandey Inn-Budget-Double MAP | E79: 2000
A80: Hotel New Pandey Inn-Budget-Triple EP | B80: 1800 | D80: Hotel New Pandey Inn-Budget-Triple EP | E80: 1800
A81: Hotel New Pandey Inn-Budget-Triple CP | B81: 2400 | D81: Hotel New Pandey Inn-Budget-Triple CP | E81: 2400
A82: Hotel New Pandey Inn-Budget-Triple MAP | B82: 3000 | D82: Hotel New Pandey Inn-Budget-Triple MAP | E82: 3000
A83: Hotel New Pandey Inn-Budget-Quad EP | B83: 2400 | D83: Hotel New Pandey Inn-Budget-Quad EP | E83: 2400
A84: Hotel New Pandey Inn-Budget-Quad MAP | B84: 4000 | D84: Hotel New Pandey Inn-Budget-Quad MAP | E84: 4000
A85: Parmeshwari Kedarnath (Only 20mts Kedarnath Temple)-Premium-Key | B85: KedarnathPremium | D85: Parmeshwari Kedarnath (Only 20mts Kedarnath Temple)-Premium-Key | E85: KedarnathPremium
A86: Parmeshwari Kedarnath (Only 20mts Kedarnath Temple)-Premium-Double MAP | B86: 7000 | D86: Parmeshwari Kedarnath (Only 20mts Kedarnath Temple)-Premium-Double MAP | E86: 7000
A87: Parmeshwari Kedarnath (Only 20mts Kedarnath Temple)-Premium-Triple MAP | B87: 10500 | D87: Parmeshwari Kedarnath (Only 20mts Kedarnath Temple)-Premium-Triple MAP | E87: 10500
A88: Parmeshwari Kedarnath (Only 20mts Kedarnath Temple)-Premium-Quad MAP | B88: 12500 | D88: Parmeshwari Kedarnath (Only 20mts Kedarnath Temple)-Premium-Quad MAP | E88: 12500
A89: Blessings Resort Dormitory-Budget-Key | B89: Janki ChattiBudget | D89: Blessings Resort Dormitory-Budget-Key | E89: Janki ChattiBudget
A90: Blessings Resort Dormitory-Budget-Double EP | B90: 1200 | D90: Blessings Resort Dormitory-Budget-Double EP | E90: 1200
A91: Blessings Resort Dormitory-Budget-Double CP | B91: 1600 | D91: Blessings Resort Dormitory-Budget-Double CP | E91: 1600
A92: Blessings Resort Dormitory-Budget-Double MAP | B92: 2400 | D92: Blessings Resort Dormitory-Budget-Double MAP | E92: 2400
A93: Blessings Resort Dormitory-Budget-Triple EP | B93: 1800 | D93: Blessings Resort Dormitory-Budget-Triple EP | E93: 1800
A94: Blessings Resort Dormitory-Budget-Triple CP | B94: 2400 | D94: Blessings Resort Dormitory-Budget-Triple CP | E94: 2400
A95: Blessings Resort Dormitory-Budget-Triple MAP | B95: 3600 | D95: Blessings Resort Dormitory-Budget-Triple MAP | E95: 3600
A96: Blessings Resort Dormitory-Budget-Quad EP | B96: 2400 | D96: Blessings Resort Dormitory-Budget-Quad EP | E96: 2400
A97: Blessings Resort Dormitory-Budget-Quad MAP | B97: 4800 | D97: Blessings Resort Dormitory-Budget-Quad MAP | E97: 4800
A98: Blessings Resort Dormitory-Budget-Quad CP | B98: 3200 | D98: Blessings Resort Dormitory-Budget-Quad CP | E98: 3200
A99: Hotel Ankit Palace-Standard-Key | B99: UttarkashiStandard | D99: Hotel Ankit Palace-Standard-Key | E99: UttarkashiStandard
A100: Hotel Ankit Palace-Standard-Double EP | B100: 2000 | D100: Hotel Ankit Palace-Standard-Double EP | E100: 2000
...

Sheet Day Wise Exursion
A1: Day No. | B1: Title | C1: Description
A2: =IF(B2="","", "Day " & ROW(A2)-1)
A3: =IF(B3="","", "Day " & ROW(A3)-1)
A4: =IF(B4="","", "Day " & ROW(A4)-1)
A5: =IF(B5="","", "Day " & ROW(A5)-1)
A6: =IF(B6="","", "Day " & ROW(A6)-1)
A7: =IF(B7="","", "Day " & ROW(A7)-1)
A8: =IF(B8="","", "Day " & ROW(A8)-1)
A9: =IF(B9="","", "Day " & ROW(A9)-1)
A10: =IF(B10="","", "Day " & ROW(A10)-1)
A11: =IF(B11="","", "Day " & ROW(A11)-1)
A12: =IF(B12="","", "Day " & ROW(A12)-1)
A13: =IF(B13="","", "Day " & ROW(A13)-1)
... A32: =IF(B32="","", "Day " & ROW(A32)-1)

Sheet Sheet1
A1: Barkot | B1: Number | C1: Status | D1: Janki Chati | E1: Number2 | F1: Status2 | G1: Uttarkashi | H1: Number3 | I1: Status3 | J1: Sitapur | K1: Number6 | L1: Status4 | M1: Sonprayag | N1: Number63 | O1: Status72 | P1: Kedarnath | Q1: Number8 | R1: Status9 | S1: Pipalkothi | T1: Number10 | U1: Status11 | V1: Rudraprayag | W1: Number12 | X1: Status22 | Y1: Status23 | Z1: Status24
A2: Gaurav home stay | B2: 62022 21906 | D2: AP Residency | E2: 81261 29244 | F2: Done | G2: Hotel Ankit Palace | H2: (+91 84779 70854) | J2: Hotel Blue Pine Sitapur Kedarnath Rudraprayag | K2: 73022 46705 | M2: Neelansh Resort | N2: 84497 84725 | P2: BIKANER HOUSE KEDARNATH | Q2: 7701818848 | S2: HOTEL DEVLOK | T2: (+91 98374 28573) | V2: Hotel Srikot Castle | Y2: Sanchet Pandit Kedarnath | Z2: 90272 57463
A3: Hotel Jagatguru | B3: 8979873775 | D3: Buransh Homestay | E3: 89542 97901 | G3: Hotel Sravasti uttarkashi | H3: (+91 9927137581)(+919634791633) | J3: Hotel Namami Gange | K3: 81262 97258 | M3: Shri Narayan Touris Lodge & Chandica Hotel | N3: (+91 94101 90517) | P3: Rudra Camp Kedarnath | Q3: (+91 97611 62608) | S3: Hotel Heaven | T3: (+91 9411535970) | V3: Hotel Blue Orchid | W3: (+91 82737 08462) 7300907201 | Y3: Vikas Panditji Badrinath | Z3: 95202 00882
A4: Hotel Magpie | B4: 9456527523/7467047043 | D4: Blessings Resort Yamunotri | E4: 89796 04465 | G4: Hotel maharishi | H4: (+91 9411332768) | J4: Phulwari Resort | K4: 98731 11710 | M4: Kailashpati Resort | N4: 9368678109/ 8171672141 | P4: Hotel New Pandey Inn | Q4: (+91 95570 39123) | S4: hotel heaven | T4: (+91 9917781959) | V4: Tuilp Resort
A5: Madhuvan Guest House | B5: 9917603134/74569 99072 | D5: Yamunotri Cottages | E5: 96502 44553 | G5: Shivlinga Resort | H5: (+91 99174 77718)/8755544335 | J5: NEW BASERA HOTEL | K5: 78277 20186 | M5: Narayan Valley Resort | N5: 82796 70379 | P5: Marwar house | Q5: 94581 28124 | S5: Hotel Vinayak | T5: (+91 9412029833) {+91 6395 367 534} | V5: River side resort
A6: Hotel Mountain Paradise & Restaurant | B6: 85060 50464 | D6: Hotel Laxmi Palace | E6: 97600 58409 | G6: Maa Saraswati Hotel | H6: (+91 98975 19437) | J6: Abhishek Hotel | K6: 82798 63790 | M6: Kedar Hill Resort | N6: 95363 88868 | S6: Hotel Bhawani | T6: (+91 94565 65694) | V6: Lovekush
A7: Hotel Vivek Palace and Restaurant | B7: 85328 71220 | D7: Gaurav hotel jankichatti | E7: 89796 60958 | G7: Hotel Sahaj Villa | H7: (+91 95574 20698) | J7: Hotel Shiv Manohar | K7: 81691 06875 | S7: Heritage Inn | T7: (+91 9557654106) | V7: Ivy Top
A8: Hotel Pinewood (The om Hotels) reservations@theomhotels.com | B8: 9582060044 | D8: Hotel Aakashdeep | E8: 75002 47797 | G8: Hotel Anandam | H8: (+91 95366 55223) | J8: shri Narayan Resort | K8: 9760328706 | S8: HOTEL COMFORT INN | T8: (+91 94129 61867) | V8: Tulip Resort | W8: (+91-9997888111)
A9: Hotel Devbhoomi | B9: 81717 54463 | D9: Shiv Shakti Eco Resort | E9: 99107 23070 | G9: HOTEL SURYANSH | H9: (+91 97607 99099) | J9: Shivalik Valley Resorts | K9: 93188 03777 | S9: Hotel Le Meadows , Pipalkoti | T9: (+91 95288 69233) | V9: Monal Resort
A10: Hotel Aswal Deluxe | B10: 7718271009 | D10: Hotel Vijay Residency Barkot | E10: 94129 40987,9412940987.9897230743. | G10: Anand Ganga | H10: (+91 90127 07517) | S10: Harela Inn Luxury Hotel Restaurant North & South Indian | T10: (+91 92584 40449) | V10: Hotel Samrat Resort Rudraprayag | W10: (+9187559 98877) {+91 6396148290} {+91 9756855844}
A11: Hotel Aditya Palace Barkot | B11: 94115 52105 | D11: Hotel Santosh | E11: 89389 36363 | G11: RAJAJI HOTELS | H11: (+91 85275 21888) | S11: HOTEL AND RESTAURANT DHAULI GANGA | T11: (+91 86500 97080) | V11: Hotel Le Meadows | W11: (+91 95288 69233)
A12: Hotel vivek palace | B12: 89794 55591 | G12: Shrigangalok hotels | H12: (+91 95689 46061) | S12: Kandari Guest House | T12: (+91 87917 75911) | V12: HOTEL BATTALION 10 | W12: ( +91 89795 55514)
A13: Hotel Garhwal Palace | B13: 94101 09164 | G13: osho zenganga commune | H13: (+91 96347 91633) | S13: Hotel Sudarshan Palace | T13: 075003 02065 | V13: Sukoon Dk | W13: 87911 69111
A14: Hotel Shivlinga Villa | B14: 87555 44335 | G14: Hotel Narayan Palace The Om Hotel | H14: (+91 9582060044) | S14: Hotel Nirvanam | T14: 094109 97676
A15: Hotel Necklace Moon | B15: 98723 65465 | S15: La Riviere Waterfront A Traditional Stay | T15: 093530 12144
A16: Hotel Ashiyana Barkot | B16: 093893 01916/92581 26088 | S16: Tapovan Resort | T16: 097201 02741
A17: Hotel Mangalam | B17: 94115 64102 | S17: Phulari House - Heart in Hills | T17: 080775 32798
A18: Hotel Poll Star Inn The Om Hotel | B18: 80771 37481 | S18: Vasudev lodge | T18: 062800 69347
A19: Raturi Annexe Hotel & Restaurant Barkot | B19: 78955 22660 | S19: KDC GUEST HOUSE | T19: 073511 50170
A20: The Monkey Tail Resort (luxry Premium) | B20: 89796 63432 | S20: New Shivlok Hotel Pipalkoti | T20: 094120 32191
A21: RJ Anandam Resort | B21: 7037736310 | S21: Hotel Ajay Palace | T21: 94121 19046
S22: Rudra Homestay | T22: 097610 71155
S23: New Indra Lodge | T23: 094113 79963
S24: The Royal Fateh Inn | T24: 7668598928
S25: Hotel Mount Inn Badrinath Marg , Birahi , Chamoli | T25: 084330 77950
S26: SATOPANTH INN LUXURY HOTEL & RESTAURANT, GARHWALI, NORTH & SOUTH INDIAN | T26: 074570 07268
S27: Kalp Palace Homestay | T27: 078180 99103
S28: Hotel Rajendra Palace - Urgam Valley | T28: 094105 07814
S29: Sayana hotel Chamoli | T29: 099971 92838
S30: Hotel Chandra deep | T30: 098973 55552
S31: Peaches and Pears | T31: 099170 12636
S32: Astha Guest House | T32: 081713 68023
S33: AGARWAL HOTEL & RESTAURENT | T33: 099971 35057
S34: Hotel Auli D - Hotel In Joshimath | T34: 091682 25688
S35: Om Pingaksh hotel & restaurant | T35: 095685 35463
S36: Hotel Manorama Palace | T36: 090128 44644
... S42: Badriville Resort | T42: 90589 88006

Sheet Sheet2
B1: City
B2: {=_xlfn.UNIQUE(RAW[[Destination ]])} -> Janki Chatti | D2: INDEX(Sheet1!$B$3:$D$7,0,MATCH(Sheet1!$B$11,Heading,0))
B3: Kedarnath
B4: Uttarkashi
B5: Sonprayag
B6: Sitapur
B7: Rudraprayag
B8: Pipalkoti
B9: Badarinath
B10: Barkot
B11: Pandukeshwar
B12: Guptkashi
B13: Chopta
B14: Joshimath
... B18: Haridwar
A21: City | B21: Hotecode | D21: Premium | E21: Budget | F21: Standard | G21: Value | J21: {=TRANSPOSE(City)} -> Janki Chatti | K21: Kedarnath | L21: Uttarkashi | M21: Sonprayag | N21: Sitapur | O21: Rudraprayag | P21: Pipalkoti | Q21: Badarinath | R21: Barkot | S21: Pandukeshwar | T21: Guptkashi | U21: Chopta | V21: Joshimath | W21: Rishikesh | X21: Harsil | Y21: Netala | Z21: Haridwar | AA21: 0 | AB21: 0
A22: =IF(B22="","",_xlfn.XLOOKUP(B22,'Raw'!D:D,'Raw'!B:B)) -> #N/A | B22: {=_xlfn.UNIQUE(RAW[Hotel Code])} -> 0 | C22: =VLOOKUP(B22,RAW[[Hotel Code]:[Hotel / Resort Name ]],2,0) -> #N/A | D22: =$A22&D$21 -> #N/A | E22: =$A22&E$21 -> #N/A | F22: =$A22&F$21 -> #N/A | G22: Janki ChattiPremium | J22: {=_xlfn.UNIQUE(_xlfn._xlws.FILTER(RAW[Room Type],RAW[[Destination ]]=Sheet2!J21))} -> Budget | K22: {=_xlfn.UNIQUE(_xlfn._xlws.FILTER(RAW[Room Type],RAW[[Destination ]]=Sheet2!K21))} -> Premium | L22: {=_xlfn.UNIQUE(_xlfn._xlws.FILTER(RAW[Room Type],RAW[[Destination ]]=Sheet2!L21))} -> Standard | M22: {=_xlfn.UNIQUE(_xlfn._xlws.FILTER(RAW[Room Type],RAW[[Destination ]]=Sheet2!M21))} -> Budget | N22: {=_xlfn.UNIQUE(_xlfn._xlws.FILTER(RAW[Room Type],RAW[[Destination ]]=Sheet2!N21))} -> Standard | O22: {=_xlfn.UNIQUE(_xlfn._xlws.FILTER(RAW[Room Type],RAW[[Destination ]]=Sheet2!O21))} -> Standard | P22: {=_xlfn.UNIQUE(_xlfn._xlws.FILTER(RAW[Room Type],RAW[[Destination ]]=Sheet2!P21))} -> Premium | Q22: {=_xlfn.UNIQUE(_xlfn._xlws.FILTER(RAW[Room Type],RAW[[Destination ]]=Sheet2!Q21))} -> Premium | ... AC22: {=_xlfn.UNIQUE(_xlfn._xlws.FILTER(RAW[Room Type],RAW[[Destination ]]=Sheet2!AC21))} -> #VALUE! | AD22: {=IF(AD21="","",_xlfn._xlws.FILTER(RAW[[#All],[Room Type]],RAW[[#All],[Hotel / Resort Name ]]=Sheet2!AD$21))} | AE22: {=IF(AE21="","",_xlfn._xlws.FILTER(RAW[[#All],[Room Type]],RAW[[#All],[Hotel / Resort Name ]]=Sheet2!AE$21))} | AF22: {=IF(AF21="","",_xlfn._xlws.FILTER(RAW[[#All],[Room Type]],RAW[[#All],[Hotel / Resort Name ]]=Sheet2!AF$21))} | AG22: {=IF(AG21="","",_xlfn._xlws.FILTER(RAW[[#All],[Room Type]],RAW[[#All],[Hotel / Resort Name ]]=Sheet2!AG$21))} | AH22: {=IF(AH21="","",_xlfn._xlws.FILTER(RAW[[#All],[Room Type]],RAW[[#All],[Hotel / Resort Name ]]=Sheet2!AH$21))} | AI22: {=IF(AI21="","",_xlfn._xlws.FILTER(RAW[[#All],[Room Type]],RAW[[#All],[Hotel / Resort Name ]]=Sheet2!AI$21))} | AJ22: {=IF(AJ21="","",_xlfn._xlws.FILTER(RAW[[#All],[Room Type]],RAW[[#All],[Hotel / Resort Name ]]=Sheet2!AJ$21))} | AK22: {=IF(AK21="","",_xlfn._xlws.FILTER(RAW[[#All],[Room Type]],RAW[[#All],[Hotel / Resort Name ]]=Sheet2!AK$21))} | ... BT22: {=IF(BT21="","",_xlfn._xlws.FILTER(RAW[[#All],[Room Type]],RAW[[#All],[Hotel / Resort Name ]]=Sheet2!BT$21))} | BU22: {=IF(BU$21<>"",_xlfn.UNIQUE(_xlfn._xlws.FILTER(RAW[[#All],[Room Type]],RAW[[#All],[Hotel / Resort Name ]]=Sheet2!BU$21)),"")} | BV22: {=IF(BV$21<>"",_xlfn.UNIQUE(_xlfn._xlws.FILTER(RAW[[#All],[Room Type]],RAW[[#All],[Hotel / Resort Name ]]=Sheet2!BV$21)),"")} | BW22: {=IF(BW$21<>"",_xlfn.UNIQUE(_xlfn._xlws.FILTER(RAW[[#All],[Room Type]],RAW[[#All],[Hotel / Resort Name ]]=Sheet2!BW$21)),"")} | BX22: {=IF(BX$21<>"",_xlfn.UNIQUE(_xlfn._xlws.FILTER(RAW[[#All],[Room Type]],RAW[[#All],[Hotel / Resort Name ]]=Sheet2!BX$21)),"")} | BY22: {=IF(BY$21<>"",_xlfn.UNIQUE(_xlfn._xlws.FILTER(RAW[[#All],[Room Type]],RAW[[#All],[Hotel / Resort Name ]]=Sheet2!BY$21)),"")} | BZ22: {=IF(BZ$21<>"",_xlfn.UNIQUE(_xlfn._xlws.FILTER(RAW[[#All],[Room Type]],RAW[[#All],[Hotel / Resort Name ]]=Sheet2!BZ$21)),"")} | CA22: {=IF(CA$21<>"",_xlfn.UNIQUE(_xlfn._xlws.FILTER(RAW[[#All],[Room Type]],RAW[[#All],[Hotel / Resort Name ]]=Sheet2!CA$21)),"")} | CB22: {=IF(CB$21<>"",_xlfn.UNIQUE(_xlfn._xlws.FILTER(RAW[[#All],[Room Type]],RAW[[#All],[Hotel / Resort Name ]]=Sheet2!CB$21)),"")} | ... ADG22: {=IF(ADG$21<>"",_xlfn.UNIQUE(_xlfn._xlws.FILTER(RAW[[#All],[Room Type]],RAW[[#All],[Hotel / Resort Name ]]=Sheet2!ADG$21)),"")}
A23: =IF(B23="","",_xlfn.XLOOKUP(B23,'Raw'!D:D,'Raw'!B:B)) | C23: =VLOOKUP(B23,RAW[[Hotel Code]:[Hotel / Resort Name ]],2,0) -> #N/A | D23: =$A23&D$21 -> Premium | E23: =$A23&E$21 -> Budget | F23: =$A23&F$21 -> Standard | G23: Janki ChattiBudget | J23: Standard | K23: Budget | L23: Budget | M23: Standard | N23: Premium | O23: Premium | P23: Standard | Q23: Standard | R23: Budget | Z23: Premium
A24: =IF(B24="","",_xlfn.XLOOKUP(B24,'Raw'!D:D,'Raw'!B:B)) | C24: =VLOOKUP(B24,RAW[[Hotel Code]:[Hotel / Resort Name ]],2,0) -> #N/A | D24: =$A24&D$21 -> Premium | E24: =$A24&E$21 -> Budget | F24: =$A24&F$21 -> Standard | G24: Janki ChattiStandard | J24: Premium | L24: Premium | M24: Premium | N24: Budget | P24: Budget | R24: Premium | Z24: Standard
A25: =IF(B25="","",_xlfn.XLOOKUP(B25,'Raw'!D:D,'Raw'!B:B)) | C25: =VLOOKUP(B25,RAW[[Hotel Code]:[Hotel / Resort Name ]],2,0) -> #N/A | D25: =$A25&D$21 -> Premium | E25: =$A25&E$21 -> Budget | F25: =$A25&F$21 -> Standard | G25: KedarnathPremium
A26: =IF(B26="","",_xlfn.XLOOKUP(B26,'Raw'!D:D,'Raw'!B:B)) | C26: =VLOOKUP(B26,RAW[[Hotel Code]:[Hotel / Resort Name ]],2,0) -> #N/A | D26: =$A26&D$21 -> Premium | E26: =$A26&E$21 -> Budget | F26: =$A26&F$21 -> Standard | G26: KedarnathBudget
A27: =IF(B27="","",_xlfn.XLOOKUP(B27,'Raw'!D:D,'Raw'!B:B)) | C27: =VLOOKUP(B27,RAW[[Hotel Code]:[Hotel / Resort Name ]],2,0) -> #N/A | D27: =$A27&D$21 -> Premium | E27: =$A27&E$21 -> Budget | F27: =$A27&F$21 -> Standard | G27: KedarnathStandard
A28: =IF(B28="","",_xlfn.XLOOKUP(B28,'Raw'!D:D,'Raw'!B:B)) | C28: =VLOOKUP(B28,RAW[[Hotel Code]:[Hotel / Resort Name ]],2,0) -> #N/A | D28: =$A28&D$21 -> Premium | E28: =$A28&E$21 -> Budget | F28: =$A28&F$21 -> Standard | G28: UttarkashiPremium
A29: =IF(B29="","",_xlfn.XLOOKUP(B29,'Raw'!D:D,'Raw'!B:B)) | C29: =VLOOKUP(B29,RAW[[Hotel Code]:[Hotel / Resort Name ]],2,0) -> #N/A | D29: =$A29&D$21 -> Premium | E29: =$A29&E$21 -> Budget | F29: =$A29&F$21 -> Standard | G29: UttarkashiBudget
A30: =IF(B30="","",_xlfn.XLOOKUP(B30,'Raw'!D:D,'Raw'!B:B)) | C30: =VLOOKUP(B30,RAW[[Hotel Code]:[Hotel / Resort Name ]],2,0) -> #N/A | D30: =$A30&D$21 -> Premium | E30: =$A30&E$21 -> Budget | F30: =$A30&F$21 -> Standard | G30: UttarkashiStandard
A31: =IF(B31="","",_xlfn.XLOOKUP(B31,'Raw'!D:D,'Raw'!B:B)) | C31: =VLOOKUP(B31,RAW[[Hotel Code]:[Hotel / Resort Name ]],2,0) -> #N/A | D31: =$A31&D$21 -> Premium | E31: =$A31&E$21 -> Budget | F31: =$A31&F$21 -> Standard | G31: SonprayagPremium
A32: =IF(B32="","",_xlfn.XLOOKUP(B32,'Raw'!D:D,'Raw'!B:B)) | C32: =VLOOKUP(B32,RAW[[Hotel Code]:[Hotel / Resort Name ]],2,0) -> #N/A | D32: =$A32&D$21 -> Premium | E32: =$A32&E$21 -> Budget | F32: =$A32&F$21 -> Standard | G32: SonprayagBudget | J32: {=TRANSPOSE(Table5_1[Value])} -> Janki ChattiPremium | K32: Janki ChattiBudget | L32: Janki ChattiStandard | M32: KedarnathPremium | N32: KedarnathBudget | O32: KedarnathStandard | P32: UttarkashiPremium | Q32: UttarkashiBudget | R32: UttarkashiStandard | S32: SonprayagPremium | T32: SonprayagBudget | U32: SonprayagStandard | V32: SitapurPremium | W32: SitapurBudget | X32: SitapurStandard | Y32: RudraprayagPremium | Z32: RudraprayagBudget | AA32: RudraprayagStandard | AB32: PipalkotiPremium | AC32: PipalkotiBudget | AD32: PipalkotiStandard | AE32: BadarinathPremium | AF32: BadarinathBudget | AG32: BadarinathStandard | AH32: BarkotPremium | AI32: BarkotBudget | AJ32: BarkotStandard | AK32: PandukeshwarPremium | AL32: PandukeshwarBudget | AM32: PandukeshwarStandard | AN32: GuptkashiPremium | AO32: GuptkashiBudget | AP32: GuptkashiStandard | AQ32: ChoptaPremium | AR32: ChoptaBudget | AS32: ChoptaStandard | AT32: JoshimathPremium | AU32: JoshimathBudget | AV32: JoshimathStandard | AW32: RishikeshPremium | AX32: RishikeshBudget | AY32: RishikeshStandard | AZ32: HarsilPremium | BA32: HarsilBudget | BB32: HarsilStandard | BC32: NetalaPremium | BD32: NetalaBudget | BE32: NetalaStandard | BF32: HaridwarPremium | BG32: HaridwarBudget | BH32: HaridwarStandard
A33: =IF(B33="","",_xlfn.XLOOKUP(B33,'Raw'!D:D,'Raw'!B:B)) | C33: =VLOOKUP(B33,RAW[[Hotel Code]:[Hotel / Resort Name ]],2,0) -> #N/A | D33: =$A33&D$21 -> Premium | E33: =$A33&E$21 -> Budget | F33: =$A33&F$21 -> Standard | G33: SonprayagStandard | J33: {=IF(J$32=0,"",_xlfn._xlws.FILTER(RAW[Hotel / Resort Name ],RAW[Key]=Sheet2!J$32,"Not Found"))} -> Blessings Resort Family Cottages (Mountain view with private balcony) | K33: {=IF(K$32=0,"",_xlfn._xlws.FILTER(RAW[Hotel / Resort Name ],RAW[Key]=Sheet2!K$32,"Not Found"))} -> Hotel Santosh | L33: {=IF(L$32=0,"",_xlfn._xlws.FILTER(RAW[Hotel / Resort Name ],RAW[Key]=Sheet2!L$32,"Not Found"))} -> AP Residency | M33: {=IF(M$32=0,"",_xlfn._xlws.FILTER(RAW[Hotel / Resort Name ],RAW[Key]=Sheet2!M$32,"Not Found"))} -> Rudra Camp Kedarnath | N33: {=IF(N$32=0,"",_xlfn._xlws.FILTER(RAW[Hotel / Resort Name ],RAW[Key]=Sheet2!N$32,"Not Found"))} -> Rudra Hotel | O33: {=IF(O$32=0,"",_xlfn._xlws.FILTER(RAW[Hotel / Resort Name ],RAW[Key]=Sheet2!O$32,"Not Found"))} -> Not Found | P33: {=IF(P$32=0,"",_xlfn._xlws.FILTER(RAW[Hotel / Resort Name ],RAW[Key]=Sheet2!P$32,"Not Found"))} -> Shivlinga Resort Deluxe Non AC | Q33: {=IF(Q$32=0,"",_xlfn._xlws.FILTER(RAW[Hotel / Resort Name ],RAW[Key]=Sheet2!Q$32,"Not Found"))} -> Hotel maharishi | ... BZ33: {=IF(BZ$32=0,"",_xlfn._xlws.FILTER(RAW[Hotel / Resort Name ],RAW[Key]=Sheet2!BZ$32,"Not Found"))}
A34: =IF(B34="","",_xlfn.XLOOKUP(B34,'Raw'!D:D,'Raw'!B:B)) | C34: =VLOOKUP(B34,RAW[[Hotel Code]:[Hotel / Resort Name ]],2,0) -> #N/A | D34: =$A34&D$21 -> Premium | E34: =$A34&E$21 -> Budget | F34: =$A34&F$21 -> Standard | G34: SitapurPremium | J34: Blessings Resort Deluxe Cottages (Mountain view with private balcony) | K34: Gaurav Hotel | L34: Hotel Laxmi Palace | M34: Parmeshwari Kedarnath (Only 20mts Kedarnath Temple) | N34: Hotel New Pandey Inn | P34: Anand Ganga Ganga View Rooms | Q34: Osho Zenganga Commune | R34: Hotel Sravasti | U34: Narayan Valley Resort | V34: New Basera | W34: Hotel Shiv Manohar | X34: Namami Gange | Y34: Hotel Blue Orchid | AA34: Hotel Battalion 10 AC Super Deluxe | AB34: Hotel Vinayak Executive Room | AD34: Hotel Ajay Palace | AE34: Badri Palace by Namami Gange | AI34: Hotel Vijay Residency | AJ34: Hotel Pinewood (The om Hotels) | AS34: paradise Adventure camp | AT34: Hotel Panchvati Inn Deluxe | AW34: DLS Hotels on the Ganges | AZ34: Prakriti Retreat Premium Room | BC34: Hotel Bhagirathi Residency Super Deluxe Room (Non-AC)
A35: =IF(B35="","",_xlfn.XLOOKUP(B35,'Raw'!D:D,'Raw'!B:B)) | C35: =VLOOKUP(B35,RAW[[Hotel Code]:[Hotel / Resort Name ]],2,0) -> #N/A | D35: =$A35&D$21 -> Premium | E35: =$A35&E$21 -> Budget | F35: =$A35&F$21 -> Standard | G35: SitapurBudget | J35: Blessings Resort Luxury Cottages (Mountain & River view with private balcony) | K35: Buransh Homestay | M35: Raatri Hotels | N35: BIKANER HOUSE | R35: Maa Saraswati Hotel | U35: Neelansh Resort | V35: Hotel New Mandakini River Resort | X35: Abhishek Hotel | Y35: Raatri Hotel Bhanu Palace | AA35: Hotel Mandakini Deluxe Rooms | AB35: Hotel Le Meadows | AD35: Ajay Palace Pipalkoti | AE35: Hotel Neelkanth | AJ35: Hotel Poll Star Inn (The om Hotels) | AT35: Hotel Panchvati Inn Premium | AZ35: Prakriti Retreat Standard | BC35: Hotel Bhagirathi Residency Super Deluxe Room (AC)
A36: =IF(B36="","",_xlfn.XLOOKUP(B36,'Raw'!D:D,'Raw'!B:B)) | C36: =VLOOKUP(B36,RAW[[Hotel Code]:[Hotel / Resort Name ]],2,0) -> #N/A | D36: =$A36&D$21 -> Premium | E36: =$A36&E$21 -> Budget | F36: =$A36&F$21 -> Standard | G36: SitapurStandard | J36: Yamunotri Cottages (Classic) | K36: Blessings Resort Dormitory | M36: Marwar House Hotel | N36: Bagwari House | R36: Hotel Sahaj Villa | V36: Shivalik Valley Resorts | X36: Hotel Namami Gange | Y36: Hotel Samrat Resort | AB36: Hotel Uday Palace | AD36: Hotel Bhawani | AE36: Badriville Resort | AJ36: Hotel Sunrise (Raatri Hotels) | AZ36: Nelangana Resort Deluxe Room
A37: =IF(B37="","",_xlfn.XLOOKUP(B37,'Raw'!D:D,'Raw'!B:B)) | C37: =VLOOKUP(B37,RAW[[Hotel Code]:[Hotel / Resort Name ]],2,0) -> #N/A | D37: =$A37&D$21 -> Premium | E37: =$A37&E$21 -> Budget | F37: =$A37&F$21 -> Standard | G37: RudraprayagPremium | J37: Yamunotri Cottages (Luxury Pine) | K37: Shiv Shakti Eco Resort | M37: Kedarnath Deluxe by K3yaStays | R37: Hotel Narayan Palace | V37: Phulwari Resort Deluxe Room | X37: Shri Narayan Resort | Y37: Hotel Mandakini Superior Rooms | AD37: Hotel Devlok | AE37: Hotel Panchvati Inn | AJ37: RJ Anandam Resort | AZ37: Hotel Royal Hillcrest
A38: =IF(B38="","",_xlfn.XLOOKUP(B38,'Raw'!D:D,'Raw'!B:B)) | C38: =VLOOKUP(B38,RAW[[Hotel Code]:[Hotel / Resort Name ]],2,0) -> #N/A | D38: =$A38&D$21 -> Premium | E38: =$A38&E$21 -> Budget | F38: =$A38&F$21 -> Standard | G38: RudraprayagBudget | K38: Hotel Aakashdeep | R38: Anand Ganga | V38: Phulwari Resort Premium Room | X38: Rumkh Kedar Resort | Y38: Sukoon DK | AD38: Hotel BALBEER PALACE | AE38: Shree Kuber Regency | AJ38: Yamunotri Darshan Resort
A39: =IF(B39="","",_xlfn.XLOOKUP(B39,'Raw'!D:D,'Raw'!B:B)) | C39: =VLOOKUP(B39,RAW[[Hotel Code]:[Hotel / Resort Name ]],2,0) -> #N/A | D39: =$A39&D$21 -> Premium | E39: =$A39&E$21 -> Budget | F39: =$A39&F$21 -> Standard | G39: RudraprayagStandard | K39: Gaurav Hotel | R39: Hotel Suryansh | V39: Phulwari Resort Suite Room 4 Person | AE39: Badrinath Anant Hotel | AJ39: Hotel Om Shivaay Inn
A40: =IF(B40="","",_xlfn.XLOOKUP(B40,'Raw'!D:D,'Raw'!B:B)) | C40: =VLOOKUP(B40,RAW[[Hotel Code]:[Hotel / Resort Name ]],2,0) -> #N/A | D40: =$A40&D$21 -> Premium | E40: =$A40&E$21 -> Budget | F40: =$A40&F$21 -> Standard | G40: PipalkotiPremium | V40: Phulwari Resort Presidential Suite Room | AE40: VijayLord's palace Badrinath
A41: =IF(B41="","",_xlfn.XLOOKUP(B41,'Raw'!D:D,'Raw'!B:B)) | C41: =VLOOKUP(B41,RAW[[Hotel Code]:[Hotel / Resort Name ]],2,0) -> #N/A | D41: =$A41&D$21 -> Premium | E41: =$A41&E$21 -> Budget | F41: =$A41&F$21 -> Standard | G41: PipalkotiBudget | AE41: Suryoday: The Vaikunth Premium King room
A42: =IF(B42="","",_xlfn.XLOOKUP(B42,'Raw'!D:D,'Raw'!B:B)) | C42: =VLOOKUP(B42,RAW[[Hotel Code]:[Hotel / Resort Name ]],2,0) -> #N/A | D42: =$A42&D$21 -> Premium | E42: =$A42&E$21 -> Budget | F42: =$A42&F$21 -> Standard | G42: PipalkotiStandard | AE42: Suryoday: The Vaikunth Mini Cozy Suite
A43: =IF(B43="","",_xlfn.XLOOKUP(B43,'Raw'!D:D,'Raw'!B:B)) | C43: =VLOOKUP(B43,RAW[[Hotel Code]:[Hotel / Resort Name ]],2,0) -> #N/A | D43: =$A43&D$21 -> Premium | E43: =$A43&E$21 -> Budget | F43: =$A43&F$21 -> Standard | G43: BadarinathPremium | AE43: Hotel New Urvashi
A44: =IF(B44="","",_xlfn.XLOOKUP(B44,'Raw'!D:D,'Raw'!B:B)) | C44: =VLOOKUP(B44,RAW[[Hotel Code]:[Hotel / Resort Name ]],2,0) -> #N/A | D44: =$A44&D$21 -> Premium | E44: =$A44&E$21 -> Budget | F44: =$A44&F$21 -> Standard | G44: BadarinathBudget
A45: =IF(B45="","",_xlfn.XLOOKUP(B45,'Raw'!D:D,'Raw'!B:B)) | C45: =VLOOKUP(B45,RAW[[Hotel Code]:[Hotel / Resort Name ]],2,0) -> #N/A | D45: =$A45&D$21 -> Premium | E45: =$A45&E$21 -> Budget | F45: =$A45&F$21 -> Standard | G45: BadarinathStandard
A46: =IF(B46="","",_xlfn.XLOOKUP(B46,'Raw'!D:D,'Raw'!B:B)) | C46: =VLOOKUP(B46,RAW[[Hotel Code]:[Hotel / Resort Name ]],2,0) -> #N/A | D46: =$A46&D$21 -> Premium | E46: =$A46&E$21 -> Budget | F46: =$A46&F$21 -> Standard | G46: BarkotPremium
A47: =IF(B47="","",_xlfn.XLOOKUP(B47,'Raw'!D:D,'Raw'!B:B)) | C47: =VLOOKUP(B47,RAW[[Hotel Code]:[Hotel / Resort Name ]],2,0) -> #N/A | D47: =$A47&D$21 -> Premium | E47: =$A47&E$21 -> Budget | F47: =$A47&F$21 -> Standard | G47: BarkotBudget
A48: =IF(B48="","",_xlfn.XLOOKUP(B48,'Raw'!D:D,'Raw'!B:B)) | C48: =VLOOKUP(B48,RAW[[Hotel Code]:[Hotel / Resort Name ]],2,0) -> #N/A | D48: =$A48&D$21 -> Premium | E48: =$A48&E$21 -> Budget | F48: =$A48&F$21 -> Standard | G48: BarkotStandard
A49: =IF(B49="","",_xlfn.XLOOKUP(B49,'Raw'!D:D,'Raw'!B:B)) | C49: =VLOOKUP(B49,RAW[[Hotel Code]:[Hotel / Resort Name ]],2,0) -> #N/A | D49: =$A49&D$21 -> Premium | E49: =$A49&E$21 -> Budget | F49: =$A49&F$21 -> Standard | G49: PandukeshwarPremium
A50: =IF(B50="","",_xlfn.XLOOKUP(B50,'Raw'!D:D,'Raw'!B:B)) | C50: =VLOOKUP(B50,RAW[[Hotel Code]:[Hotel / Resort Name ]],2,0) -> #N/A | D50: =$A50&D$21 -> Premium | E50: =$A50&E$21 -> Budget | F50: =$A50&F$21 -> Standard | G50: PandukeshwarBudget
A51: =IF(B51="","",_xlfn.XLOOKUP(B51,'Raw'!D:D,'Raw'!B:B)) | C51: =VLOOKUP(B51,RAW[[Hotel Code]:[Hotel / Resort Name ]],2,0) -> #N/A | D51: =$A51&D$21 -> Premium | E51: =$A51&E$21 -> Budget | F51: =$A51&F$21 -> Standard | G51: PandukeshwarStandard
A52: =IF(B52="","",_xlfn.XLOOKUP(B52,'Raw'!D:D,'Raw'!B:B)) | C52: =VLOOKUP(B52,RAW[[Hotel Code]:[Hotel / Resort Name ]],2,0) -> #N/A | D52: =$A52&D$21 -> Premium | E52: =$A52&E$21 -> Budget | F52: =$A52&F$21 -> Standard | G52: GuptkashiPremium
A53: =IF(B53="","",_xlfn.XLOOKUP(B53,'Raw'!D:D,'Raw'!B:B)) | C53: =VLOOKUP(B53,RAW[[Hotel Code]:[Hotel / Resort Name ]],2,0) -> #N/A | D53: =$A53&D$21 -> Premium | E53: =$A53&E$21 -> Budget | F53: =$A53&F$21 -> Standard | G53: GuptkashiBudget
A54: =IF(B54="","",_xlfn.XLOOKUP(B54,'Raw'!D:D,'Raw'!B:B)) | C54: =VLOOKUP(B54,RAW[[Hotel Code]:[Hotel / Resort Name ]],2,0) -> #N/A | D54: =$A54&D$21 -> Premium | E54: =$A54&E$21 -> Budget | F54: =$A54&F$21 -> Standard | G54: GuptkashiStandard
A55: =IF(B55="","",_xlfn.XLOOKUP(B55,'Raw'!D:D,'Raw'!B:B)) | C55: =VLOOKUP(B55,RAW[[Hotel Code]:[Hotel / Resort Name ]],2,0) -> #N/A | D55: =$A55&D$21 -> Premium | E55: =$A55&E$21 -> Budget | F55: =$A55&F$21 -> Standard | G55: ChoptaPremium
... A72: =IF(B72="","",_xlfn.XLOOKUP(B72,'Raw'!D:D,'Raw'!B:B)) | C72: =VLOOKUP(B72,RAW[[Hotel Code]:[Hotel / Resort Name ]],2,0) -> #N/A | D72: =$A72&D$21 -> Premium | E72: =$A72&E$21 -> Budget | F72: =$A72&F$21 -> Standard | G72: HaridwarStandard
A73: =IF(B73="","",_xlfn.XLOOKUP(B73,'Raw'!D:D,'Raw'!B:B)) | C73: =VLOOKUP(B73,RAW[[Hotel Code]:[Hotel / Resort Name ]],2,0) -> #N/A | D73: =$A73&D$21 -> Premium | E73: =$A73&E$21 -> Budget | F73: =$A73&F$21 -> Standard
A74: =IF(B74="","",_xlfn.XLOOKUP(B74,'Raw'!D:D,'Raw'!B:B)) | C74: =VLOOKUP(B74,RAW[[Hotel Code]:[Hotel / Resort Name ]],2,0) -> #N/A | D74: =$A74&D$21 -> Premium | E74: =$A74&E$21 -> Budget | F74: =$A74&F$21 -> Standard
A75: =IF(B75="","",_xlfn.XLOOKUP(B75,'Raw'!D:D,'Raw'!B:B)) | C75: =VLOOKUP(B75,RAW[[Hotel Code]:[Hotel / Resort Name ]],2,0) -> #N/A | D75: =$A75&D$21 -> Premium | E75: =$A75&E$21 -> Budget | F75: =$A75&F$21 -> Standard
A76: =IF(B76="","",_xlfn.XLOOKUP(B76,'Raw'!D:D,'Raw'!B:B)) | C76: =VLOOKUP(B76,RAW[[Hotel Code]:[Hotel / Resort Name ]],2,0) -> #N/A | D76: =$A76&D$21 -> Premium | E76: =$A76&E$21 -> Budget | F76: =$A76&F$21 -> Standard
A77: =IF(B77="","",_xlfn.XLOOKUP(B77,'Raw'!D:D,'Raw'!B:B)) | C77: =VLOOKUP(B77,RAW[[Hotel Code]:[Hotel / Resort Name ]],2,0) -> #N/A | D77: =$A77&D$21 -> Premium | E77: =$A77&E$21 -> Budget | F77: =$A77&F$21 -> Standard
A78: =IF(B78="","",_xlfn.XLOOKUP(B78,'Raw'!D:D,'Raw'!B:B)) | C78: =VLOOKUP(B78,RAW[[Hotel Code]:[Hotel / Resort Name ]],2,0) -> #N/A | D78: =$A78&D$21 -> Premium | E78: =$A78&E$21 -> Budget | F78: =$A78&F$21 -> Standard
A79: =IF(B79="","",_xlfn.XLOOKUP(B79,'Raw'!D:D,'Raw'!B:B)) | C79: =VLOOKUP(B79,RAW[[Hotel Code]:[Hotel / Resort Name ]],2,0) -> #N/A | D79: =$A79&D$21 -> Premium | E79: =$A79&E$21 -> Budget | F79: =$A79&F$21 -> Standard
A80: =IF(B80="","",_xlfn.XLOOKUP(B80,'Raw'!D:D,'Raw'!B:B)) | C80: =VLOOKUP(B80,RAW[[Hotel Code]:[Hotel / Resort Name ]],2,0) -> #N/A | D80: =$A80&D$21 -> Premium | E80: =$A80&E$21 -> Budget | F80: =$A80&F$21 -> Standard
A81: =IF(B81="","",_xlfn.XLOOKUP(B81,'Raw'!D:D,'Raw'!B:B)) | C81: =VLOOKUP(B81,RAW[[Hotel Code]:[Hotel / Resort Name ]],2,0) -> #N/A | D81: =$A81&D$21 -> Premium | E81: =$A81&E$21 -> Budget | F81: =$A81&F$21 -> Standard
A82: =IF(B82="","",_xlfn.XLOOKUP(B82,'Raw'!D:D,'Raw'!B:B)) | C82: =VLOOKUP(B82,RAW[[Hotel Code]:[Hotel / Resort Name ]],2,0) -> #N/A | D82: =$A82&D$21 -> Premium | E82: =$A82&E$21 -> Budget | F82: =$A82&F$21 -> Standard
A83: =IF(B83="","",_xlfn.XLOOKUP(B83,'Raw'!D:D,'Raw'!B:B)) | C83: =VLOOKUP(B83,RAW[[Hotel Code]:[Hotel / Resort Name ]],2,0) -> #N/A | D83: =$A83&D$21 -> Premium | E83: =$A83&E$21 -> Budget | F83: =$A83&F$21 -> Standard
A84: =IF(B84="","",_xlfn.XLOOKUP(B84,'Raw'!D:D,'Raw'!B:B)) | C84: =VLOOKUP(B84,RAW[[Hotel Code]:[Hotel / Resort Name ]],2,0) -> #N/A | D84: =$A84&D$21 -> Premium | E84: =$A84&E$21 -> Budget | F84: =$A84&F$21 -> Standard
... A124: =IF(B124="","",_xlfn.XLOOKUP(B124,'Raw'!D:D,'Raw'!B:B)) | C124: =VLOOKUP(B124,RAW[[Hotel Code]:[Hotel / Resort Name ]],2,0) -> #N/A | D124: =$A124&D$21 -> Premium | E124: =$A124&E$21 -> Budget | F124: =$A124&F$21 -> Standard
A126: =IF(B126="","",_xlfn.XLOOKUP(B126,'Raw'!D:D,'Raw'!B:B))
A127: =IF(B127="","",_xlfn.XLOOKUP(B127,'Raw'!D:D,'Raw'!B:B))
A128: =IF(B128="","",_xlfn.XLOOKUP(B128,'Raw'!D:D,'Raw'!B:B))
A129: =IF(B129="","",_xlfn.XLOOKUP(B129,'Raw'!D:D,'Raw'!B:B))
A130: =IF(B130="","",_xlfn.XLOOKUP(B130,'Raw'!D:D,'Raw'!B:B))
A131: =IF(B131="","",_xlfn.XLOOKUP(B131,'Raw'!D:D,'Raw'!B:B))
A132: =IF(B132="","",_xlfn.XLOOKUP(B132,'Raw'!D:D,'Raw'!B:B))
A133: =IF(B133="","",_xlfn.XLOOKUP(B133,'Raw'!D:D,'Raw'!B:B))
A134: =IF(B134="","",_xlfn.XLOOKUP(B134,'Raw'!D:D,'Raw'!B:B))
A135: =IF(B135="","",_xlfn.XLOOKUP(B135,'Raw'!D:D,'Raw'!B:B))
A136: =IF(B136="","",_xlfn.XLOOKUP(B136,'Raw'!D:D,'Raw'!B:B))
A137: =IF(B137="","",_xlfn.XLOOKUP(B137,'Raw'!D:D,'Raw'!B:B))
... A531: =IF(B531="","",_xlfn.XLOOKUP(B531,'Raw'!D:D,'Raw'!B:B))
