Workbook
Name City: Sheet2!$B$2:$B$10
Name Day_Wise_Exursion: 'Day Wise Exursion'!$B$27:$B$37
Name Header: Sheet2!$H$12:$FH$12
Name MYName: IF(INDEX(Sheet2!$H$13:$FH$19,0,MATCH(Summary!XFD1,Header,0))=0,"",INDEX(Sheet2!$H$13:$FH$19,0,MATCH(Summary!XFD1,Header,0)))
Name Type: INDEX(Sheet2!$H$13:$FH$18,0,MATCH(Summary!$E11,Header,0))

Sheet Summary
D1: https://rateonclick.com/rate
H2: Address: - Shop No. 210, 2nd Floor, Pratap Complex, Metro Gate Number 3, near Munirka, Baba Gangnath Market, Munirka, New Delhi, Delhi 110067 Phone: +91-9870229792, +91-9910987264 Email: info@ghumofiroo.com
D6: Kerala Deluxe Plus Package
D7: =IF(AND(F17<>"", H17<>""), "For " & TEXT(LEFT(F17, FIND(" ", H17)-1), "00") & " Nights " & TEXT(LEFT(H17, FIND(" ", H17)-1), "00") & " Days", "") -> For 07 Nights 08 Days
D8: Travel Itinerary
D9: Welcome to Ghumo Firoo!
D11: This is Navin Kumar Mishra, and I will be working with you to plan your trip to Kerala.
D13: Please find below details for your trip and feel free to call me at +91-9910987264.
D15: Query Details
D16: #Booking Code | F16: Q/25/979949 | H16: Total Guests | K16: 2 | N16: Occupancy Type | O16: Double | P16: SIC Sightseeing | Q16: Honeymoon Inclusions
D17: Trip Duration | F17: =(H37-G37)&" "&"Nights" -> 7 Nights | H17: =DAY(H37-G37)+1&" "&"Days" -> 8 Days | J17: =O17 -> NA | K17: =IF(O16="Double", MOD(K16,2),IF(O16="Triple", MOD(K16,3),IF(O16="Quad", MOD(K16,4), 0))) -> 0 | N17: Passanger Type | O17: NA | P17: Activity 2
D18: Pick Up City | E18: Airport | F18: Drop City | H18: Airport | J18: Start Date | K18: =G37 -> 46178 | P18: Activity 3
D19: Destination Covered | F19: {=_xlfn.TEXTJOIN(", ", TRUE, _xlfn.UNIQUE(_xlfn._xlws.FILTER(D26:D36, D26:D36<>"")))} -> Kochi, Munnar, Thekkady , Varkala, Alleppey | J19: End Date | K19: =H37 -> 46185 | N19: Cab Type | O19: Sedan 4 Seater | P19: Activity 4
D20: Ghumo Firoo Travels: Where dreams become Itineraries, and Bucket-Lists turn into Checklists | P20: Activity 5
N21: Markup | O21: 0.04 | P21: Activity 6
N22: Cost of Markup | O22: =V37*O21 -> 2264 | P22: Activity 7
D24: Package Name: Kerala Deluxe Plus Package | O24: 1 Night/Day Price | T24: Total Price
D25: City | E25: Hotel Name | F25: Room Type | G25: Check-In | H25: Check-Out | I25: Nights | J25: Cab Type | K25: Meal Plan | L25: Rooms | M25: Total Guests | N25: Extra Passanger | O25: Double | P25: Triple | Q25: =IF(O17="NA", "Cost Not Applicable", "Cost of " & O17) -> Cost Not Applicable | R25: Transfer Cost | S25: Excursion Cost | T25: Total Room Price | U25: =IF(O17="NA", "Cost Not Applicable", "Total Cost of " & O17) -> Cost Not Applicable | V25: Total Price | W25: Advance | X25: Balance
A26: =IF(E26="","",E26&"-"&F26&"-"&$O$16&" "&$K26) -> Broad Bean Hotel-Standard Room-Double MAP | B26: =IF(E26="","",E26&"-"&$O$17&"-"&$O$16&" "&$K26) -> Broad Bean Hotel-NA-Double MAP | D26: Kochi | E26: Broad Bean Hotel | F26: Standard Room | G26: =IF(ISNUMBER($G$37), $G$37, "") -> 46178 | H26: =IF(I26=0, "", G26 + I26) -> 46179 | I26: 1 | J26: =IF(E26="","",$O$19) -> Sedan 4 Seater | K26: MAP | L26: =IF(E26="","",IF($O$16="Double", FLOOR($K$16/2, 1), IF($O$16="Triple", FLOOR($K$16/3, 1), 0))) -> 1 | M26: =IF(E26="","",$K$16) -> 2 | N26: =IF(E26="","",$K$17) -> 0 | O26: =IFERROR(IF(E26="","",IF($O$16="Double",VLOOKUP($A26,Price[],2,0),"")),0) -> 4300 | P26: =IFERROR(IF(E26="","",IF($O$16="Triple",VLOOKUP($A26,Price[],2,0),"")),0) | Q26: =IFERROR(IF(E26="","",VLOOKUP($B26,Extra_fare_price[#All],2,0)),0) -> 0 | R26: =IF(OR($O$19="",D26="",I26=""),"",I26 *IF(AND($E$18<>"",$H$18<>""),IF($E$18=$H$18,VLOOKUP($O$19, Price!$J:$L, MATCH(TRIM($E$18), Price!$J$1:$L$1, 0), FALSE),""),IF($E$18<>"",VLOOKUP($O$19, Price!$J:$L, MATCH(TRIM($E$18), Price!$J$1:$L$1, 0), FALSE),IF($H$18<>"",VLOOKUP($O$19, Price!$J:$L, MATCH(TRIM($H$18), Price!$J$1:$L$1, 0), FALSE),"")))) -> 3200 | S26: =IF(Q16="", "", _xlfn.XLOOKUP(Q16, ActivitiesMaster!C:C, ActivitiesMaster!E:E, 0) * $K$16) -> 0 | T26: =IF(E26="","",SUM(O26:P26)*I26*L26) -> 4300 | U26: =IF(E26="","",Q26*I26) -> 0 | V26: =IF(AND(R26="",T26="", U26=""), "", SUM(R26:U26)) -> 7500 | W26: 2000 | X26: =IF(V26="","",V26-W26) -> 5500 | Y26: =IF(V26 = (R26 + S26+T26 + U26), "✅", "❌") -> ✅ | Z26: 3000 | AA26: 18500 | AB26: 999 | AC26: 999 | AD26: =Z26-AB26 -> 2001 | AE26: =AA26-AC26 -> 17501
A27: =IF(E27="","",E27&"-"&F27&"-"&$O$16&" "&$K27) -> Blossom Hill Resort-Valley View Cottage (With Balcony)-Double MAP | B27: =IF(E27="","",E27&"-"&$O$17&"-"&$O$16&" "&$K27) -> Blossom Hill Resort-NA-Double MAP | D27: Munnar | E27: Blossom Hill Resort | F27: Valley View Cottage (With Balcony) | G27: =IF(E27="","",IF(ISNUMBER(H26), H26, "")) -> 46179 | H27: =IF(I27=0, "", G27 + I27) -> 46181 | I27: 2 | J27: =IF(E27="","",$O$19) -> Sedan 4 Seater | K27: MAP | L27: =IF(E27="","",IF($O$16="Double", FLOOR($K$16/2, 1), IF($O$16="Triple", FLOOR($K$16/3, 1), 0))) -> 1 | M27: =IF(E27="","",$K$16) -> 2 | N27: =IF(E27="","",$K$17) -> 0 | O27: =IFERROR(IF(E27="","",IF($O$16="Double",VLOOKUP($A27,Price[],2,0),"")),0) -> 4700 | P27: =IFERROR(IF(E27="","",IF($O$16="Triple",VLOOKUP($A27,Price[],2,0),"")),0) | Q27: =IFERROR(IF(E27="","",VLOOKUP($B27,Extra_fare_price[#All],2,0)),0) -> 0 | R27: =IF(OR($O$19="",D27="",I27=""),"",I27 *IF(AND($E$18<>"",$H$18<>""),IF($E$18=$H$18,VLOOKUP($O$19, Price!$J:$L, MATCH(TRIM($E$18), Price!$J$1:$L$1, 0), FALSE),""),IF($E$18<>"",VLOOKUP($O$19, Price!$J:$L, MATCH(TRIM($E$18), Price!$J$1:$L$1, 0), FALSE),IF($H$18<>"",VLOOKUP($O$19, Price!$J:$L, MATCH(TRIM($H$18), Price!$J$1:$L$1, 0), FALSE),"")))) -> 6400 | S27: =IF(Q17="", "", _xlfn.XLOOKUP(Q17, ActivitiesMaster!C:C, ActivitiesMaster!E:E, 0) * $K$16) | T27: =IF(E27="","",SUM(O27:P27)*I27*L27) -> 9400 | U27: =IF(E27="","",Q27*I27) -> 0 | V27: =IF(AND(R27="",T27="", U27=""), "", SUM(R27:U27)) -> 15800 | W27: 5000 | X27: =IF(V27="","",V27-W27) -> 10800 | Y27: =IF(V27 = (R27 + S27+T27 + U27), "✅", "❌") -> #VALUE! | Z27: 3000 | AB27: 999 | AD27: =Z27-AB27 -> 2001
A28: =IF(E28="","",E28&"-"&F28&"-"&$O$16&" "&$K28) -> Jungle Park Resort-Jungle View Venus (A/c)-Double MAP | B28: =IF(E28="","",E28&"-"&$O$17&"-"&$O$16&" "&$K28) -> Jungle Park Resort-NA-Double MAP | D28: Thekkady | E28: Jungle Park Resort | F28: Jungle View Venus (A/c) | G28: =IF(E28="","",IF(ISNUMBER(H27), H27, "")) -> 46181 | H28: =IF(I28=0, "", G28 + I28) -> 46182 | I28: 1 | J28: =IF(E28="","",$O$19) -> Sedan 4 Seater | K28: MAP | L28: =IF(E28="","",IF($O$16="Double", FLOOR($K$16/2, 1), IF($O$16="Triple", FLOOR($K$16/3, 1), 0))) -> 1 | M28: =IF(E28="","",$K$16) -> 2 | N28: =IF(E28="","",$K$17) -> 0 | O28: =IFERROR(IF(E28="","",IF($O$16="Double",VLOOKUP($A28,Price[],2,0),"")),0) -> 4900 | P28: =IFERROR(IF(E28="","",IF($O$16="Triple",VLOOKUP($A28,Price[],2,0),"")),0) | Q28: =IFERROR(IF(E28="","",VLOOKUP($B28,Extra_fare_price[#All],2,0)),0) -> 0 | R28: =IF(OR($O$19="",D28="",I28=""),"",I28 *IF(AND($E$18<>"",$H$18<>""),IF($E$18=$H$18,VLOOKUP($O$19, Price!$J:$L, MATCH(TRIM($E$18), Price!$J$1:$L$1, 0), FALSE),""),IF($E$18<>"",VLOOKUP($O$19, Price!$J:$L, MATCH(TRIM($E$18), Price!$J$1:$L$1, 0), FALSE),IF($H$18<>"",VLOOKUP($O$19, Price!$J:$L, MATCH(TRIM($H$18), Price!$J$1:$L$1, 0), FALSE),"")))) -> 3200 | S28: =IF(Q18="", "", _xlfn.XLOOKUP(Q18, ActivitiesMaster!C:C, ActivitiesMaster!E:E, 0) * $K$16) | T28: =IF(E28="","",SUM(O28:P28)*I28*L28) -> 4900 | U28: =IF(E28="","",Q28*I28) -> 0 | V28: =IF(AND(R28="",T28="", U28=""), "", SUM(R28:U28)) -> 8100 | W28: 9000 | X28: =IF(V28="","",V28-W28) -> -900 | Y28: =IF(V28 = (R28 + S28+T28 + U28), "✅", "❌") -> #VALUE! | Z28: 8500 | AB28: 999 | AD28: =Z28-AB28 -> 7501
A29: =IF(E29="","",E29&"-"&F29&"-"&$O$16&" "&$K29) -> Sunview Beach Resort & Spa by Citrine-Garden View-Double CP | B29: =IF(E29="","",E29&"-"&$O$17&"-"&$O$16&" "&$K29) -> Sunview Beach Resort & Spa by Citrine-NA-Double CP | D29: Varkala | E29: Sunview Beach Resort & Spa by Citrine | F29: Garden View | G29: =IF(E29="","",IF(ISNUMBER(H28), H28, "")) -> 46182 | H29: =IF(I29=0, "", G29 + I29) -> 46183 | I29: 1 | J29: =IF(E29="","",$O$19) -> Sedan 4 Seater | K29: CP | L29: =IF(E29="","",IF($O$16="Double", FLOOR($K$16/2, 1), IF($O$16="Triple", FLOOR($K$16/3, 1), 0))) -> 1 | M29: =IF(E29="","",$K$16) -> 2 | N29: =IF(E29="","",$K$17) -> 0 | O29: =IFERROR(IF(E29="","",IF($O$16="Double",VLOOKUP($A29,Price[],2,0),"")),0) -> 6500 | P29: =IFERROR(IF(E29="","",IF($O$16="Triple",VLOOKUP($A29,Price[],2,0),"")),0) | Q29: =IFERROR(IF(E29="","",VLOOKUP($B29,Extra_fare_price[#All],2,0)),0) -> 0 | R29: =IFERROR(IF(E29="","",VLOOKUP($O$19,Table2[],2,0)),0) -> 3200 | S29: =IF(Q19="", "", _xlfn.XLOOKUP(Q19, ActivitiesMaster!C:C, ActivitiesMaster!E:E, 0) * $K$16) | T29: =IF(E29="","",SUM(O29:P29)*I29*L29) -> 6500 | U29: =IF(E29="","",Q29*I29) -> 0 | V29: =IF(AND(R29="",T29="", U29=""), "", SUM(R29:U29)) -> 9700 | X29: =IF(V29="","",V29-W29) -> 9700 | Y29: =IF(V29 = (R29 + S29+T29 + U29), "✅", "❌") -> #VALUE! | Z29: 4000 | AB29: 999 | AD29: =Z29-AB29 -> 3001
A30: =IF(E30="","",E30&"-"&F30&"-"&$O$16&" "&$K30) -> Trium Resort & Houseboats-Standard Room Non AC-Double MAP | B30: =IF(E30="","",E30&"-"&$O$17&"-"&$O$16&" "&$K30) -> Trium Resort & Houseboats-NA-Double MAP | D30: Alleppey | E30: Trium Resort & Houseboats | F30: Standard Room Non AC | G30: =IF(E30="","",IF(ISNUMBER(H29), H29, "")) -> 46183 | H30: =IF(I30=0, "", G30 + I30) -> 46184 | I30: 1 | J30: =IF(E30="","",$O$19) -> Sedan 4 Seater | K30: MAP | L30: =IF(E30="","",IF($O$16="Double", FLOOR($K$16/2, 1), IF($O$16="Triple", FLOOR($K$16/3, 1), 0))) -> 1 | M30: =IF(E30="","",$K$16) -> 2 | N30: =IF(E30="","",$K$17) -> 0 | O30: =IFERROR(IF(E30="","",IF($O$16="Double",VLOOKUP($A30,Price[],2,0),"")),0) -> 2900 | P30: =IFERROR(IF(E30="","",IF($O$16="Triple",VLOOKUP($A30,Price[],2,0),"")),0) | Q30: =IFERROR(IF(E30="","",VLOOKUP($B30,Extra_fare_price[#All],2,0)),0) -> 0 | R30: =IFERROR(IF(E30="","",VLOOKUP($O$19,Table2[],2,0)),0) -> 3200 | S30: =IF(Q20="", "", _xlfn.XLOOKUP(Q20, ActivitiesMaster!C:C, ActivitiesMaster!E:E, 0) * $K$16) | T30: =IF(E30="","",SUM(O30:P30)*I30*L30) -> 2900 | U30: =IF(E30="","",Q30*I30) -> 0 | V30: =IF(AND(R30="",T30="", U30=""), "", SUM(R30:U30)) -> 6100 | W30: =IF(E30="","",Q30*I30) -> 0 | X30: =IF(V30="","",V30-W30) -> 6100 | Y30: =IF(V30 = (R30 + S30+T30 + U30), "✅", "❌") -> #VALUE! | Z30: 4000 | AB30: 999 | AD30: =Z30-AB30 -> 3001
A31: =IF(E31="","",E31&"-"&F31&"-"&$O$16&" "&$K31) -> Symphony Houseboats-A Day Cruise without room Checkin 1pm to Checkout 5:30pm same day ,Veg-Double CP | B31: =IF(E31="","",E31&"-"&$O$17&"-"&$O$16&" "&$K31) -> Symphony Houseboats-NA-Double CP | D31: Alleppey | E31: Symphony Houseboats | F31: A Day Cruise without room Checkin 1pm to Checkout 5:30pm same day ,Veg | G31: =IF(E31="","",IF(ISNUMBER(H30), H30, "")) -> 46184 | H31: =IF(I31=0, "", G31 + I31) -> 46185 | I31: 1 | J31: =IF(E31="","",$O$19) -> Sedan 4 Seater | K31: CP | L31: =IF(E31="","",IF($O$16="Double", FLOOR($K$16/2, 1), IF($O$16="Triple", FLOOR($K$16/3, 1), 0))) -> 1 | M31: =IF(E31="","",$K$16) -> 2 | N31: =IF(E31="","",$K$17) -> 0 | O31: =IFERROR(IF(E31="","",IF($O$16="Double",VLOOKUP($A31,Price[],2,0),"")),0) -> 3000 | P31: =IFERROR(IF(E31="","",IF($O$16="Triple",VLOOKUP($A31,Price[],2,0),"")),0) | Q31: =IFERROR(IF(E31="","",VLOOKUP($B31,Extra_fare_price[#All],2,0)),0) -> 0 | R31: =IFERROR(IF(E31="","",VLOOKUP($O$19,Table2[],2,0)),0) -> 3200 | S31: =IF(Q21="", "", _xlfn.XLOOKUP(Q21, ActivitiesMaster!C:C, ActivitiesMaster!E:E, 0) * $K$16) | T31: =IF(E31="","",SUM(O31:P31)*I31*L31) -> 3000 | U31: =IF(E31="","",Q31*I31) -> 0 | V31: =IF(AND(R31="",T31="", U31=""), "", SUM(R31:U31)) -> 6200 | W31: =IF(E31="","",Q31*I31) -> 0 | X31: =IF(V31="","",V31-W31) -> 6200 | Y31: =IF(V31 = (R31 + S31+T31 + U31), "✅", "❌") -> #VALUE!
A32: =IF(E32="","",E32&"-"&F32&"-"&$O$16&" "&$K32) | B32: =IF(E32="","",E32&"-"&$O$17&"-"&$O$16&" "&$K32) | G32: =IF(E32="","",IF(ISNUMBER(H31), H31, "")) | H32: =IF(I32=0, "", G32 + I32) | J32: =IF(E32="","",$O$19) | L32: =IF(E32="","",IF($O$16="Double", FLOOR($K$16/2, 1), IF($O$16="Triple", FLOOR($K$16/3, 1), 0))) | M32: =IF(E32="","",$K$16) | N32: =IF(E32="","",$K$17) | O32: =IFERROR(IF(E32="","",IF($O$16="Double",VLOOKUP($A32,Price[],2,0),"")),0) | P32: =IFERROR(IF(E32="","",IF($O$16="Triple",VLOOKUP($A32,Price[],2,0),"")),0) | Q32: =IFERROR(IF(E32="","",VLOOKUP($B32,Extra_fare_price[#All],2,0)),0) | R32: =IFERROR(IF(E32="","",VLOOKUP($O$19,Table2[],2,0)),0) | S32: =IF(Q22="", "", _xlfn.XLOOKUP(Q22, ActivitiesMaster!C:C, ActivitiesMaster!E:E, 0) * $K$16) | T32: =IF(E32="","",SUM(O32:P32)*I32*L32) | U32: =IF(E32="","",Q32*I32) | V32: =IF(AND(R32="",T32="", U32=""), "", SUM(R32:U32)) | W32: =IF(E32="","",Q32*I32) | X32: =IF(V32="","",V32-W32) | Y32: =IF(V32 = (R32 + S32+T32 + U32), "✅", "❌") -> #VALUE!
A33: =IF(E33="","",E33&"-"&F33&"-"&$O$16&" "&$K33) | B33: =IF(E33="","",E33&"-"&$O$17&"-"&$O$16&" "&$K33) | G33: =IF(E33="","",IF(ISNUMBER(H32), H32, "")) | H33: =IF(I33=0, "", G33 + I33) | J33: =IF(E33="","",$O$19) | L33: =IF(E33="","",IF($O$16="Double", FLOOR($K$16/2, 1), IF($O$16="Triple", FLOOR($K$16/3, 1), 0))) | M33: =IF(E33="","",$K$16) | N33: =IF(E33="","",$K$17) | O33: =IFERROR(IF(E33="","",IF($O$16="Double",VLOOKUP($A33,Price[],2,0),"")),0) | P33: =IFERROR(IF(E33="","",IF($O$16="Triple",VLOOKUP($A33,Price[],2,0),"")),0) | Q33: =IFERROR(IF(E33="","",VLOOKUP($B33,Extra_fare_price[#All],2,0)),0) | R33: =IFERROR(IF(E33="","",VLOOKUP($O$19,Table2[],2,0)),0) | T33: =IF(E33="","",SUM(O33:P33)*I33*L33) | U33: =IF(E33="","",Q33*I33) | V33: =IF(AND(R33="",T33="", U33=""), "", SUM(R33:U33)) | W33: =IF(E33="","",Q33*I33) | X33: =IF(V33="","",V33-W33) | Y33: =IF(V33 = (R33 + S33+T33 + U33), "✅", "❌") -> #VALUE!
A34: =IF(E34="","",E34&"-"&F34&"-"&$O$16&" "&$K34) | B34: =IF(E34="","",E34&"-"&$O$17&"-"&$O$16&" "&$K34) | G34: =IF(E34="","",IF(ISNUMBER(H33), H33, "")) | H34: =IF(I34=0, "", G34 + I34) | J34: =IF(E34="","",$O$19) | L34: =IF(E34="","",IF($O$16="Double", FLOOR($K$16/2, 1), IF($O$16="Triple", FLOOR($K$16/3, 1), 0))) | M34: =IF(E34="","",$K$16) | N34: =IF(E34="","",$K$17) | O34: =IFERROR(IF(E34="","",IF($O$16="Double",VLOOKUP($A34,Price[],2,0),"")),0) | P34: =IFERROR(IF(E34="","",IF($O$16="Triple",VLOOKUP($A34,Price[],2,0),"")),0) | Q34: =IFERROR(IF(E34="","",VLOOKUP($B34,Extra_fare_price[#All],2,0)),0) | R34: =IFERROR(IF(E34="","",VLOOKUP($O$19,Table2[],2,0)),0) | T34: =IF(E34="","",SUM(O34:P34)*I34*L34) | U34: =IF(E34="","",Q34*I34) | V34: =IF(AND(R34="",T34="", U34=""), "", SUM(R34:U34)) | W34: =IF(E34="","",Q34*I34) | X34: =IF(V34="","",V34-W34) | Y34: =IF(V34 = (R34 + S34+T34 + U34), "✅", "❌") -> #VALUE!
A35: =IF(E35="","",E35&"-"&F35&"-"&$O$16&" "&$K35) | B35: =IF(E35="","",E35&"-"&$O$17&"-"&$O$16&" "&$K35) | G35: =IF(E35="","",IF(ISNUMBER(H34), H34, "")) | I35: =IF(E35="","",DAY(H35-G35)) | J35: =IF(E35="","",$O$19) | L35: =IF(E35="","",IF($O$16="Double", FLOOR($K$16/2, 1), IF($O$16="Triple", FLOOR($K$16/3, 1), 0))) | M35: =IF(E35="","",$K$16) | N35: =IF(E35="","",$K$17) | O35: =IFERROR(IF(E35="","",IF($O$16="Double",VLOOKUP($A35,Price[],2,0),"")),0) | P35: =IFERROR(IF(E35="","",IF($O$16="Triple",VLOOKUP($A35,Price[],2,0),"")),0) | Q35: =IFERROR(IF(E35="","",VLOOKUP($B35,Extra_fare_price[#All],2,0)),0) | R35: =IFERROR(IF(E35="","",VLOOKUP($O$19,Table2[],2,0)),0) | T35: =IF(E35="","",SUM(O35:P35)*I35*L35) | U35: =IF(E35="","",Q35*I35) | V35: =IF(AND(R35="",T35="", U35=""), "", SUM(R35:U35)) | W35: =IF(E35="","",Q35*I35) | X35: =IF(V35="","",V35-W35) | Y35: =IF(V35 = (R35 + S35+T35 + U35), "✅", "❌") -> #VALUE!
A36: =IF(E36="","",E36&"-"&F36&"-"&$O$16&" "&$K36) | B36: =IF(E36="","",E36&"-"&$O$17&"-"&$O$16&" "&$K36) | G36: =IF(E36="","",IF(ISNUMBER(H35), H35, "")) | I36: =IF(E36="","",DAY(H36-G36)) | J36: =IF(E36="","",$O$19) | L36: =IF(E36="","",IF($O$16="Double", FLOOR($K$16/2, 1), IF($O$16="Triple", FLOOR($K$16/3, 1), 0))) | M36: =IF(E36="","",$K$16) | N36: =IF(E36="","",$K$17) | O36: =IFERROR(IF(E36="","",IF($O$16="Double",VLOOKUP($A36,Price[],2,0),"")),0) | P36: =IFERROR(IF(E36="","",IF($O$16="Triple",VLOOKUP($A36,Price[],2,0),"")),0) | Q36: =IFERROR(IF(E36="","",VLOOKUP($B36,Extra_fare_price[#All],2,0)),0) | R36: =IFERROR(IF(E36="","",VLOOKUP($O$19,Table2[],2,0)),0) | V36: =IF(AND(R36="",T36="", U36=""), "", SUM(R36:U36)) | X36: =IF(V36="","",V36-W36) | Y36: =IF(V36 = (R36 + S36+T36 + U36), "✅", "❌") -> #VALUE!
D37: Total Duration of Stay | G37: 46178 | H37: =IF(AND(ISNUMBER(G37), ISNUMBER(I37)), G37 + I37, "") -> 46185 | I37: =SUM(I26:I36) -> 7 | O37: =SUM(O26:O36) -> 26300 | P37: =SUM(P26:P36) -> 0 | Q37: =SUM(Q26:Q36) -> 0 | R37: =SUM(R26:R36)+IF(OR($O$19="",R26=""),"",VLOOKUP($O$19,Price!$J:$L,MATCH(TRIM($E$18),Price!$J$1:$L$1,0),FALSE)) -> 25600 | S37: =SUM(S26:S36) -> 0 | T37: =SUM(T26:T36) -> 31000 | U37: =SUM(U26:U36) -> 0 | V37: =SUM(R37:U37) -> 56600 | W37: =SUM(W26:W36) -> 16000 | X37: =SUM(X26:X36) -> 37400 | Y37: =IF(V37 = (R37 +S37+ T37 + U37), "✅", "❌") -> ✅
N38: Total Cost | R38: =SUM(R37:U37) -> 56600 | U38: =IF(V37 = (R37 + S37+T37 + U37), "✅", "❌") -> ✅
D39: Package Price Details
D40: Pax Type | F40: Total Guest | H40: Cost Per Guest Per Night | K40: Grand Total Cost | N40: Total Cost
D41: Total Adult or Child | F41: =K16-K17 -> 2 | H41: =(K41/F41)/$I$37 -> 4204.5714 | K41: =(N41*$O$21)+N41 -> 58864 | N41: =(R37/$F$43)*F41+T37 -> 56600
D42: Cost of Extra Adult Passenger/Child | F42: =$K$17 -> 0 | H42: =IF(F42=0, 0, K42/F42/$I$37) -> 0 | K42: =(N42*$O$21)+N42 -> 0 | N42: =(R37/$F$43)*F42+U37 -> 0
D43: Final Package Amount | F43: =SUM(F41:F42) -> 2 | H43: =K43/(F43*$I$37) -> 4204.5714 | K43: =K41+K42 -> 58864 | N43: =N41+N42 -> 56600
D44: Per Passenger Cost | H44: =K43/F43 -> 29432 | N44: =K43-N43 -> 2264
D45: IMPORTANT PACKAGES INFORMATION
D46: Packages Inclusion | H46: Packages Exclusion
D47: =IF(I37<>"","1. " & TEXT(I37,"00") & " nights’ stay at the hotels specified in the itinerary.","") -> 1. 07 nights’ stay at the hotels specified in the itinerary. | H47: 1. Extra Meals, Drinks & things not mentioned in including.
D48: =IF(COUNTA(K26:K36)=0, "","2. Meals included: "& TEXT((COUNTIF(K26:K36,"CP")+COUNTIF(K26:K36,"MAP")+COUNTIF(K26:K36,"AP"))*I26,"00") & " breakfast" & IF(COUNTIF(K26:K36,"AP")>0, ", " & TEXT(COUNTIF(K26:K36,"AP")*I26, "00") & " lunch", "") & IF((COUNTIF(K26:K36,"MAP")+COUNTIF(K26:K36,"AP"))>0, " and " & TEXT((COUNTIF(K26:K36,"MAP")+COUNTIF(K26:K36,"AP"))*I26,"00") & " dinner", "") & IF(COUNTIF(K26:K36,"EP")=COUNTA(K26:K36), "No meals", "") & ", as per the selected meal plan.") -> 2. Meals included: 06 breakfast and 04 dinner, as per the selected meal plan. | H48: 2. Guide / Entry Fees / Cable Car / Ropeway
D49: {=_xlfn.LET(_xlpm.list, _xlfn._xlws.FILTER(Q16:Q22,(Q16:Q22<>"")*(Q16:Q22<>"NA"),""),_xlpm.n,SUMPRODUCT(--(_xlpm.list<>"")),_xlpm.veh, O19,IF(OR(_xlpm.veh="",_xlpm.veh="NA"),"","3. All transfers and sightseeing as per the itinerary" & IF(_xlpm.n=0,"", " (" & IF(_xlpm.n=1, INDEX(_xlpm.list,1),_xlfn.TEXTJOIN(", ",TRUE,INDEX(_xlpm.list,_xlfn.SEQUENCE(_xlpm.n-1))) & " and " & INDEX(_xlpm.list,_xlpm.n) ) & ")" ) & " by " & _xlpm.veh & ". Air-conditioned vehicle provided in non-hill areas only." ) )} -> 3. All transfers and sightseeing as per the itinerary (Honeymoon Inclusions) by Sedan 4 Seater. Air-conditioned vehicle provided in non-hill areas only. | H49: 3. Adventure activities: Rafting / Bungy / Paragliding / Rope Activities / Boat Ride / Jungle Safari.
D50: {=_xlfn.LET(_xlpm.activity, Q16,_xlpm.desc, IF(OR(_xlpm.activity="", _xlpm.activity="NA"), "", _xlfn.XLOOKUP(TRIM(_xlpm.activity), TRIM(ActivitiesMaster!C:C), ActivitiesMaster!D:D, "")), IF(_xlpm.desc="", "", "4. " & _xlpm.desc) )} -> 4. ABC | H50: 4. Air / Train / Helicopter Tickets unless mentioned.
D51: {=_xlfn.LET( _xlpm.activity, Q17, _xlpm.desc, IF(OR(_xlpm.activity="", _xlpm.activity="NA"), "", _xlfn.XLOOKUP(TRIM(_xlpm.activity), TRIM(ActivitiesMaster!C:C), ActivitiesMaster!D:D, "")), IF(_xlpm.desc="", "", "5. " & _xlpm.desc) )} | H51: 5. Horse / Porter etc for Trekking.
D52: {=_xlfn.LET( _xlpm.activity, Q18, _xlpm.desc, IF(OR(_xlpm.activity="", _xlpm.activity="NA"), "", _xlfn.XLOOKUP(TRIM(_xlpm.activity), TRIM(ActivitiesMaster!C:C), ActivitiesMaster!D:D, "")), IF(_xlpm.desc="", "", "5. " & _xlpm.desc) )} | H52: 6. Travel & Medical Insurance.
D53: {=_xlfn.LET( _xlpm.activity, Q19, _xlpm.desc, IF(OR(_xlpm.activity="", _xlpm.activity="NA"), "", _xlfn.XLOOKUP(TRIM(_xlpm.activity), TRIM(ActivitiesMaster!C:C), ActivitiesMaster!D:D, "")), IF(_xlpm.desc="", "", "5. " & _xlpm.desc) )}
D54: {=_xlfn.LET( _xlpm.activity, Q20, _xlpm.desc, IF(OR(_xlpm.activity="", _xlpm.activity="NA"), "", _xlfn.XLOOKUP(TRIM(_xlpm.activity), TRIM(ActivitiesMaster!C:C), ActivitiesMaster!D:D, "")), IF(_xlpm.desc="", "", "5. " & _xlpm.desc) )}
D55: {=_xlfn.LET( _xlpm.activity, Q21, _xlpm.desc, IF(OR(_xlpm.activity="", _xlpm.activity="NA"), "", _xlfn.XLOOKUP(TRIM(_xlpm.activity), TRIM(ActivitiesMaster!C:C), ActivitiesMaster!D:D, "")), IF(_xlpm.desc="", "", "5. " & _xlpm.desc) )}
D56: {=_xlfn.LET( _xlpm.activity, Q22, _xlpm.desc, IF(OR(_xlpm.activity="", _xlpm.activity="NA"), "", _xlfn.XLOOKUP(TRIM(_xlpm.activity), TRIM(ActivitiesMaster!C:C), ActivitiesMaster!D:D, "")), IF(_xlpm.desc="", "", "5. " & _xlpm.desc) )}
D57: KINDLY NOTE ALL THE PICK UP IS ON SIC BASIS & LOCATION ARE (Baga, Calangute, Candolim & Arpora)
D58: FOLLOWING YOUR DAY WISE SCHEDULED ITINERARY FOR THIS TOUR.
D60: Day 1: | E60: Arrival at Cochin & Transfer to Munnar + Munnar Sightseeing
D62: =_xlfn.XLOOKUP(E$60,'Day Wise Exursion'!$B:$B,'Day Wise Exursion'!$C:$C) -> Upon arrival in Cochin, proceed to Munnar for a day of sightseeing. Start with a visit to Mattupetty Dam (additional ticket fee applies), a concrete gravity dam nestled in the mountains. Mattupetty offers a captivating blend of natural beauty, featuring sprawling tea plantations, rolling grasslands, and lush Shola forests. These forests are perfect for trekking and serve as a habitat for a wide variety of birds. Later visit Kundala Dam (ticket price extra), the famous Neela Kurunji flowers which bloom once in twelve years, bloom in the hills and valleys around Kundala lake. Enroute visit Echo Point & Pothamedu View Point. Echo Point always has a greenish look as it is covered with abundant green sceneries. View Point is perfect to enjoy the spectacular beauty of the coffee, tea & cardamom plantations. They are an adventurous destination, which will be a perfect choice for those who love to have a nature walk or trekking. Overnight stay at Hotel.
D64: Day 2: | E64: Munnar Full Day Sightseeing Tour
D66: =_xlfn.XLOOKUP(E$64,'Day Wise Exursion'!$B:$B,'Day Wise Exursion'!$C:$C) -> After breakfast proceed for sightseeing of Munnar. Visit Eravikulam National Park (ticket price extra) Closed for Jan 2025 till March 2025 & Mattupetty Dam (ticket price extra), a storage concrete gravity dam built in the mountains. Mattupetty offers many fascinating sights to relish. Besides the tea plantations & the rolling grasslands, the Shola forests in and around Mattupetty are ideal for trekking and are habitat to a variety of birds. Later visit Kundala Dam (ticket price extra), the famous Neela Kurunji flowers which bloom once in twelve years, bloom in the hills and valleys around Kundala lake. Enroute visit Echo Point & Pothamedu View Point. Echo Point always has a greenish look as it is covered with abundant green sceneries. View Point is perfect to enjoy the spectacular beauty of the coffee, tea & cardamom plantations. They are an adventurous destination, which will be a perfect choice for those who love to have a nature walk or trekking. Overnight stay at Hotel.
D68: Day 3: | E68: Transfer from Munnar to Thekkady - (85 Kms - Approx 3 Hrs)
D70: =_xlfn.XLOOKUP(E$68,'Day Wise Exursion'!$B:$B,'Day Wise Exursion'!$C:$C) -> After breakfast, check out from hotel & proceed to Thekkady. Thekkady is considered as a heaven for natural spices. The Periyar forests of Thekkady is one of the finest wildlife reserves in India. Periyar encompasses 777 sq km & a 26-sq-km artificial lake. Check-in at hotel & later head out for sightseeing to visit the Periyar Wildlife Sanctuary (ticket price extra), it is home to herds of wild Elephants, Sambar, Tigers, Gaur, Lion-tailed Macaques, Nilgiri Langurs & more. The place can sometimes feel a bit like Disneyland-in-the-Ghats, but its mountain scenery & jungle walks make for an enjoyable visit. Evening enjoy the boat cruise in the lake (at additional cost) to spot wild animals. Overnight stay at Hotel.
D72: Day 4: | E72: Transfer from Thekkady to Alleppey - (135 Kms - Approx 4 Hrs)
D74: =_xlfn.XLOOKUP(E$72,'Day Wise Exursion'!$B:$B,'Day Wise Exursion'!$C:$C) -> After breakfast, check out from hotel and proceed to Alleppey which has an immense natural beauty and is also known as the “Venice of the East”. It is famous for backwater cruising and boat race. Check into your hotel/houseboat & cruise (if staying in houseboat) through the Narrow Canal amidst the Paddy Fields, Coconut Lagoons and Coir Villages in Alleppey. Overnight stay in Alleppey.
D76: Day 5: | E76: Day Trip to Jatayu Earth Centre
D78: =_xlfn.XLOOKUP(E$76,'Day Wise Exursion'!$B:$B,'Day Wise Exursion'!$C:$C) -> After breakfast in the morning, proceed for Jatayu earth's center located at a small village called Chadayamangalam in Kollam (around 65 kms from Kovalam). Its assumed that this is the place where – Jatayu, a demi-god of Hindu epic "Ramayana" having the form of a vulture, fought with Ravana - multi headed demon king of Lanka (now Sri Lanka) to prevent kidnapping of Goddess Sita, and got slain off one of his wing. The giant concrete statue of Jatayu is built on a mighty rock named Jatayupara (para means rock in Malayalam). The colossal statue is 200 feet long, 150 feet wide and 70 feet making is the largest functional bird sculpture in the world. You can take a cable car ride (on supplementary cost) to visit the Jatayu statue, audio visual museum and mini theatre. Cable car can be booked online in advance. Jatayu earth's center is spread across four hills in Chadayamangalam. The Jatayu Rock Hill represents the safety of women and their honour. The Adventure Rock Hill offers many adventure activities and nature walk. Adventure activities (all on supplementary cost) include paintball, rifle shooting, chimney climbing, rappelling, bouldering, etc. At Elephant Rock Hill, you can enjoy an overnight stay here in tented camps. The spot offers zip-lining, campfire, live music and kitchen, etc. The fourth hill, The Kitchen Rock Hill, provides a ten-day Siddha rejuvenation package.
D80: Day 6: | E80: Transfer to Trivandrum + Sightseeing of Trivandrum + Departure from Trivandrum
D82: =_xlfn.XLOOKUP(E$80,'Day Wise Exursion'!$B:$B,'Day Wise Exursion'!$C:$C) -> After breakfast, proceed for sightseeing of Trivandrum. Visit Sri Padmanabhaswamy Temple (260 yrs old) - the most religious icon of the city built by the Travancore Royal family, here the deity Padmanabha reclines on the sacred serpent & is made from over 10,000 salagramam (sacred stones) that were transported from Nepal by elephant. Secondly, visit Puthe Maliga Palace Museum (ticket price extra) - a 200 year old palace which has carved wooden ceilings, marble sculptures & imported Belgian glass. Inside you'll find Kathakali images, an armoury, portraits of maharajas, ornate thrones & other artefacts. Later proceed to Veli Tourist Village, a beautiful & popular picnic spot well-known because of its serenity, the Lake that meets the Arabian Sea. The main attraction of Veli Tourist Village is a floating bridge that has been erected at this place. The place also has a floating restaurant that gives you an amazing array of food products which might match your taste buds. By evening proceed to Shankumugham Beach, the beach is well known for its breathtaking sunset view which is such memorable moment whose beauty will refresh your mind. The beautiful sculpture of a mermaid is a major attraction here, this giant statue is more than 35m long. Later transfer to Trivandrum airport/railway station for departure, back to home with beautiful memories of God's Own Country
D84: Day 7: | E84: Day Sightseeing of Kanyakumari
D86: =_xlfn.XLOOKUP(E$84,'Day Wise Exursion'!$B:$B,'Day Wise Exursion'!$C:$C) -> After breakfast, embark on a scenic drive to Kanyakumari, a town enveloped by majestic hills and scenic sea-shores, adorned with coconut trees and lush paddy fields. En route, make a stop at Suchindram, a sacred site situated along the banks of the river Pazhayar. In Kanyakumari, pay a visit to the Vivekananda Rock Memorial (entrance fee required), a revered monument believed to be the site where Goddess Kanyakumari undertook her Tapas. Next, explore the Thiruvalluvar Statue, a monumental tribute to Thiruvalluvar. The pedestal of the statue stands at 38 feet tall, while the statue itself towers at 95 feet, making for a grand total of 133 feet for the entire sculpture. In the evening, return to Kovalam for an overnight stay at your hotel.
D88: Day 8: | E88: Munnar Full Day Sightseeing Tour
D90: =_xlfn.XLOOKUP(E$88,'Day Wise Exursion'!$B:$B,'Day Wise Exursion'!$C:$C) -> After breakfast proceed for sightseeing of Munnar. Visit Eravikulam National Park (ticket price extra) Closed for Jan 2025 till March 2025 & Mattupetty Dam (ticket price extra), a storage concrete gravity dam built in the mountains. Mattupetty offers many fascinating sights to relish. Besides the tea plantations & the rolling grasslands, the Shola forests in and around Mattupetty are ideal for trekking and are habitat to a variety of birds. Later visit Kundala Dam (ticket price extra), the famous Neela Kurunji flowers which bloom once in twelve years, bloom in the hills and valleys around Kundala lake. Enroute visit Echo Point & Pothamedu View Point. Echo Point always has a greenish look as it is covered with abundant green sceneries. View Point is perfect to enjoy the spectacular beauty of the coffee, tea & cardamom plantations. They are an adventurous destination, which will be a perfect choice for those who love to have a nature walk or trekking. Overnight stay at Hotel.
D92: Day 9: | E92: Sightseeing of Trivandrum & Return to Kovalam (16 Kms - Approx 30 Mins)
D94: =_xlfn.XLOOKUP(E$92,'Day Wise Exursion'!$B:$B,'Day Wise Exursion'!$C:$C) -> After breakfast proceed for sightseeing of Trivandrum, city of the Holy Ananth which is named after Ananthan, the cosmic serpent with a thousand heads. Visit Sri Padmanabhaswamy Temple (260 yrs old) - the most religious icon of the city built by the Travancore Royal family, here the deity Padmanabha reclines on the sacred serpent & is made from over 10,000 salagramam (sacred stones) that were transported from Nepal by elephant. Secondly, visit Puthe Maliga Palace Museum (ticket price extra) - a 200 year old palace which has carved wooden ceilings, marble sculptures & imported Belgian glass. Inside you'll find Kathakali images, an armoury, portraits of maharajas, ornate thrones & other artefacts. Later proceed to Veli Tourist Village, a beautiful & popular picnic spot well-known because of its serenity, the Lake that meets the Arabian Sea. The main attraction of Veli Tourist Village is a floating bridge that has been erected at this place. The place also has a floating restaurant that gives you an amazing array of food products which might match your taste buds. By evening proceed to Shankumugham Beach, the beach is well known for its breathtaking sunset view which is such memorable moment whose beauty will refresh your mind. The beautiful sculpture of a mermaid is a major attraction here, this giant statue is more than 35m long. Later return to Kovalam. Overnight stay at the Hotel. less Sree Padmanabhaswamy Temple, Shanghumukham Beach, Veli Tourist Village, Kuthiramalika Palace Museum are also covered on Day 7 (Transfer to Trivandrum + Sightseeing of Trivandrum + Departure from Trivandrum); Kuthiramalika Palace Museum - Closed
D96: Day 10: | E96: Transfer from Alleppey to Kovalam (160 Kms - Approx 4.5 Hrs) Via Poovar
D98: =_xlfn.XLOOKUP(E$96,'Day Wise Exursion'!$B:$B,'Day Wise Exursion'!$C:$C) -> After breakfast check out from hotel & proceed to Trivandrum, city of the Holy Ananth which is named after Ananthan, the cosmic serpent with a thousand heads. Visit Sri Padmanabhaswamy Temple (260 yrs old) - the most religious icon of the city built by the Travancore Royal family, here the deity Padmanabha reclines on the sacred serpent & is made from over 10,000 salagramam (sacred stones) that were transported from Nepal by elephant. Poovar is one among the natural wonders where the Lake, River, Sea and Beach meet the land. A rare find in Kerala. Poovar is basically a fishing village and the only way to reach Poovar is through water, it is known for its pristine and virginal beauty, Poovar Beach is haunted by those who love solitude. Later proceed to Kovalam. Kovalam is an internationally renowned beach destination with three adjacent crescent beaches & also known as the "Paradise of the South". On arrival check in at the hotel & relax for a while amidst the comforts of your room. By evening explore on your own to see how the everlasting sea touches the everlasting sky. Kovalam is the place where one can see the golden sand at the day time & silver sand in the night, with high rock promontory & a calm bay of blue waters, this beach paradise creates a unique aquarelle on moonlight nights. Overnight stay at Hotel.
D100: Terms and Conditions for Sale of Tour Packages
D102: 1. All quotations provided by the company are subject to availability of hotel rooms/cruise cabins, services and/or flights at the time of processing the reservation. At the time of reservation, the prices might change without prior notice.
D104: 2. All services provided by the Company are subject to full realization of payment before departure.
D106: 3. Bookings for Travel inside 30 Days or sooner 100% Full payment required.
D108: 4. This quote is valid till 48 hours of issuance date
D110: Terms and Conditions

Sheet Raw
B2: Destination | C2: Hotel Code | D2: Hotel / Resort Name | E2: Room Type | F2: Double EP | G2: Double CP | H2: Double MAP | I2: Double AP | J2: Triple EP | K2: Triple CP | L2: Triple MAP | M2: Triple AP
B3: Alleppey | C3: KL1 | D3: Venice Iva Residency | E3: Deluxe Room | G3: 3900 | H3: 5100
B4: Thekkady | C4: KL2 | D4: The Elephant Court | E4: Patio | G4: 7200 | H4: 9100 | I4: 13500
B5: Thekkady | C5: KL3 | D5: The Elephant Court | E5: Honeymoon Suite | G5: 9500 | H5: 11400 | I5: 15800
B6: Thekkady | C6: KL4 | D6: The Elephant Court | E6: Garden Suite | G6: 12000 | H6: 13900 | I6: 18300
B7: Thekkady | C7: KL5 | D7: The Elephant Court | E7: Pool Studio | G7: 14500 | H7: 16400 | I7: 20800
B8: Thekkady | C8: KL6 | D8: The Elephant Court | E8: Extra Adult passenger | G8: 2000 | H8: 2950 | I8: 3950
B9: Thekkady | C9: KL7 | D9: The Elephant Court | E9: Child with bed | G9: 1250 | H9: 1700 | I9: 2150
B10: Thekkady | C10: KL8 | D10: The Elephant Court | E10: Child without bed | G10: 700 | H10: 1150 | I10: 1600
B11: Thekkady | C11: KL9 | D11: Peppervine | E11: Deluxe Room | G11: 4300 | H11: 5700 | I11: 7100
B12: Thekkady | C12: KL10 | D12: Peppervine | E12: Suite Room | G12: 5300 | H12: 6700 | I12: 8100
B13: Thekkady | C13: KL11 | D13: Peppervine | E13: Extra Adult passenger | G13: 1500 | H13: 2200 | I13: 2900
B14: Thekkady | C14: KL12 | D14: Peppervine | E14: Child with bed | G14: 950 | H14: 1300 | I14: 1650
B15: Thekkady | C15: KL13 | D15: Peppervine | E15: Child without bed | G15: 500 | H15: 850 | I15: 1200
... B53: Munnar | C53: KL53 | D53: Tea castle resort | E53: Child without bed | G53: 700 | H53: 1200 | I53: 1700
B54: Munnar | C54: KL54 | D54: The Breeze Resort | E54: Deluxe Room (With Balcony) | G54: 3500 | H54: 3400
B55: Munnar | C55: KL55 | D55: The Breeze Resort | E55: Extra Adult passenger | G55: 800 | H55: 1350
B56: Munnar | C56: KL56 | D56: The Whispering Meadows | E56: Executive Room | G56: 3600 | H56: 4900
B57: Munnar | C57: KL57 | D57: The Whispering Meadows | E57: Extra Adult passenger | G57: 800 | H57: 1450
B58: Munnar | C58: KL58 | D58: Blossom Hill Resort | E58: Valley View Cottage (With Balcony) | G58: 3400 | H58: =RAW[[#This Row],[Double CP]]+1300 -> 4700
B59: Munnar | C59: KL59 | D59: Blossom Hill Resort | E59: Extra Adult passenger | G59: 800 | H59: =RAW[[#This Row],[Double CP]]+650 -> 1450
B60: Alleppey | C60: KL62 | D60: Venice Iva Residency | E60: Quadruple Bed Room (04 pax) | G60: 4900 | H60: 6100
B61: Alleppey | C61: KL63 | D61: Venice Iva Residency | E61: Extra Adult passenger | G61: 800 | H61: 1400
B62: Munnar | C62: KL64 | D62: Seven Springs Plantation Resort | E62: Deluxe Room | G62: 3500 | H62: 4500
B63: Munnar | C63: KL65 | D63: Seven Springs Plantation Resort | E63: Super Deluxe Room | G63: 4500 | H63: 5500
B64: Munnar | C64: KL66 | D64: Seven Springs Plantation Resort | E64: Suite Rooms | G64: 5500 | H64: 6500
B65: Munnar | C65: KL67 | D65: Seven Springs Plantation Resort | E65: Tree House | G65: 8000 | H65: 9000
B66: Munnar | C66: KL68 | D66: Seven Springs Plantation Resort | E66: Extra Adult passenger | G66: 1000 | H66: 2000
B67: Alleppey | C67: KL69 | D67: Casino Houseboats | E67: Standard | I67: 5500
B68: Alleppey | C68: KL70 | D68: Casino Houseboats | E68: Preimum | I68: 8500
B69: Alleppey | C69: KL72 | D69: Haveli Backwater Resort | E69: Royal Deluxe | G69: 3200 | H69: 4400 | I69: 5600
B70: Alleppey | C70: KL73 | D70: Haveli Backwater Resort | E70: Royal Grand | G70: 3500 | H70: 4700 | I70: 5900
B71: Alleppey | C71: KL74 | D71: Haveli Backwater Resort | E71: Royal Suite | G71: 4500 | H71: 5700 | I71: 6900
B72: Alleppey | C72: KL75 | D72: Haveli Backwater Resort | E72: Extra Adult passenger | G72: 1000 | H72: 1600 | I72: 2200
B73: Alleppey | C73: KL76 | D73: Haveli Backwater Resort | E73: Child with bed | G73: 800 | H73: 1200 | I73: 1600
B74: Alleppey | C74: KL77 | D74: Haveli Backwater Resort | E74: Child without bed | G74: 500 | H74: 800 | I74: 1100
B75: Alleppey | C75: KL78 | D75: Pagoda Resorts | E75: Deluxe | G75: 2500 | H75: 3600 | I75: 4700
B76: Alleppey | C76: KL79 | D76: Pagoda Resorts | E76: Deluxe Superior | G76: 2800 | H76: 3900 | I76: 5000
B77: Alleppey | C77: KL80 | D77: Pagoda Resorts | E77: Pagoda Cottage | G77: 3300 | H77: 4400 | I77: 5500
B78: Alleppey | C78: KL81 | D78: Pagoda Resorts | E78: Suite | G78: 3600 | H78: 4700 | I78: 5800
B79: Alleppey | C79: KL82 | D79: Pagoda Resorts | E79: Extra Adult passenger | G79: 800 | H79: 1350 | I79: 1900
B80: Alleppey | C80: KL83 | D80: Pagoda Resorts | E80: Child with bed | G80: 600 | H80: 900 | I80: 1200
B81: Alleppey | C81: KL84 | D81: Pagoda Resorts | E81: Child without bed | G81: 400 | H81: 700 | I81: 1000
B82: Thekkady | C82: KL85 | D82: Pagoda Plantation Resort | E82: Valley View Deluxe | G82: 3300 | H82: 4300
B83: Thekkady | C83: KL86 | D83: Pagoda Plantation Resort | E83: Hill Top Deluxe | G83: 3800 | H83: 4800
B84: Thekkady | C84: KL87 | D84: Pagoda Plantation Resort | E84: Hill Top Premium | G84: 4100 | H84: 5100
B85: Thekkady | C85: KL88 | D85: Pagoda Plantation Resort | E85: Valley View Family Room (4 PAX) | G85: 4800 | H85: 6800
B86: Thekkady | C86: KL89 | D86: Pagoda Plantation Resort | E86: Tea Valley Deluxe | G86: 5000 | H86: 6000
B87: Thekkady | C87: KL90 | D87: Pagoda Plantation Resort | E87: Tea Valley Premium | G87: 5500 | H87: 6500
B88: Thekkady | C88: KL91 | D88: Pagoda Plantation Resort | E88: Extra Adult passenger | G88: 900 | H88: 1400
B89: Thekkady | C89: KL92 | D89: Pagoda Plantation Resort | E89: Child with bed | G89: 600 | H89: 900
B90: Thekkady | C90: KL93 | D90: Pagoda Plantation Resort | E90: Child without bed | G90: 400 | H90: 700
B91: Munnar | C91: KL94 | D91: The Breeze Resort | E91: Valley View Room (With Balcony) | G91: 3750 | H91: 4950
B92: Thekkady | C92: KL95 | D92: Jungle Park Resort | E92: Jungle View Deluxe (Non A/c) | G92: 3100 | H92: 4400
B93: Thekkady | C93: KL96 | D93: Jungle Park Resort | E93: Jungle View Venus (A/c) | G93: 3600 | H93: 4900
... B99: Thekkady | C99: KL102 | D99: Jungle Park Resort | E99: Child without bed | G99: 500 | H99: 900
B100: Munnar | C100: KL103 | D100: Blossom Hill Resort | E100: Premium Valley View Cottage (With Balcony) | G100: 3900 | H100: =RAW[[#This Row],[Double CP]]+1300 -> 5200
B101: Alleppey | C101: KL104 | D101: Symphony Houseboats | E101: A Day Cruise without room Checkin 1pm to Checkout 5:30pm same day ,Veg | G101: 3000
B102: Kovalam | C102: KL105 | D102: Jeevan Beach Resort | E102: Sea Shell (Partial Sea View) | G102: 3400 | H102: 4600
B103: Kovalam | C103: KL106 | D103: Jeevan Beach Resort | E103: Sea Shore (Partial Sea View over the Pool) | G103: 3400 | H103: 4600
B104: Kovalam | C104: KL107 | D104: Jeevan Beach Resort | E104: Bay Watch (Sunset Sea View) | G104: 3600 | H104: 4800
B105: Kovalam | C105: KL108 | D105: Jeevan Beach Resort | E105: Exotic Sea View (Best Sea View) | G105: 3900 | H105: 5200
B106: Kovalam | C106: KL109 | D106: Jeevan Beach Resort | E106: Wooden Suite (Partial Sea View) | G106: 5000 | H106: 6200
B107: Kovalam | C107: KL110 | D107: Jeevan Beach Resort | E107: Pearl Sea View With Terrace (Best Sea View) | G107: 5500 | H107: 7200
B108: Varkala | C108: KL111 | D108: Sunview Beach Resort & Spa by Citrine | E108: Garden View | G108: 6500
B109: Varkala | C109: KL112 | D109: Sunview Beach Resort & Spa by Citrine | E109: Pool View | G109: 7000
B110: Varkala | C110: KL113 | D110: Sunview Beach Resort & Spa by Citrine | E110: Ocean View | G110: 7500
B111: Varkala | C111: KL114 | D111: Sunview Beach Resort & Spa by Citrine | E111: Heritage | G111: 8500
B112: Varkala | C112: KL115 | D112: Sunview Beach Resort & Spa by Citrine | E112: Royal Seaview | G112: 9000
B113: Varkala | C113: KL116 | D113: Sunview Beach Resort & Spa by Citrine | E113: Panoramic Vista | G113: 12000
B114: Varkala | C114: KL117 | D114: Sunview Beach Resort & Spa by Citrine | E114: D Series (No View) | G114: 3500
B115: Alleppey | C115: KL118 | D115: Venice Iva Residency | E115: Triple Bed Room (03 pax) | G115: 5600 | H115: 6800
B116: Alleppey | C116: KL119 | D116: Venice Iva Residency | E116: Child with bed | G116: 600 | H116: 1000
B117: Alleppey | C117: KL120 | D117: Venice Iva Residency | E117: Child without bed | G117: 500 | H117: 900
B118: Munnar | C118: KL121 | D118: Sprise Munnar Resort & Spa | E118: Marvellous Mountain View | G118: 6250 | H118: 7050
B119: Munnar | C119: KL122 | D119: Sprise Munnar Resort & Spa | E119: Majestic Ponmudi Dam View | G119: 6750 | H119: 7550
B120: Munnar | C120: KL123 | D120: Sprise Munnar Resort & Spa | E120: Timeless Jacuzzi Suite | G120: 10000 | H120: 10800
B121: Munnar | C121: KL124 | D121: Sprise Munnar Resort & Spa | E121: Fabulous Interconnecting Suite (04 Pax) | G121: 12500 | H121: 13300
B122: Munnar | C122: KL125 | D122: Sprise Munnar Resort & Spa | E122: Extra Adult passenger | G122: 1750 | H122: 2350
B123: Munnar | C123: KL126 | D123: Sprise Munnar Resort & Spa | E123: Child with bed | G123: 1250 | H123: 1850
B124: Munnar | C124: KL127 | D124: Sprise Munnar Resort & Spa | E124: Child without bed | G124: 750 | H124: 1350
B125: Kochi | C125: KL128 | D125: Broad Bean Hotel | E125: Standard Room | G125: 3100 | H125: 4300
B126: Kochi | C126: KL129 | D126: Broad Bean Hotel | E126: Deluxe Room | G126: 3400 | H126: 4600
... B190: Alleppey | C190: KL193 | D190: Miraaya Sundara Island Villa | E190: Child without bed | G190: 1000 | H190: 1500

Sheet Price
A1: Name | B1: Value | D1: Name | E1: Value | G1: Extra passenger | J1: Vehicle | K1: Airport
A2: Venice Iva Residency-Deluxe Room-Double CP | B2: 3900 | D2: Venice Iva Residency-Deluxe Room-Double CP | E2: 3900 | G2: Extra Adult passenger | J2: Sedan 4 Seater | K2: 3200
A3: Venice Iva Residency-Deluxe Room-Double MAP | B3: 5100 | D3: Venice Iva Residency-Deluxe Room-Double MAP | E3: 5100 | G3: Child with bed | J3: Mahindra Xuv Cab | K3: 4500
A4: The Elephant Court-Patio-Double CP | B4: 7200 | D4: The Elephant Court-Patio-Double CP | E4: 7200 | G4: Child without bed | J4: Innova 7 Seater | K4: 6000
A5: The Elephant Court-Patio-Double MAP | B5: 9100 | D5: The Elephant Court-Patio-Double MAP | E5: 9100 | G5: NA | J5: Crysta 7 Seater | K5: 3150
A6: The Elephant Court-Patio-Double AP | B6: 13500 | D6: The Elephant Court-Patio-Double AP | E6: 13500 | J6: Winger 12 Seater | K6: 3800
A7: The Elephant Court-Honeymoon Suite-Double CP | B7: 9500 | D7: The Elephant Court-Honeymoon Suite-Double CP | E7: 9500 | J7: Tempo 17 Seater | K7: 4200
A8: The Elephant Court-Honeymoon Suite-Double MAP | B8: 11400 | D8: The Elephant Court-Honeymoon Suite-Double MAP | E8: 11400 | J8: Tempo 20 Seater | K8: 4700
A9: The Elephant Court-Honeymoon Suite-Double AP | B9: 15800 | D9: The Elephant Court-Honeymoon Suite-Double AP | E9: 15800 | J9: Tempo 25 Seater | K9: 5200
A10: The Elephant Court-Garden Suite-Double CP | B10: 12000 | D10: The Elephant Court-Garden Suite-Double CP | E10: 12000 | J10: Mini Coach 30 Seater | K10: 6200
A11: The Elephant Court-Garden Suite-Double MAP | B11: 13900 | D11: The Elephant Court-Garden Suite-Double MAP | E11: 13900 | J11: Large Coach 40 Seater | K11: 7200
A12: The Elephant Court-Garden Suite-Double AP | B12: 18300 | D12: The Elephant Court-Garden Suite-Double AP | E12: 18300 | J12: NA | K12: 0
A13: The Elephant Court-Pool Studio-Double CP | B13: 14500 | D13: The Elephant Court-Pool Studio-Double CP | E13: 14500
A14: The Elephant Court-Pool Studio-Double MAP | B14: 16400 | D14: The Elephant Court-Pool Studio-Double MAP | E14: 16400
A15: The Elephant Court-Pool Studio-Double AP | B15: 20800 | D15: The Elephant Court-Pool Studio-Double AP | E15: 20800
A16: The Elephant Court-Extra Adult passenger-Double CP | B16: 2000 | D16: The Elephant Court-Extra Adult passenger-Double CP | E16: 2000
A17: The Elephant Court-Extra Adult passenger-Double MAP | B17: 2950 | D17: The Elephant Court-Extra Adult passenger-Double MAP | E17: 2950
A18: The Elephant Court-Extra Adult passenger-Double AP | B18: 3950 | D18: The Elephant Court-Extra Adult passenger-Double AP | E18: 3950
A19: The Elephant Court-Child with bed -Double CP | B19: 1250 | D19: The Elephant Court-Child with bed -Double CP | E19: 1250
A20: The Elephant Court-Child with bed -Double MAP | B20: 1700 | D20: The Elephant Court-Child with bed -Double MAP | E20: 1700
A21: The Elephant Court-Child with bed -Double AP | B21: 2150 | D21: The Elephant Court-Child with bed -Double AP | E21: 2150
A22: The Elephant Court-Child without bed-Double CP | B22: 700 | D22: The Elephant Court-Child without bed-Double CP | E22: 700
A23: The Elephant Court-Child without bed-Double MAP | B23: 1150 | D23: The Elephant Court-Child without bed-Double MAP | E23: 1150
A24: The Elephant Court-Child without bed-Double AP | B24: 1600 | D24: The Elephant Court-Child without bed-Double AP | E24: 1600
... A228: Pagoda Plantation Resort -Valley View Family Room (4 PAX)-Double MAP | B228: 6800 | D228: Pagoda Plantation Resort -Valley View Family Room (4 PAX)-Double MAP | E228: 6800
A229: Pagoda Plantation Resort -Valley View Family Room (4 PAX)-Triple EP | D229: Pagoda Plantation Resort -Valley View Family Room (4 PAX)-Triple EP
A230: Pagoda Plantation Resort -Tea Valley Deluxe-Double CP | B230: 5000 | D230: Pagoda Plantation Resort -Tea Valley Deluxe-Double CP | E230: 5000
A231: Pagoda Plantation Resort -Tea Valley Deluxe-Double MAP | B231: 6000 | D231: Pagoda Plantation Resort -Tea Valley Deluxe-Double MAP | E231: 6000
A232: Pagoda Plantation Resort -Tea Valley Deluxe-Triple EP | D232: Pagoda Plantation Resort -Tea Valley Deluxe-Triple EP
A233: Pagoda Plantation Resort -Tea Valley Premium-Double CP | B233: 5500 | D233: Pagoda Plantation Resort -Tea Valley Premium-Double CP | E233: 5500
A234: Pagoda Plantation Resort -Tea Valley Premium-Double MAP | B234: 6500 | D234: Pagoda Plantation Resort -Tea Valley Premium-Double MAP | E234: 6500
A235: Pagoda Plantation Resort -Tea Valley Premium-Triple EP | D235: Pagoda Plantation Resort -Tea Valley Premium-Triple EP
A236: Pagoda Plantation Resort -Extra Adult passenger-Double CP | B236: 900 | D236: Pagoda Plantation Resort -Extra Adult passenger-Double CP | E236: 900
A237: Pagoda Plantation Resort -Extra Adult passenger-Double MAP | B237: 1400 | D237: Pagoda Plantation Resort -Extra Adult passenger-Double MAP | E237: 1400
A238: Pagoda Plantation Resort -Child with bed -Double CP | B238: 600 | D238: Pagoda Plantation Resort -Child with bed -Double CP | E238: 600
A239: Pagoda Plantation Resort -Child with bed -Double MAP | B239: 900 | D239: Pagoda Plantation Resort -Child with bed -Double MAP | E239: 900
A240: Pagoda Plantation Resort -Child without bed-Double CP | B240: 400 | D240: Pagoda Plantation Resort -Child without bed-Double CP | E240: 400
A241: Pagoda Plantation Resort -Child without bed-Double MAP | B241: 700 | D241: Pagoda Plantation Resort -Child without bed-Double MAP | E241: 700
A242: Pagoda Plantation Resort -Child without bed-Triple EP | D242: Pagoda Plantation Resort -Child without bed-Triple EP
A243: The Breeze Resort -Valley View Room (With Balcony)-Double CP | B243: 3750 | D243: The Breeze Resort -Valley View Room (With Balcony)-Double CP | E243: 3750
A244: The Breeze Resort -Valley View Room (With Balcony)-Double MAP | B244: 4950 | D244: The Breeze Resort -Valley View Room (With Balcony)-Double MAP | E244: 4950
A245: Jungle Park Resort-Jungle View Deluxe (Non A/c)-Double CP | B245: 3100 | D245: Jungle Park Resort-Jungle View Deluxe (Non A/c)-Double CP | E245: 3100
A246: Jungle Park Resort-Jungle View Deluxe (Non A/c)-Double MAP | B246: 4400 | D246: Jungle Park Resort-Jungle View Deluxe (Non A/c)-Double MAP | E246: 4400
A247: Jungle Park Resort-Jungle View Venus (A/c)-Double CP | B247: 3600 | D247: Jungle Park Resort-Jungle View Venus (A/c)-Double CP | E247: 3600
A248: Jungle Park Resort-Jungle View Venus (A/c)-Double MAP | B248: 4900 | D248: Jungle Park Resort-Jungle View Venus (A/c)-Double MAP | E248: 4900
A249: Jungle Park Resort-Jungle View Venus (A/c)-Triple EP | D249: Jungle Park Resort-Jungle View Venus (A/c)-Triple EP
A250: Jungle Park Resort-DeluxeFamilyRoom-03Pax (Non A/c)-Double CP | B250: 3700 | D250: Jungle Park Resort-DeluxeFamilyRoom-03Pax (Non A/c)-Double CP | E250: 3700
A251: Jungle Park Resort-DeluxeFamilyRoom-03Pax (Non A/c)-Double MAP | B251: 5000 | D251: Jungle Park Resort-DeluxeFamilyRoom-03Pax (Non A/c)-Double MAP | E251: 5000
A252: Jungle Park Resort-Jungle View Family- 4Pax (Non A/c)-Double CP | B252: 5500 | D252: Jungle Park Resort-Jungle View Family- 4Pax (Non A/c)-Double CP | E252: 5500
A253: Jungle Park Resort-Jungle View Family- 4Pax (Non A/c)-Double MAP | B253: 6800 | D253: Jungle Park Resort-Jungle View Family- 4Pax (Non A/c)-Double MAP | E253: 6800
A254: Jungle Park Resort-Jungle View Family- 4Pax (A/c)-Double CP | B254: 6000 | D254: Jungle Park Resort-Jungle View Family- 4Pax (A/c)-Double CP | E254: 6000
A255: Jungle Park Resort-Jungle View Family- 4Pax (A/c)-Double MAP | B255: 7300 | D255: Jungle Park Resort-Jungle View Family- 4Pax (A/c)-Double MAP | E255: 7300
A256: Jungle Park Resort-Extra Adult passenger-Double CP | B256: 800 | D256: Jungle Park Resort-Extra Adult passenger-Double CP | E256: 800
A257: Jungle Park Resort-Extra Adult passenger-Double MAP | B257: 1450 | D257: Jungle Park Resort-Extra Adult passenger-Double MAP | E257: 1450
A258: Jungle Park Resort-Child with bed -Double CP | B258: 600 | D258: Jungle Park Resort-Child with bed -Double CP | E258: 600
A259: Jungle Park Resort-Child with bed -Double MAP | B259: 1000 | D259: Jungle Park Resort-Child with bed -Double MAP | E259: 1000
A260: Jungle Park Resort-Child without bed-Double CP | B260: 500 | D260: Jungle Park Resort-Child without bed-Double CP | E260: 500
A261: Jungle Park Resort-Child without bed-Double MAP | B261: 900 | D261: Jungle Park Resort-Child without bed-Double MAP | E261: 900
... A435: Miraaya Sundara Island Villa-Child without bed-Double MAP | B435: 1500 | D435: Miraaya Sundara Island Villa-Child without bed-Double MAP | E435: 1500

Sheet ActivitiesMaster
C1: Name of Activity | D1: Description | E1: Price
C2: Honeymoon Inclusions | D2: ABC
C3: Candle Lit Dinner
C14: Vehicle | D14: Airport
C15: Mahindra Xuv Cab | D15: 4500
C16: Innova 7 Seater | D16: 6000
C25: Taxi Shim Meghalaya | D25: 70056 76675

Sheet Day Wise Exursion
A1: Day No. | B1: Title | C1: Description
A2: =IF(B2="","", "Day " & ROW(A2)-1) -> Day 1 | B2: Arrival at Cochin & Transfer to Munnar + Munnar Sightseeing | C2: Upon arrival in Cochin, proceed to Munnar for a day of sightseeing. Start with a visit to Mattupetty Dam (additional ticket fee applies), a concrete gravity dam nestled in the mountains. Mattupetty offers a captivating blend of natural beauty, featuring sprawling tea plantations, rolling grasslands, and lush Shola forests. These forests are perfect for trekking and serve as a habitat for a wide variety of birds. Later visit Kundala Dam (ticket price extra), the famous Neela Kurunji flowers which bloom once in twelve years, bloom in the hills and valleys around Kundala lake. Enroute visit Echo Point & Pothamedu View Point. Echo Point always has a greenish look as it is covered with abundant green sceneries. View Point is perfect to enjoy the spectacular beauty of the coffee, tea & cardamom plantations. They are an adventurous destination, which will be a perfect choice for those who love to have a nature walk or trekking. Overnight stay at Hotel.
A3: =IF(B3="","", "Day " & ROW(A3)-1) -> Day 2 | B3: Arrival at Cochin - Athirappilly Falls - Munnar | C3: On arrival at Cochin, proceed to Munnar via Athirappilly falls, the most famous waterfalls of Kerala. The 80 ft high and 330 ft wide Athirapally falls is a majestic waterfall that is right in front of the Sholayar ranges and is often referred to as the "Niagara Falls of India". Just 5 km from this fall is another majestic waterfall - Vazhachal. After spending some time at the waterfalls, proceed towards Munnar. Situated at 1,600m above sea level with unending expanse of tea plantations - pristine valleys and mountains, you’re often up above the clouds watching veils of mist clinging to the mountain tops. Overnight stay at Hotel.
A4: =IF(B4="","", "Day " & ROW(A4)-1) -> Day 3 | B4: Munnar Full Day Sightseeing Tour | C4: After breakfast proceed for sightseeing of Munnar. Visit Eravikulam National Park (ticket price extra) Closed for Jan 2025 till March 2025 & Mattupetty Dam (ticket price extra), a storage concrete gravity dam built in the mountains. Mattupetty offers many fascinating sights to relish. Besides the tea plantations & the rolling grasslands, the Shola forests in and around Mattupetty are ideal for trekking and are habitat to a variety of birds. Later visit Kundala Dam (ticket price extra), the famous Neela Kurunji flowers which bloom once in twelve years, bloom in the hills and valleys around Kundala lake. Enroute visit Echo Point & Pothamedu View Point. Echo Point always has a greenish look as it is covered with abundant green sceneries. View Point is perfect to enjoy the spectacular beauty of the coffee, tea & cardamom plantations. They are an adventurous destination, which will be a perfect choice for those who love to have a nature walk or trekking. Overnight stay at Hotel.
A5: =IF(B5="","", "Day " & ROW(A5)-1) -> Day 4 | B5: Munnar Dream Land Spices Park | C5: Enjoy your breakfast today before we head out. We’re going on a trip to Dream Land Spices Park at an extra cost for entry and rides. There’s so much to do and explore here where you can go for challenging Tyre Climbing or get drenched at the Water Park. Try out the Archery and Camel Ride, have fun at the Trampoline or bond with your family with some off-road cycling and city scooter. There’s something for everyone here! We’re going to head back to the hotel in Munnar for our overnight stay after this.
A6: =IF(B6="","", "Day " & ROW(A6)-1) -> Day 5 | B6: Transfer from Munnar to Thekkady - (85 Kms - Approx 3 Hrs) | C6: After breakfast, check out from hotel & proceed to Thekkady. Thekkady is considered as a heaven for natural spices. The Periyar forests of Thekkady is one of the finest wildlife reserves in India. Periyar encompasses 777 sq km & a 26-sq-km artificial lake. Check-in at hotel & later head out for sightseeing to visit the Periyar Wildlife Sanctuary (ticket price extra), it is home to herds of wild Elephants, Sambar, Tigers, Gaur, Lion-tailed Macaques, Nilgiri Langurs & more. The place can sometimes feel a bit like Disneyland-in-the-Ghats, but its mountain scenery & jungle walks make for an enjoyable visit. Evening enjoy the boat cruise in the lake (at additional cost) to spot wild animals. Overnight stay at Hotel.
A7: =IF(B7="","", "Day " & ROW(A7)-1) -> Day 6 | B7: Transfer from Thekkady to Alleppey - (135 Kms - Approx 4 Hrs) | C7: After breakfast, check out from hotel and proceed to Alleppey which has an immense natural beauty and is also known as the “Venice of the East”. It is famous for backwater cruising and boat race. Check into your hotel/houseboat & cruise (if staying in houseboat) through the Narrow Canal amidst the Paddy Fields, Coconut Lagoons and Coir Villages in Alleppey. Overnight stay in Alleppey.
A8: =IF(B8="","", "Day " & ROW(A8)-1) -> Day 7 | B8: Transfer from Alleppey to Kovalam (160 Kms - Approx 4.5 Hrs) | C8: After breakfast, check out from hotel & proceed to Kovalam. Kovalam is an internationally renowned beach destination with three adjacent crescent beaches & also known as the "Paradise of the South". On arrival check-in at the hotel & relax for a while amidst the comforts of your room. By evening explore on your own to see how the everlasting sea touches the everlasting sky. Kovalam is the place where one can see the golden sand at the day time & silver sand in the night, with high rock promontory & a calm bay of blue waters, this beach paradise creates a unique aquarelle on moonlight nights. Overnight stay at Hotel.
A9: =IF(B9="","", "Day " & ROW(A9)-1) -> Day 8 | B9: Transfer from Alleppey to Kovalam (160 Kms - Approx 4.5 Hrs) Via Poovar | C9: After breakfast check out from hotel & proceed to Trivandrum, city of the Holy Ananth which is named after Ananthan, the cosmic serpent with a thousand heads. Visit Sri Padmanabhaswamy Temple (260 yrs old) - the most religious icon of the city built by the Travancore Royal family, here the deity Padmanabha reclines on the sacred serpent & is made from over 10,000 salagramam (sacred stones) that were transported from Nepal by elephant. Poovar is one among the natural wonders where the Lake, River, Sea and Beach meet the land. A rare find in Kerala. Poovar is basically a fishing village and the only way to reach Poovar is through water, it is known for its pristine and virginal beauty, Poovar Beach is haunted by those who love solitude. Later proceed to Kovalam. Kovalam is an internationally renowned beach destination with three adjacent crescent beaches & also known as the "Paradise of the South". On arrival check in at the hotel & relax for a while amidst the comforts of your room. By evening explore on your own to see how the everlasting sea touches the everlasting sky. Kovalam is the place where one can see the golden sand at the day time & silver sand in the night, with high rock promontory & a calm bay of blue waters, this beach paradise creates a unique aquarelle on moonlight nights. Overnight stay at Hotel.
A10: =IF(B10="","", "Day " & ROW(A10)-1) -> Day 9 | B10: Transfer from Alleppey to Kovalam (160 Kms - Approx 4.5 Hrs) With Sri Padmanabhaswamy Temple | C10: After breakfast check out from hotel & proceed to Trivandrum, city of the Holy Ananth which is named after Ananthan, the cosmic serpent with a thousand heads. Visit Sri Padmanabhaswamy Temple (260 yrs old) - the most religious icon of the city built by the Travancore Royal family, here the deity Padmanabha reclines on the sacred serpent & is made from over 10,000 salagramam (sacred stones) that were transported from Nepal by elephant. Later proceed to Kovalam. Kovalam is an internationally renowned beach destination with three adjacent crescent beaches & also known as the "Paradise of the South". On arrival check in at the hotel & relax for a while amidst the comforts of your room. By evening explore on your own to see how the everlasting sea touches the everlasting sky. Kovalam is the place where one can see the golden sand at the day time & silver sand in the night, with high rock promontory & a calm bay of blue waters, this beach paradise creates a unique aquarelle on moonlight nights. Overnight stay at Hotel.
A11: =IF(B11="","", "Day " & ROW(A11)-1) -> Day 10 | B11: Transfer from Alleppey to Kovalam enroute Jatayu Earth Centre | C11: After breakfast in the morning, proceed for Jatayu earth's center located at a small village called Chadayamangalam in Kollam (around 50 kms from Trivandrum). Its assumed that this is the place where – Jatayu, a demi-god of Hindu epic "Ramayana" having the form of a vulture, fought with Ravana - multi headed demon king of Lanka (now Sri Lanka) to prevent kidnapping of Goddess Sita, and got slain off one of his wing. The giant concrete statue of Jatayu is built on a mighty rock named Jatayupara (para means rock in Malayalam). The colossal statue is 200 feet long, 150 feet wide and 70 feet making is the largest functional bird sculpture in the world. You can take a cable car ride (on supplementary cost) to visit the Jatayu statue, audio visual museum and mini theatre. Cable car can be booked online in advance. Jatayu earth's center is spread across four hills in Chadayamangalam. The Jatayu Rock Hill represents the safety of women and their honour. The Adventure Rock Hill offers many adventure activities and nature walk. Adventure activities (all on supplementary cost) include paintball, rifle shooting, chimney climbing, rappelling, bouldering, etc. At Elephant Rock Hill, you can enjoy an overnight stay here in tented camps. The spot offers zip-lining, campfire, live music and kitchen, etc. The fourth hill, The Kitchen Rock Hill, provides a ten-day Siddha rejuvenation package. Then proceed to Kovalam. Kovalam is an internationally renowned beach destination with three adjacent crescent beaches & also known as the "Paradise of the South". On arrival check-in at the hotel & relax for a while amidst the comforts of your room. By evening explore on your own to see how the everlasting sea touches the everlasting sky. Kovalam is the place where one can see the golden sand at the day time & silver sand in the night, with high rock promontory & a calm bay of blue waters, this beach paradise creates a unique aquarelle on moonlight nights. Overnight stay at Hotel.
A12: =IF(B12="","", "Day " & ROW(A12)-1) -> Day 11 | B12: Sightseeing of Trivandrum & Return to Kovalam (16 Kms - Approx 30 Mins) | C12: After breakfast proceed for sightseeing of Trivandrum, city of the Holy Ananth which is named after Ananthan, the cosmic serpent with a thousand heads. Visit Sri Padmanabhaswamy Temple (260 yrs old) - the most religious icon of the city built by the Travancore Royal family, here the deity Padmanabha reclines on the sacred serpent & is made from over 10,000 salagramam (sacred stones) that were transported from Nepal by elephant. Secondly, visit Puthe Maliga Palace Museum (ticket price extra) - a 200 year old palace which has carved wooden ceilings, marble sculptures & imported Belgian glass. Inside you'll find Kathakali images, an armoury, portraits of maharajas, ornate thrones & other artefacts. Later proceed to Veli Tourist Village, a beautiful & popular picnic spot well-known because of its serenity, the Lake that meets the Arabian Sea. The main attraction of Veli Tourist Village is a floating bridge that has been erected at this place. The place also has a floating restaurant that gives you an amazing array of food products which might match your taste buds. By evening proceed to Shankumugham Beach, the beach is well known for its breathtaking sunset view which is such memorable moment whose beauty will refresh your mind. The beautiful sculpture of a mermaid is a major attraction here, this giant statue is more than 35m long. Later return to Kovalam. Overnight stay at the Hotel. less Sree Padmanabhaswamy Temple, Shanghumukham Beach, Veli Tourist Village, Kuthiramalika Palace Museum are also covered on Day 7 (Transfer to Trivandrum + Sightseeing of Trivandrum + Departure from Trivandrum); Kuthiramalika Palace Museum - Closed
A13: =IF(B13="","", "Day " & ROW(A13)-1) -> Day 12 | B13: Day Sightseeing of Kanyakumari | C13: After breakfast, embark on a scenic drive to Kanyakumari, a town enveloped by majestic hills and scenic sea-shores, adorned with coconut trees and lush paddy fields. En route, make a stop at Suchindram, a sacred site situated along the banks of the river Pazhayar. In Kanyakumari, pay a visit to the Vivekananda Rock Memorial (entrance fee required), a revered monument believed to be the site where Goddess Kanyakumari undertook her Tapas. Next, explore the Thiruvalluvar Statue, a monumental tribute to Thiruvalluvar. The pedestal of the statue stands at 38 feet tall, while the statue itself towers at 95 feet, making for a grand total of 133 feet for the entire sculpture. In the evening, return to Kovalam for an overnight stay at your hotel.
... A17: =IF(B17="","", "Day " & ROW(A17)-1) -> Day 16 | B17: Transfer to Trivandrum + Sightseeing of Trivandrum + Departure from Trivandrum | C17: After breakfast, proceed for sightseeing of Trivandrum. Visit Sri Padmanabhaswamy Temple (260 yrs old) - the most religious icon of the city built by the Travancore Royal family, here the deity Padmanabha reclines on the sacred serpent & is made from over 10,000 salagramam (sacred stones) that were transported from Nepal by elephant. Secondly, visit Puthe Maliga Palace Museum (ticket price extra) - a 200 year old palace which has carved wooden ceilings, marble sculptures & imported Belgian glass. Inside you'll find Kathakali images, an armoury, portraits of maharajas, ornate thrones & other artefacts. Later proceed to Veli Tourist Village, a beautiful & popular picnic spot well-known because of its serenity, the Lake that meets the Arabian Sea. The main attraction of Veli Tourist Village is a floating bridge that has been erected at this place. The place also has a floating restaurant that gives you an amazing array of food products which might match your taste buds. By evening proceed to Shankumugham Beach, the beach is well known for its breathtaking sunset view which is such memorable moment whose beauty will refresh your mind. The beautiful sculpture of a mermaid is a major attraction here, this giant statue is more than 35m long. Later transfer to Trivandrum airport/railway station for departure, back to home with beautiful memories of God's Own Country
A18: =IF(B18="","", "Day " & ROW(A18)-1)
A19: =IF(B19="","", "Day " & ROW(A19)-1)
A20: =IF(B20="","", "Day " & ROW(A20)-1)
A21: =IF(B21="","", "Day " & ROW(A21)-1)
A22: =IF(B22="","", "Day " & ROW(A22)-1)
A23: =IF(B23="","", "Day " & ROW(A23)-1)
A24: =IF(B24="","", "Day " & ROW(A24)-1)
A25: =IF(B25="","", "Day " & ROW(A25)-1)
A26: =IF(B26="","", "Day " & ROW(A26)-1)
A27: =IF(B27="","", "Day " & ROW(A27)-1)
A28: =IF(B28="","", "Day " & ROW(A28)-1)
A29: =IF(B29="","", "Day " & ROW(A29)-1)
... A32: =IF(B32="","", "Day " & ROW(A32)-1)

Sheet Sheet2
B1: City
B2: {=_xlfn.UNIQUE(RAW[[Destination ]])} -> Alleppey | C2: INDEX(Sheet1!$B$3:$D$7,0,MATCH(Sheet1!$B$11,Heading,0))
B3: Thekkady
B4: Kovalam
B5: Thiruvananthapuram
B6: Munnar
B7: Varkala
B8: Kochi
A12: City | B12: Hotecode | C12: Hotel Name | H12: {=TRANSPOSE($C$13:$C$790)} -> Venice Iva Residency | I12: The Elephant Court | J12: The Elephant Court | K12: The Elephant Court | L12: The Elephant Court | M12: The Elephant Court | N12: The Elephant Court | O12: The Elephant Court | P12: Peppervine | Q12: Peppervine | R12: Peppervine | S12: Peppervine | T12: Peppervine | U12: Peppervine | V12: Uday Samudra Beach Hotel | W12: Uday Samudra Leisure Beach Hotel | X12: Uday Samudra Leisure Beach Hotel | Y12: Uday Samudra Leisure Beach Hotel | Z12: Uday Samudra Leisure Beach Hotel | AA12: Uday Samudra Leisure Beach Hotel | AB12: Uday Samudra Leisure Beach Hotel | AC12: Uday Samudra Leisure Beach Hotel | AD12: Uday Samudra Leisure Beach Hotel | AE12: Uday Samudra Leisure Beach Hotel | AF12: Uday Samudra Leisure Beach Hotel | AG12: Uday Samudra Leisure Beach Hotel | AH12: The Byke Heritage - Puja Samudra | AI12: The Byke Heritage - Puja Samudra | AJ12: Uday Backwater Resort | AK12: Uday Backwater Resort | AL12: Uday Backwater Resort | AM12: Uday Backwater Resort | AN12: Uday Backwater Resort | AO12: Uday Backwater Resort | AP12: Uday Backwater Resort | AQ12: Uday Backwater Resort | AR12: Uday Backwater Resort | AS12: Uday Suites, The Airport Hotel | AT12: Uday Suites, The Airport Hotel | AU12: Uday Suites, The Airport Hotel | AV12: Uday Suites, The Airport Hotel | AW12: Uday Suites, The Airport Hotel | AX12: Uday Suites, The Airport Hotel | AY12: Uday Suites, The Airport Hotel | AZ12: Uday Suites, The Airport Hotel | BA12: Tea castle resort | BB12: Tea castle resort | BC12: Tea castle resort | BD12: Tea castle resort | BE12: Tea castle resort | BF12: Tea castle resort | BG12: The Breeze Resort | BH12: The Breeze Resort | BI12: The Whispering Meadows | BJ12: The Whispering Meadows | BK12: Blossom Hill Resort | BL12: Blossom Hill Resort | BM12: Venice Iva Residency | BN12: Venice Iva Residency | BO12: Seven Springs Plantation Resort | BP12: Seven Springs Plantation Resort | BQ12: Seven Springs Plantation Resort | BR12: Seven Springs Plantation Resort | BS12: Seven Springs Plantation Resort | BT12: Casino Houseboats | BU12: Casino Houseboats | BV12: Haveli Backwater Resort | BW12: Haveli Backwater Resort | BX12: Haveli Backwater Resort | BY12: Haveli Backwater Resort | BZ12: Haveli Backwater Resort | CA12: Haveli Backwater Resort | CB12: Pagoda Resorts | CC12: Pagoda Resorts | CD12: Pagoda Resorts | CE12: Pagoda Resorts | CF12: Pagoda Resorts | CG12: Pagoda Resorts | CH12: Pagoda Resorts | CI12: Pagoda Plantation Resort | CJ12: Pagoda Plantation Resort | CK12: Pagoda Plantation Resort | CL12: Pagoda Plantation Resort | CM12: Pagoda Plantation Resort | CN12: Pagoda Plantation Resort | CO12: Pagoda Plantation Resort | CP12: Pagoda Plantation Resort | CQ12: Pagoda Plantation Resort | CR12: The Breeze Resort | CS12: Jungle Park Resort | CT12: Jungle Park Resort | CU12: Jungle Park Resort | CV12: Jungle Park Resort | CW12: Jungle Park Resort | CX12: Jungle Park Resort | CY12: Jungle Park Resort | CZ12: Jungle Park Resort | DA12: Blossom Hill Resort | DB12: Symphony Houseboats | DC12: Jeevan Beach Resort | DD12: Jeevan Beach Resort | DE12: Jeevan Beach Resort | DF12: Jeevan Beach Resort | DG12: Jeevan Beach Resort | DH12: Jeevan Beach Resort | DI12: Sunview Beach Resort & Spa by Citrine | DJ12: Sunview Beach Resort & Spa by Citrine | DK12: Sunview Beach Resort & Spa by Citrine | DL12: Sunview Beach Resort & Spa by Citrine | DM12: Sunview Beach Resort & Spa by Citrine | DN12: Sunview Beach Resort & Spa by Citrine | DO12: Sunview Beach Resort & Spa by Citrine | DP12: Venice Iva Residency | DQ12: Venice Iva Residency | DR12: Venice Iva Residency | DS12: Sprise Munnar Resort & Spa | DT12: Sprise Munnar Resort & Spa | DU12: Sprise Munnar Resort & Spa | DV12: Sprise Munnar Resort & Spa | DW12: Sprise Munnar Resort & Spa | DX12: Sprise Munnar Resort & Spa | DY12: Sprise Munnar Resort & Spa | DZ12: Broad Bean Hotel | EA12: Broad Bean Hotel | EB12: Broad Bean Hotel | EC12: Broad Bean Hotel | ED12: Broad Bean Hotel | EE12: Broad Bean Hotel | EF12: Broad Bean Hotel | EG12: Broad Bean Hotel | EH12: The Breeze Resort | EI12: The Breeze Resort | EJ12: Jeevan Beach Resort | EK12: Jeevan Beach Resort | EL12: Jeevan Beach Resort | EM12: Blossom Hill Resort | EN12: Blossom Hill Resort | EO12: Lagoona Beach Resort | EP12: Lagoona Beach Resort | EQ12: Lagoona Beach Resort | ER12: Lagoona Beach Resort | ES12: Lagoona Beach Resort | ET12: Lagoona Beach Resort | EU12: Lagoona Beach Resort | EV12: Lagoona Beach Resort | EW12: Lagoona Beach Resort | EX12: The Whispering Meadows | EY12: The Whispering Meadows | EZ12: The Whispering Meadows | FA12: Napier Heritage Fort | FB12: Napier Heritage Fort | FC12: Napier Heritage Fort | FD12: Napier Heritage Fort | FE12: Napier Heritage Fort | FF12: Napier Heritage Fort | FG12: Napier Heritage Fort | FH12: Napier Heritage Fort | FI12: Napier Heritage Fort | FJ12: Napier Heritage Fort | FK12: Trium Resort & Houseboats | FL12: Trium Resort & Houseboats | FM12: Trium Resort & Houseboats | FN12: Trium Resort & Houseboats | FO12: Trium Resort & Houseboats | FP12: Trium Resort & Houseboats | FQ12: Trium Deluxe Houseboats | FR12: Trium Deluxe Houseboats | FS12: Trium Preimum Houseboats | FT12: Trium Preimum Houseboats | FU12: Ocean Bay Ayurvedic Beach Resort | FV12: Ocean Bay Ayurvedic Beach Resort | FW12: Ocean Bay Ayurvedic Beach Resort | FX12: Ocean Bay Ayurvedic Beach Resort | FY12: Ocean Bay Ayurvedic Beach Resort | FZ12: Aadisaktthi Resort | GA12: Aadisaktthi Resort | GB12: Aadisaktthi Resort | GC12: Aadisaktthi Resort | GD12: Aadisaktthi Resort | GE12: Aadisaktthi Resort | GF12: Aadisaktthi Resort | GG12: Aadisaktthi Resort | GH12: Aadisaktthi Resort | GI12: Miraaya Sundara Island Villa | GJ12: Miraaya Sundara Island Villa | GK12: Miraaya Sundara Island Villa | GL12: Miraaya Sundara Island Villa | GM12: Miraaya Sundara Island Villa
A13: =IF(B12="","",_xlfn.XLOOKUP(B13,'Raw'!C:C,'Raw'!B:B)) -> Alleppey | B13: {=_xlfn.UNIQUE(RAW[Hotel Code])} -> KL1 | C13: =IF(B13="","",VLOOKUP(B13,RAW[[Hotel Code]:[Hotel / Resort Name ]],2,0)) -> Venice Iva Residency | H13: {=IF(H12="","",_xlfn._xlws.FILTER(RAW[[#All],[Room Type]],RAW[[#All],[Hotel / Resort Name ]]=Sheet2!H$12))} -> Deluxe Room | I13: {=IF(I12="","",_xlfn._xlws.FILTER(RAW[[#All],[Room Type]],RAW[[#All],[Hotel / Resort Name ]]=Sheet2!I$12))} -> Patio | J13: {=IF(J12="","",_xlfn._xlws.FILTER(RAW[[#All],[Room Type]],RAW[[#All],[Hotel / Resort Name ]]=Sheet2!J$12))} -> Patio | K13: {=IF(K12="","",_xlfn._xlws.FILTER(RAW[[#All],[Room Type]],RAW[[#All],[Hotel / Resort Name ]]=Sheet2!K$12))} -> Patio | L13: {=IF(L12="","",_xlfn._xlws.FILTER(RAW[[#All],[Room Type]],RAW[[#All],[Hotel / Resort Name ]]=Sheet2!L$12))} -> Patio | M13: {=IF(M12="","",_xlfn._xlws.FILTER(RAW[[#All],[Room Type]],RAW[[#All],[Hotel / Resort Name ]]=Sheet2!M$12))} -> Patio | N13: {=IF(N12="","",_xlfn._xlws.FILTER(RAW[[#All],[Room Type]],RAW[[#All],[Hotel / Resort Name ]]=Sheet2!N$12))} -> Patio | O13: {=IF(O12="","",_xlfn._xlws.FILTER(RAW[[#All],[Room Type]],RAW[[#All],[Hotel / Resort Name ]]=Sheet2!O$12))} -> Patio | ... BR13: {=IF(BR12="","",_xlfn._xlws.FILTER(RAW[[#All],[Room Type]],RAW[[#All],[Hotel / Resort Name ]]=Sheet2!BR$12))} -> Deluxe Room | BS13: {=IF(BS$12<>"",_xlfn.UNIQUE(_xlfn._xlws.FILTER(RAW[[#All],[Room Type]],RAW[[#All],[Hotel / Resort Name ]]=Sheet2!BS$12)),"")} -> Deluxe Room | BT13: {=IF(BT$12<>"",_xlfn.UNIQUE(_xlfn._xlws.FILTER(RAW[[#All],[Room Type]],RAW[[#All],[Hotel / Resort Name ]]=Sheet2!BT$12)),"")} -> Standard | BU13: {=IF(BU$12<>"",_xlfn.UNIQUE(_xlfn._xlws.FILTER(RAW[[#All],[Room Type]],RAW[[#All],[Hotel / Resort Name ]]=Sheet2!BU$12)),"")} -> Standard | BV13: {=IF(BV$12<>"",_xlfn.UNIQUE(_xlfn._xlws.FILTER(RAW[[#All],[Room Type]],RAW[[#All],[Hotel / Resort Name ]]=Sheet2!BV$12)),"")} -> Royal Deluxe | BW13: {=IF(BW$12<>"",_xlfn.UNIQUE(_xlfn._xlws.FILTER(RAW[[#All],[Room Type]],RAW[[#All],[Hotel / Resort Name ]]=Sheet2!BW$12)),"")} -> Royal Deluxe | BX13: {=IF(BX$12<>"",_xlfn.UNIQUE(_xlfn._xlws.FILTER(RAW[[#All],[Room Type]],RAW[[#All],[Hotel / Resort Name ]]=Sheet2!BX$12)),"")} -> Royal Deluxe | BY13: {=IF(BY$12<>"",_xlfn.UNIQUE(_xlfn._xlws.FILTER(RAW[[#All],[Room Type]],RAW[[#All],[Hotel / Resort Name ]]=Sheet2!BY$12)),"")} -> Royal Deluxe | BZ13: {=IF(BZ$12<>"",_xlfn.UNIQUE(_xlfn._xlws.FILTER(RAW[[#All],[Room Type]],RAW[[#All],[Hotel / Resort Name ]]=Sheet2!BZ$12)),"")} -> Royal Deluxe | ... ADE13: {=IF(ADE$12<>"",_xlfn.UNIQUE(_xlfn._xlws.FILTER(RAW[[#All],[Room Type]],RAW[[#All],[Hotel / Resort Name ]]=Sheet2!ADE$12)),"")}
A14: =IF(B13="","",_xlfn.XLOOKUP(B14,'Raw'!C:C,'Raw'!B:B)) -> Thekkady | B14: KL2 | C14: =IF(B14="","",VLOOKUP(B14,RAW[[Hotel Code]:[Hotel / Resort Name ]],2,0)) -> The Elephant Court | H14: Quadruple Bed Room (04 pax) | I14: Honeymoon Suite | J14: Honeymoon Suite | K14: Honeymoon Suite | L14: Honeymoon Suite | M14: Honeymoon Suite | N14: Honeymoon Suite | O14: Honeymoon Suite | P14: Suite Room | Q14: Suite Room | R14: Suite Room | S14: Suite Room | T14: Suite Room | U14: Suite Room | W14: Pool view Room | X14: Pool view Room | Y14: Pool view Room | Z14: Pool view Room | AA14: Pool view Room | AB14: Pool view Room | AC14: Pool view Room | AD14: Pool view Room | AE14: Pool view Room | AF14: Pool view Room | AG14: Pool view Room | AH14: Super Deluxe | AI14: Super Deluxe | AJ14: Lake View Elite Rooms | AK14: Lake View Elite Rooms | AL14: Lake View Elite Rooms | AM14: Lake View Elite Rooms | AN14: Lake View Elite Rooms | AO14: Lake View Elite Rooms | AP14: Lake View Elite Rooms | AQ14: Lake View Elite Rooms | AR14: Lake View Elite Rooms | AS14: Ixora | AT14: Ixora | AU14: Ixora | AV14: Ixora | AW14: Ixora | AX14: Ixora | AY14: Ixora | AZ14: Ixora | BA14: Deluxe Room | BB14: Deluxe Room | BC14: Deluxe Room | BD14: Deluxe Room | BE14: Deluxe Room | BF14: Deluxe Room | BG14: Extra Adult passenger | BH14: Extra Adult passenger | BI14: Extra Adult passenger | BJ14: Extra Adult passenger | BK14: Extra Adult passenger | BL14: Extra Adult passenger | BM14: Quadruple Bed Room (04 pax) | BN14: Quadruple Bed Room (04 pax) | BO14: Super Deluxe Room | BP14: Super Deluxe Room | BQ14: Super Deluxe Room | BR14: Super Deluxe Room | BS14: Super Deluxe Room | BT14: Preimum | BU14: Preimum | BV14: Royal Grand | BW14: Royal Grand | BX14: Royal Grand | BY14: Royal Grand | BZ14: Royal Grand | CA14: Royal Grand | CB14: Deluxe Superior | CC14: Deluxe Superior | CD14: Deluxe Superior | CE14: Deluxe Superior | CF14: Deluxe Superior | CG14: Deluxe Superior | CH14: Deluxe Superior | CI14: Hill Top Deluxe | CJ14: Hill Top Deluxe | CK14: Hill Top Deluxe | CL14: Hill Top Deluxe | CM14: Hill Top Deluxe | CN14: Hill Top Deluxe | CO14: Hill Top Deluxe | CP14: Hill Top Deluxe | CQ14: Hill Top Deluxe | CR14: Extra Adult passenger | CS14: Jungle View Venus (A/c) | CT14: Jungle View Venus (A/c) | CU14: Jungle View Venus (A/c) | CV14: Jungle View Venus (A/c) | CW14: Jungle View Venus (A/c) | CX14: Jungle View Venus (A/c) | CY14: Jungle View Venus (A/c) | CZ14: Jungle View Venus (A/c) | DA14: Extra Adult passenger | DC14: Sea Shore (Partial Sea View over the Pool) | DD14: Sea Shore (Partial Sea View over the Pool) | DE14: Sea Shore (Partial Sea View over the Pool) | DF14: Sea Shore (Partial Sea View over the Pool) | DG14: Sea Shore (Partial Sea View over the Pool) | DH14: Sea Shore (Partial Sea View over the Pool) | DI14: Pool View | DJ14: Pool View | DK14: Pool View | DL14: Pool View | DM14: Pool View | DN14: Pool View | DO14: Pool View | DP14: Quadruple Bed Room (04 pax) | DQ14: Quadruple Bed Room (04 pax) | DR14: Quadruple Bed Room (04 pax) | DS14: Majestic Ponmudi Dam View | DT14: Majestic Ponmudi Dam View | DU14: Majestic Ponmudi Dam View | DV14: Majestic Ponmudi Dam View | DW14: Majestic Ponmudi Dam View | DX14: Majestic Ponmudi Dam View | DY14: Majestic Ponmudi Dam View | DZ14: Deluxe Room | EA14: Deluxe Room | EB14: Deluxe Room | EC14: Deluxe Room | ED14: Deluxe Room | EE14: Deluxe Room | EF14: Deluxe Room | EG14: Deluxe Room | EH14: Extra Adult passenger | EI14: Extra Adult passenger | EJ14: Sea Shore (Partial Sea View over the Pool) | EK14: Sea Shore (Partial Sea View over the Pool) | EL14: Sea Shore (Partial Sea View over the Pool) | EM14: Extra Adult passenger | EN14: Extra Adult passenger | EO14: Lagoona Standard Non-Sea View | EP14: Lagoona Standard Non-Sea View | EQ14: Lagoona Standard Non-Sea View | ER14: Lagoona Standard Non-Sea View | ES14: Lagoona Standard Non-Sea View | ET14: Lagoona Standard Non-Sea View | EU14: Lagoona Standard Non-Sea View | EV14: Lagoona Standard Non-Sea View | EW14: Lagoona Standard Non-Sea View | EX14: Extra Adult passenger | EY14: Extra Adult passenger | EZ14: Extra Adult passenger | FA14: Executive Room | FB14: Executive Room | FC14: Executive Room | FD14: Executive Room | FE14: Executive Room | FF14: Executive Room | FG14: Executive Room | FH14: Executive Room | FI14: Executive Room | FJ14: Executive Room | FK14: Standard Room AC | FL14: Standard Room AC | FM14: Standard Room AC | FN14: Standard Room AC | FO14: Standard Room AC | FP14: Standard Room AC | FQ14: Day Nigt Cruise 12PM-9AM | FR14: Day Nigt Cruise 12PM-9AM | FS14: Day Nigt Cruise 12PM-9AM | FT14: Day Nigt Cruise 12PM-9AM | FU14: DLX AC DBL | FV14: DLX AC DBL | FW14: DLX AC DBL | FX14: DLX AC DBL | FY14: DLX AC DBL | FZ14: Club Deluxe Garden view | GA14: Club Deluxe Garden view | GB14: Club Deluxe Garden view | GC14: Club Deluxe Garden view | GD14: Club Deluxe Garden view | GE14: Club Deluxe Garden view | GF14: Club Deluxe Garden view | GG14: Club Deluxe Garden view | GH14: Club Deluxe Garden view | GI14: Jacuzzi Suite Villa | GJ14: Jacuzzi Suite Villa | GK14: Jacuzzi Suite Villa | GL14: Jacuzzi Suite Villa | GM14: Jacuzzi Suite Villa
A15: =IF(B14="","",_xlfn.XLOOKUP(B15,'Raw'!C:C,'Raw'!B:B)) -> Thekkady | B15: KL3 | C15: =IF(B15="","",VLOOKUP(B15,RAW[[Hotel Code]:[Hotel / Resort Name ]],2,0)) -> The Elephant Court | H15: Extra Adult passenger | I15: Garden Suite | J15: Garden Suite | K15: Garden Suite | L15: Garden Suite | M15: Garden Suite | N15: Garden Suite | O15: Garden Suite | P15: Extra Adult passenger | Q15: Extra Adult passenger | R15: Extra Adult passenger | S15: Extra Adult passenger | T15: Extra Adult passenger | U15: Extra Adult passenger | W15: Coastal view room | X15: Coastal view room | Y15: Coastal view room | Z15: Coastal view room | AA15: Coastal view room | AB15: Coastal view room | AC15: Coastal view room | AD15: Coastal view room | AE15: Coastal view room | AF15: Coastal view room | AG15: Coastal view room | AJ15: Lakeview Premium Room | AK15: Lakeview Premium Room | AL15: Lakeview Premium Room | AM15: Lakeview Premium Room | AN15: Lakeview Premium Room | AO15: Lakeview Premium Room | AP15: Lakeview Premium Room | AQ15: Lakeview Premium Room | AR15: Lakeview Premium Room | AS15: Exotica | AT15: Exotica | AU15: Exotica | AV15: Exotica | AW15: Exotica | AX15: Exotica | AY15: Exotica | AZ15: Exotica | BA15: Club Room | BB15: Club Room | BC15: Club Room | BD15: Club Room | BE15: Club Room | BF15: Club Room | BG15: Valley View Room (With Balcony) | BH15: Valley View Room (With Balcony) | BI15: Superior Rooms [With Balcony] | BJ15: Superior Rooms [With Balcony] | BK15: Premium Valley View Cottage (With Balcony) | BL15: Premium Valley View Cottage (With Balcony) | BM15: Extra Adult passenger | BN15: Extra Adult passenger | BO15: Suite Rooms | BP15: Suite Rooms | BQ15: Suite Rooms | BR15: Suite Rooms | BS15: Suite Rooms | BV15: Royal Suite | BW15: Royal Suite | BX15: Royal Suite | BY15: Royal Suite | BZ15: Royal Suite | CA15: Royal Suite | CB15: Pagoda Cottage | CC15: Pagoda Cottage | CD15: Pagoda Cottage | CE15: Pagoda Cottage | CF15: Pagoda Cottage | CG15: Pagoda Cottage | CH15: Pagoda Cottage | CI15: Hill Top Premium | CJ15: Hill Top Premium | CK15: Hill Top Premium | CL15: Hill Top Premium | CM15: Hill Top Premium | CN15: Hill Top Premium | CO15: Hill Top Premium | CP15: Hill Top Premium | CQ15: Hill Top Premium | CR15: Valley View Room (With Balcony) | CS15: DeluxeFamilyRoom-03Pax (Non A/c) | CT15: DeluxeFamilyRoom-03Pax (Non A/c) | CU15: DeluxeFamilyRoom-03Pax (Non A/c) | CV15: DeluxeFamilyRoom-03Pax (Non A/c) | CW15: DeluxeFamilyRoom-03Pax (Non A/c) | CX15: DeluxeFamilyRoom-03Pax (Non A/c) | CY15: DeluxeFamilyRoom-03Pax (Non A/c) | CZ15: DeluxeFamilyRoom-03Pax (Non A/c) | DA15: Premium Valley View Cottage (With Balcony) | DC15: Bay Watch (Sunset Sea View) | DD15: Bay Watch (Sunset Sea View) | DE15: Bay Watch (Sunset Sea View) | DF15: Bay Watch (Sunset Sea View) | DG15: Bay Watch (Sunset Sea View) | DH15: Bay Watch (Sunset Sea View) | DI15: Ocean View | DJ15: Ocean View | DK15: Ocean View | DL15: Ocean View | DM15: Ocean View | DN15: Ocean View | DO15: Ocean View | DP15: Extra Adult passenger | DQ15: Extra Adult passenger | DR15: Extra Adult passenger | DS15: Timeless Jacuzzi Suite | DT15: Timeless Jacuzzi Suite | DU15: Timeless Jacuzzi Suite | DV15: Timeless Jacuzzi Suite | DW15: Timeless Jacuzzi Suite | DX15: Timeless Jacuzzi Suite | DY15: Timeless Jacuzzi Suite | DZ15: Executive Room | EA15: Executive Room | EB15: Executive Room | EC15: Executive Room | ED15: Executive Room | EE15: Executive Room | EF15: Executive Room | EG15: Executive Room | EH15: Valley View Room (With Balcony) | EI15: Valley View Room (With Balcony) | EJ15: Bay Watch (Sunset Sea View) | EK15: Bay Watch (Sunset Sea View) | EL15: Bay Watch (Sunset Sea View) | EM15: Premium Valley View Cottage (With Balcony) | EN15: Premium Valley View Cottage (With Balcony) | EO15: Premium Sea View Rooms with Balcony | EP15: Premium Sea View Rooms with Balcony | EQ15: Premium Sea View Rooms with Balcony | ER15: Premium Sea View Rooms with Balcony | ES15: Premium Sea View Rooms with Balcony | ET15: Premium Sea View Rooms with Balcony | EU15: Premium Sea View Rooms with Balcony | EV15: Premium Sea View Rooms with Balcony | EW15: Premium Sea View Rooms with Balcony | EX15: Superior Rooms [With Balcony] | EY15: Superior Rooms [With Balcony] | EZ15: Superior Rooms [With Balcony] | FA15: Premium Room | FB15: Premium Room | FC15: Premium Room | FD15: Premium Room | FE15: Premium Room | FF15: Premium Room | FG15: Premium Room | FH15: Premium Room | FI15: Premium Room | FJ15: Premium Room | FK15: Standard Twin Bed Room AC | FL15: Standard Twin Bed Room AC | FM15: Standard Twin Bed Room AC | FN15: Standard Twin Bed Room AC | FO15: Standard Twin Bed Room AC | FP15: Standard Twin Bed Room AC | FU15: Extra Adult passenger | FV15: Extra Adult passenger | FW15: Extra Adult passenger | FX15: Extra Adult passenger | FY15: Extra Adult passenger | FZ15: Super Deluxe AC | GA15: Super Deluxe AC | GB15: Super Deluxe AC | GC15: Super Deluxe AC | GD15: Super Deluxe AC | GE15: Super Deluxe AC | GF15: Super Deluxe AC | GG15: Super Deluxe AC | GH15: Super Deluxe AC | GI15: Extra Adult passenger | GJ15: Extra Adult passenger | GK15: Extra Adult passenger | GL15: Extra Adult passenger | GM15: Extra Adult passenger
A16: =IF(B15="","",_xlfn.XLOOKUP(B16,'Raw'!C:C,'Raw'!B:B)) -> Thekkady | B16: KL4 | C16: =IF(B16="","",VLOOKUP(B16,RAW[[Hotel Code]:[Hotel / Resort Name ]],2,0)) -> The Elephant Court | H16: Triple Bed Room (03 pax) | I16: Pool Studio | J16: Pool Studio | K16: Pool Studio | L16: Pool Studio | M16: Pool Studio | N16: Pool Studio | O16: Pool Studio | P16: Child with bed | Q16: Child with bed | R16: Child with bed | S16: Child with bed | T16: Child with bed | U16: Child with bed | W16: Premium Sea view Room | X16: Premium Sea view Room | Y16: Premium Sea view Room | Z16: Premium Sea view Room | AA16: Premium Sea view Room | AB16: Premium Sea view Room | AC16: Premium Sea view Room | AD16: Premium Sea view Room | AE16: Premium Sea view Room | AF16: Premium Sea view Room | AG16: Premium Sea view Room | AJ16: Lakeview Suite Room | AK16: Lakeview Suite Room | AL16: Lakeview Suite Room | AM16: Lakeview Suite Room | AN16: Lakeview Suite Room | AO16: Lakeview Suite Room | AP16: Lakeview Suite Room | AQ16: Lakeview Suite Room | AR16: Lakeview Suite Room | AS16: Raja Ravi Varma Suite | AT16: Raja Ravi Varma Suite | AU16: Raja Ravi Varma Suite | AV16: Raja Ravi Varma Suite | AW16: Raja Ravi Varma Suite | AX16: Raja Ravi Varma Suite | AY16: Raja Ravi Varma Suite | AZ16: Raja Ravi Varma Suite | BA16: Extra Adult passenger | BB16: Extra Adult passenger | BC16: Extra Adult passenger | BD16: Extra Adult passenger | BE16: Extra Adult passenger | BF16: Extra Adult passenger | BG16: Child with bed | BH16: Child with bed | BI16: Child with bed | BJ16: Child with bed | BK16: Child with bed | BL16: Child with bed | BM16: Triple Bed Room (03 pax) | BN16: Triple Bed Room (03 pax) | BO16: Tree House | BP16: Tree House | BQ16: Tree House | BR16: Tree House | BS16: Tree House | BV16: Extra Adult passenger | BW16: Extra Adult passenger | BX16: Extra Adult passenger | BY16: Extra Adult passenger | BZ16: Extra Adult passenger | CA16: Extra Adult passenger | CB16: Suite | CC16: Suite | CD16: Suite | CE16: Suite | CF16: Suite | CG16: Suite | CH16: Suite | CI16: Valley View Family Room (4 PAX) | CJ16: Valley View Family Room (4 PAX) | CK16: Valley View Family Room (4 PAX) | CL16: Valley View Family Room (4 PAX) | CM16: Valley View Family Room (4 PAX) | CN16: Valley View Family Room (4 PAX) | CO16: Valley View Family Room (4 PAX) | CP16: Valley View Family Room (4 PAX) | CQ16: Valley View Family Room (4 PAX) | CR16: Child with bed | CS16: Jungle View Family- 4Pax (Non A/c) | CT16: Jungle View Family- 4Pax (Non A/c) | CU16: Jungle View Family- 4Pax (Non A/c) | CV16: Jungle View Family- 4Pax (Non A/c) | CW16: Jungle View Family- 4Pax (Non A/c) | CX16: Jungle View Family- 4Pax (Non A/c) | CY16: Jungle View Family- 4Pax (Non A/c) | CZ16: Jungle View Family- 4Pax (Non A/c) | DA16: Child with bed | DC16: Exotic Sea View (Best Sea View) | DD16: Exotic Sea View (Best Sea View) | DE16: Exotic Sea View (Best Sea View) | DF16: Exotic Sea View (Best Sea View) | DG16: Exotic Sea View (Best Sea View) | DH16: Exotic Sea View (Best Sea View) | DI16: Heritage | DJ16: Heritage | DK16: Heritage | DL16: Heritage | DM16: Heritage | DN16: Heritage | DO16: Heritage | DP16: Triple Bed Room (03 pax) | DQ16: Triple Bed Room (03 pax) | DR16: Triple Bed Room (03 pax) | DS16: Fabulous Interconnecting Suite (04 Pax) | DT16: Fabulous Interconnecting Suite (04 Pax) | DU16: Fabulous Interconnecting Suite (04 Pax) | DV16: Fabulous Interconnecting Suite (04 Pax) | DW16: Fabulous Interconnecting Suite (04 Pax) | DX16: Fabulous Interconnecting Suite (04 Pax) | DY16: Fabulous Interconnecting Suite (04 Pax) | DZ16: Deluxe Suite | EA16: Deluxe Suite | EB16: Deluxe Suite | EC16: Deluxe Suite | ED16: Deluxe Suite | EE16: Deluxe Suite | EF16: Deluxe Suite | EG16: Deluxe Suite | EH16: Child with bed | EI16: Child with bed | EJ16: Exotic Sea View (Best Sea View) | EK16: Exotic Sea View (Best Sea View) | EL16: Exotic Sea View (Best Sea View) | EM16: Child with bed | EN16: Child with bed | EO16: Premium Twin Room (Non Sea View) | EP16: Premium Twin Room (Non Sea View) | EQ16: Premium Twin Room (Non Sea View) | ER16: Premium Twin Room (Non Sea View) | ES16: Premium Twin Room (Non Sea View) | ET16: Premium Twin Room (Non Sea View) | EU16: Premium Twin Room (Non Sea View) | EV16: Premium Twin Room (Non Sea View) | EW16: Premium Twin Room (Non Sea View) | EX16: Child with bed | EY16: Child with bed | EZ16: Child with bed | FA16: Club Room | FB16: Club Room | FC16: Club Room | FD16: Club Room | FE16: Club Room | FF16: Club Room | FG16: Club Room | FH16: Club Room | FI16: Club Room | FJ16: Club Room | FK16: Deluxe Room AC | FL16: Deluxe Room AC | FM16: Deluxe Room AC | FN16: Deluxe Room AC | FO16: Deluxe Room AC | FP16: Deluxe Room AC | FU16: Child with bed | FV16: Child with bed | FW16: Child with bed | FX16: Child with bed | FY16: Child with bed | FZ16: Premium AC | GA16: Premium AC | GB16: Premium AC | GC16: Premium AC | GD16: Premium AC | GE16: Premium AC | GF16: Premium AC | GG16: Premium AC | GH16: Premium AC | GI16: Child with bed | GJ16: Child with bed | GK16: Child with bed | GL16: Child with bed | GM16: Child with bed
A17: =IF(B16="","",_xlfn.XLOOKUP(B17,'Raw'!C:C,'Raw'!B:B)) -> Thekkady | B17: KL5 | C17: =IF(B17="","",VLOOKUP(B17,RAW[[Hotel Code]:[Hotel / Resort Name ]],2,0)) -> The Elephant Court | H17: Child with bed | I17: Extra Adult passenger | J17: Extra Adult passenger | K17: Extra Adult passenger | L17: Extra Adult passenger | M17: Extra Adult passenger | N17: Extra Adult passenger | O17: Extra Adult passenger | P17: Child without bed | Q17: Child without bed | R17: Child without bed | S17: Child without bed | T17: Child without bed | U17: Child without bed | W17: Lounge Suite | X17: Lounge Suite | Y17: Lounge Suite | Z17: Lounge Suite | AA17: Lounge Suite | AB17: Lounge Suite | AC17: Lounge Suite | AD17: Lounge Suite | AE17: Lounge Suite | AF17: Lounge Suite | AG17: Lounge Suite | AJ17: Pool Villa | AK17: Pool Villa | AL17: Pool Villa | AM17: Pool Villa | AN17: Pool Villa | AO17: Pool Villa | AP17: Pool Villa | AQ17: Pool Villa | AR17: Pool Villa | AS17: Heritage Suite | AT17: Heritage Suite | AU17: Heritage Suite | AV17: Heritage Suite | AW17: Heritage Suite | AX17: Heritage Suite | AY17: Heritage Suite | AZ17: Heritage Suite | BA17: Child with bed | BB17: Child with bed | BC17: Child with bed | BD17: Child with bed | BE17: Child with bed | BF17: Child with bed | BG17: Child without bed | BH17: Child without bed | BI17: Child without bed | BJ17: Child without bed | BK17: Child without bed | BL17: Child without bed | BM17: Child with bed | BN17: Child with bed | BO17: Extra Adult passenger | BP17: Extra Adult passenger | BQ17: Extra Adult passenger | BR17: Extra Adult passenger | BS17: Extra Adult passenger | BV17: Child with bed | BW17: Child with bed | BX17: Child with bed | BY17: Child with bed | BZ17: Child with bed | CA17: Child with bed | CB17: Extra Adult passenger | CC17: Extra Adult passenger | CD17: Extra Adult passenger | CE17: Extra Adult passenger | CF17: Extra Adult passenger | CG17: Extra Adult passenger | CH17: Extra Adult passenger | CI17: Tea Valley Deluxe | CJ17: Tea Valley Deluxe | CK17: Tea Valley Deluxe | CL17: Tea Valley Deluxe | CM17: Tea Valley Deluxe | CN17: Tea Valley Deluxe | CO17: Tea Valley Deluxe | CP17: Tea Valley Deluxe | CQ17: Tea Valley Deluxe | CR17: Child without bed | CS17: Jungle View Family- 4Pax (A/c) | CT17: Jungle View Family- 4Pax (A/c) | CU17: Jungle View Family- 4Pax (A/c) | CV17: Jungle View Family- 4Pax (A/c) | CW17: Jungle View Family- 4Pax (A/c) | CX17: Jungle View Family- 4Pax (A/c) | CY17: Jungle View Family- 4Pax (A/c) | CZ17: Jungle View Family- 4Pax (A/c) | DA17: Child without bed | DC17: Wooden Suite (Partial Sea View) | DD17: Wooden Suite (Partial Sea View) | DE17: Wooden Suite (Partial Sea View) | DF17: Wooden Suite (Partial Sea View) | DG17: Wooden Suite (Partial Sea View) | DH17: Wooden Suite (Partial Sea View) | DI17: Royal Seaview | DJ17: Royal Seaview | DK17: Royal Seaview | DL17: Royal Seaview | DM17: Royal Seaview | DN17: Royal Seaview | DO17: Royal Seaview | DP17: Child with bed | DQ17: Child with bed | DR17: Child with bed | DS17: Extra Adult passenger | DT17: Extra Adult passenger | DU17: Extra Adult passenger | DV17: Extra Adult passenger | DW17: Extra Adult passenger | DX17: Extra Adult passenger | DY17: Extra Adult passenger | DZ17: Premium Suite | EA17: Premium Suite | EB17: Premium Suite | EC17: Premium Suite | ED17: Premium Suite | EE17: Premium Suite | EF17: Premium Suite | EG17: Premium Suite | EH17: Child without bed | EI17: Child without bed | EJ17: Wooden Suite (Partial Sea View) | EK17: Wooden Suite (Partial Sea View) | EL17: Wooden Suite (Partial Sea View) | EM17: Child without bed | EN17: Child without bed | EO17: Premium Sea View Suite Room with Balcony | EP17: Premium Sea View Suite Room with Balcony | EQ17: Premium Sea View Suite Room with Balcony | ER17: Premium Sea View Suite Room with Balcony | ES17: Premium Sea View Suite Room with Balcony | ET17: Premium Sea View Suite Room with Balcony | EU17: Premium Sea View Suite Room with Balcony | EV17: Premium Sea View Suite Room with Balcony | EW17: Premium Sea View Suite Room with Balcony | EX17: Child without bed | EY17: Child without bed | EZ17: Child without bed | FA17: Viceroy Room | FB17: Viceroy Room | FC17: Viceroy Room | FD17: Viceroy Room | FE17: Viceroy Room | FF17: Viceroy Room | FG17: Viceroy Room | FH17: Viceroy Room | FI17: Viceroy Room | FJ17: Viceroy Room | FK17: Suite Room | FL17: Suite Room | FM17: Suite Room | FN17: Suite Room | FO17: Suite Room | FP17: Suite Room | FU17: Child without bed | FV17: Child without bed | FW17: Child without bed | FX17: Child without bed | FY17: Child without bed | FZ17: Super Deluxe Family Room (4 Pax) | GA17: Super Deluxe Family Room (4 Pax) | GB17: Super Deluxe Family Room (4 Pax) | GC17: Super Deluxe Family Room (4 Pax) | GD17: Super Deluxe Family Room (4 Pax) | GE17: Super Deluxe Family Room (4 Pax) | GF17: Super Deluxe Family Room (4 Pax) | GG17: Super Deluxe Family Room (4 Pax) | GH17: Super Deluxe Family Room (4 Pax) | GI17: Child without bed | GJ17: Child without bed | GK17: Child without bed | GL17: Child without bed | GM17: Child without bed
A18: =IF(B17="","",_xlfn.XLOOKUP(B18,'Raw'!C:C,'Raw'!B:B)) -> Thekkady | B18: KL6 | C18: =IF(B18="","",VLOOKUP(B18,RAW[[Hotel Code]:[Hotel / Resort Name ]],2,0)) -> The Elephant Court | H18: Child without bed | I18: Child with bed | J18: Child with bed | K18: Child with bed | L18: Child with bed | M18: Child with bed | N18: Child with bed | O18: Child with bed | P18: Premium Room | Q18: Premium Room | R18: Premium Room | S18: Premium Room | T18: Premium Room | U18: Premium Room | W18: Lounge Seaview Suite | X18: Lounge Seaview Suite | Y18: Lounge Seaview Suite | Z18: Lounge Seaview Suite | AA18: Lounge Seaview Suite | AB18: Lounge Seaview Suite | AC18: Lounge Seaview Suite | AD18: Lounge Seaview Suite | AE18: Lounge Seaview Suite | AF18: Lounge Seaview Suite | AG18: Lounge Seaview Suite | AJ18: Premium Pool Villa (2 Bed Room unit) | AK18: Premium Pool Villa (2 Bed Room unit) | AL18: Premium Pool Villa (2 Bed Room unit) | AM18: Premium Pool Villa (2 Bed Room unit) | AN18: Premium Pool Villa (2 Bed Room unit) | AO18: Premium Pool Villa (2 Bed Room unit) | AP18: Premium Pool Villa (2 Bed Room unit) | AQ18: Premium Pool Villa (2 Bed Room unit) | AR18: Premium Pool Villa (2 Bed Room unit) | AS18: Extra Adult passenger | AT18: Extra Adult passenger | AU18: Extra Adult passenger | AV18: Extra Adult passenger | AW18: Extra Adult passenger | AX18: Extra Adult passenger | AY18: Extra Adult passenger | AZ18: Extra Adult passenger | BA18: Child without bed | BB18: Child without bed | BC18: Child without bed | BD18: Child without bed | BE18: Child without bed | BF18: Child without bed | BM18: Child without bed | BN18: Child without bed | BV18: Child without bed | BW18: Child without bed | BX18: Child without bed | BY18: Child without bed | BZ18: Child without bed | CA18: Child without bed | CB18: Child with bed | CC18: Child with bed | CD18: Child with bed | CE18: Child with bed | CF18: Child with bed | CG18: Child with bed | CH18: Child with bed | CI18: Tea Valley Premium | CJ18: Tea Valley Premium | CK18: Tea Valley Premium | CL18: Tea Valley Premium | CM18: Tea Valley Premium | CN18: Tea Valley Premium | CO18: Tea Valley Premium | CP18: Tea Valley Premium | CQ18: Tea Valley Premium | CS18: Extra Adult passenger | CT18: Extra Adult passenger | CU18: Extra Adult passenger | CV18: Extra Adult passenger | CW18: Extra Adult passenger | CX18: Extra Adult passenger | CY18: Extra Adult passenger | CZ18: Extra Adult passenger | DC18: Pearl Sea View With Terrace (Best Sea View) | DD18: Pearl Sea View With Terrace (Best Sea View) | DE18: Pearl Sea View With Terrace (Best Sea View) | DF18: Pearl Sea View With Terrace (Best Sea View) | DG18: Pearl Sea View With Terrace (Best Sea View) | DH18: Pearl Sea View With Terrace (Best Sea View) | DI18: Panoramic Vista | DJ18: Panoramic Vista | DK18: Panoramic Vista | DL18: Panoramic Vista | DM18: Panoramic Vista | DN18: Panoramic Vista | DO18: Panoramic Vista | DP18: Child without bed | DQ18: Child without bed | DR18: Child without bed | DS18: Child with bed | DT18: Child with bed | DU18: Child with bed | DV18: Child with bed | DW18: Child with bed | DX18: Child with bed | DY18: Child with bed | DZ18: Extra Adult passenger | EA18: Extra Adult passenger | EB18: Extra Adult passenger | EC18: Extra Adult passenger | ED18: Extra Adult passenger | EE18: Extra Adult passenger | EF18: Extra Adult passenger | EG18: Extra Adult passenger | EJ18: Pearl Sea View With Terrace (Best Sea View) | EK18: Pearl Sea View With Terrace (Best Sea View) | EL18: Pearl Sea View With Terrace (Best Sea View) | EO18: Cottage Villa with Living Area | EP18: Cottage Villa with Living Area | EQ18: Cottage Villa with Living Area | ER18: Cottage Villa with Living Area | ES18: Cottage Villa with Living Area | ET18: Cottage Villa with Living Area | EU18: Cottage Villa with Living Area | EV18: Cottage Villa with Living Area | EW18: Cottage Villa with Living Area | FA18: Majestic Luxury [Bathtub Room] | FB18: Majestic Luxury [Bathtub Room] | FC18: Majestic Luxury [Bathtub Room] | FD18: Majestic Luxury [Bathtub Room] | FE18: Majestic Luxury [Bathtub Room] | FF18: Majestic Luxury [Bathtub Room] | FG18: Majestic Luxury [Bathtub Room] | FH18: Majestic Luxury [Bathtub Room] | FI18: Majestic Luxury [Bathtub Room] | FJ18: Majestic Luxury [Bathtub Room] | FK18: Extra Adult passenger | FL18: Extra Adult passenger | FM18: Extra Adult passenger | FN18: Extra Adult passenger | FO18: Extra Adult passenger | FP18: Extra Adult passenger | FZ18: The Pool Club | GA18: The Pool Club | GB18: The Pool Club | GC18: The Pool Club | GD18: The Pool Club | GE18: The Pool Club | GF18: The Pool Club | GG18: The Pool Club | GH18: The Pool Club
A19: =IF(B18="","",_xlfn.XLOOKUP(B19,'Raw'!C:C,'Raw'!B:B)) -> Thekkady | B19: KL7 | C19: =IF(B19="","",VLOOKUP(B19,RAW[[Hotel Code]:[Hotel / Resort Name ]],2,0)) -> The Elephant Court | I19: Child without bed | J19: Child without bed | K19: Child without bed | L19: Child without bed | M19: Child without bed | N19: Child without bed | O19: Child without bed | W19: Ocean Breeze Suite | X19: Ocean Breeze Suite | Y19: Ocean Breeze Suite | Z19: Ocean Breeze Suite | AA19: Ocean Breeze Suite | AB19: Ocean Breeze Suite | AC19: Ocean Breeze Suite | AD19: Ocean Breeze Suite | AE19: Ocean Breeze Suite | AF19: Ocean Breeze Suite | AG19: Ocean Breeze Suite | AJ19: Extra Adult passenger | AK19: Extra Adult passenger | AL19: Extra Adult passenger | AM19: Extra Adult passenger | AN19: Extra Adult passenger | AO19: Extra Adult passenger | AP19: Extra Adult passenger | AQ19: Extra Adult passenger | AR19: Extra Adult passenger | AS19: Child with bed | AT19: Child with bed | AU19: Child with bed | AV19: Child with bed | AW19: Child with bed | AX19: Child with bed | AY19: Child with bed | AZ19: Child with bed | CB19: Child without bed | CC19: Child without bed | CD19: Child without bed | CE19: Child without bed | CF19: Child without bed | CG19: Child without bed | CH19: Child without bed | CI19: Extra Adult passenger | CJ19: Extra Adult passenger | CK19: Extra Adult passenger | CL19: Extra Adult passenger | CM19: Extra Adult passenger | CN19: Extra Adult passenger | CO19: Extra Adult passenger | CP19: Extra Adult passenger | CQ19: Extra Adult passenger | CS19: Child with bed | CT19: Child with bed | CU19: Child with bed | CV19: Child with bed | CW19: Child with bed | CX19: Child with bed | CY19: Child with bed | CZ19: Child with bed | DC19: Extra Adult passenger | DD19: Extra Adult passenger | DE19: Extra Adult passenger | DF19: Extra Adult passenger | DG19: Extra Adult passenger | DH19: Extra Adult passenger | DI19: D Series (No View) | DJ19: D Series (No View) | DK19: D Series (No View) | DL19: D Series (No View) | DM19: D Series (No View) | DN19: D Series (No View) | DO19: D Series (No View) | DS19: Child without bed | DT19: Child without bed | DU19: Child without bed | DV19: Child without bed | DW19: Child without bed | DX19: Child without bed | DY19: Child without bed | DZ19: Child with bed | EA19: Child with bed | EB19: Child with bed | EC19: Child with bed | ED19: Child with bed | EE19: Child with bed | EF19: Child with bed | EG19: Child with bed | EJ19: Extra Adult passenger | EK19: Extra Adult passenger | EL19: Extra Adult passenger | EO19: Extra Adult passenger | EP19: Extra Adult passenger | EQ19: Extra Adult passenger | ER19: Extra Adult passenger | ES19: Extra Adult passenger | ET19: Extra Adult passenger | EU19: Extra Adult passenger | EV19: Extra Adult passenger | EW19: Extra Adult passenger | FA19: Royale Luxury Jacuzzi | FB19: Royale Luxury Jacuzzi | FC19: Royale Luxury Jacuzzi | FD19: Royale Luxury Jacuzzi | FE19: Royale Luxury Jacuzzi | FF19: Royale Luxury Jacuzzi | FG19: Royale Luxury Jacuzzi | FH19: Royale Luxury Jacuzzi | FI19: Royale Luxury Jacuzzi | FJ19: Royale Luxury Jacuzzi | FZ19: Extra Adult passenger | GA19: Extra Adult passenger | GB19: Extra Adult passenger | GC19: Extra Adult passenger | GD19: Extra Adult passenger | GE19: Extra Adult passenger | GF19: Extra Adult passenger | GG19: Extra Adult passenger | GH19: Extra Adult passenger
A20: =IF(B19="","",_xlfn.XLOOKUP(B20,'Raw'!C:C,'Raw'!B:B)) -> Thekkady | B20: KL8 | C20: =IF(B20="","",VLOOKUP(B20,RAW[[Hotel Code]:[Hotel / Resort Name ]],2,0)) -> The Elephant Court | W20: Grand Family Suite | X20: Grand Family Suite | Y20: Grand Family Suite | Z20: Grand Family Suite | AA20: Grand Family Suite | AB20: Grand Family Suite | AC20: Grand Family Suite | AD20: Grand Family Suite | AE20: Grand Family Suite | AF20: Grand Family Suite | AG20: Grand Family Suite | AJ20: Child with bed | AK20: Child with bed | AL20: Child with bed | AM20: Child with bed | AN20: Child with bed | AO20: Child with bed | AP20: Child with bed | AQ20: Child with bed | AR20: Child with bed | AS20: Child without bed | AT20: Child without bed | AU20: Child without bed | AV20: Child without bed | AW20: Child without bed | AX20: Child without bed | AY20: Child without bed | AZ20: Child without bed | CI20: Child with bed | CJ20: Child with bed | CK20: Child with bed | CL20: Child with bed | CM20: Child with bed | CN20: Child with bed | CO20: Child with bed | CP20: Child with bed | CQ20: Child with bed | CS20: Child without bed | CT20: Child without bed | CU20: Child without bed | CV20: Child without bed | CW20: Child without bed | CX20: Child without bed | CY20: Child without bed | CZ20: Child without bed | DC20: Child with bed | DD20: Child with bed | DE20: Child with bed | DF20: Child with bed | DG20: Child with bed | DH20: Child with bed | DZ20: Child without bed | EA20: Child without bed | EB20: Child without bed | EC20: Child without bed | ED20: Child without bed | EE20: Child without bed | EF20: Child without bed | EG20: Child without bed | EJ20: Child with bed | EK20: Child with bed | EL20: Child with bed | EO20: Child with bed | EP20: Child with bed | EQ20: Child with bed | ER20: Child with bed | ES20: Child with bed | ET20: Child with bed | EU20: Child with bed | EV20: Child with bed | EW20: Child with bed | FA20: Extra Adult passenger | FB20: Extra Adult passenger | FC20: Extra Adult passenger | FD20: Extra Adult passenger | FE20: Extra Adult passenger | FF20: Extra Adult passenger | FG20: Extra Adult passenger | FH20: Extra Adult passenger | FI20: Extra Adult passenger | FJ20: Extra Adult passenger | FZ20: Child with bed | GA20: Child with bed | GB20: Child with bed | GC20: Child with bed | GD20: Child with bed | GE20: Child with bed | GF20: Child with bed | GG20: Child with bed | GH20: Child with bed
A21: =IF(B20="","",_xlfn.XLOOKUP(B21,'Raw'!C:C,'Raw'!B:B)) -> Thekkady | B21: KL9 | C21: =IF(B21="","",VLOOKUP(B21,RAW[[Hotel Code]:[Hotel / Resort Name ]],2,0)) -> Peppervine | W21: Extra Adult passenger | X21: Extra Adult passenger | Y21: Extra Adult passenger | Z21: Extra Adult passenger | AA21: Extra Adult passenger | AB21: Extra Adult passenger | AC21: Extra Adult passenger | AD21: Extra Adult passenger | AE21: Extra Adult passenger | AF21: Extra Adult passenger | AG21: Extra Adult passenger | AJ21: Child without bed | AK21: Child without bed | AL21: Child without bed | AM21: Child without bed | AN21: Child without bed | AO21: Child without bed | AP21: Child without bed | AQ21: Child without bed | AR21: Child without bed | CI21: Child without bed | CJ21: Child without bed | CK21: Child without bed | CL21: Child without bed | CM21: Child without bed | CN21: Child without bed | CO21: Child without bed | CP21: Child without bed | CQ21: Child without bed | DC21: Child without bed | DD21: Child without bed | DE21: Child without bed | DF21: Child without bed | DG21: Child without bed | DH21: Child without bed | EJ21: Child without bed | EK21: Child without bed | EL21: Child without bed | EO21: Child without bed | EP21: Child without bed | EQ21: Child without bed | ER21: Child without bed | ES21: Child without bed | ET21: Child without bed | EU21: Child without bed | EV21: Child without bed | EW21: Child without bed | FA21: Child with bed | FB21: Child with bed | FC21: Child with bed | FD21: Child with bed | FE21: Child with bed | FF21: Child with bed | FG21: Child with bed | FH21: Child with bed | FI21: Child with bed | FJ21: Child with bed | FZ21: Child without bed | GA21: Child without bed | GB21: Child without bed | GC21: Child without bed | GD21: Child without bed | GE21: Child without bed | GF21: Child without bed | GG21: Child without bed | GH21: Child without bed
A22: =IF(B21="","",_xlfn.XLOOKUP(B22,'Raw'!C:C,'Raw'!B:B)) -> Thekkady | B22: KL10 | C22: =IF(B22="","",VLOOKUP(B22,RAW[[Hotel Code]:[Hotel / Resort Name ]],2,0)) -> Peppervine | W22: Child with bed | X22: Child with bed | Y22: Child with bed | Z22: Child with bed | AA22: Child with bed | AB22: Child with bed | AC22: Child with bed | AD22: Child with bed | AE22: Child with bed | AF22: Child with bed | AG22: Child with bed | FA22: Child without bed | FB22: Child without bed | FC22: Child without bed | FD22: Child without bed | FE22: Child without bed | FF22: Child without bed | FG22: Child without bed | FH22: Child without bed | FI22: Child without bed | FJ22: Child without bed
A23: =IF(B22="","",_xlfn.XLOOKUP(B23,'Raw'!C:C,'Raw'!B:B)) -> Thekkady | B23: KL11 | C23: =IF(B23="","",VLOOKUP(B23,RAW[[Hotel Code]:[Hotel / Resort Name ]],2,0)) -> Peppervine | H23: {=TRANSPOSE($B$2:$B$9)} -> Alleppey | I23: Thekkady | J23: Kovalam | K23: Thiruvananthapuram | L23: Munnar | M23: Varkala | N23: Kochi | O23: 0 | W23: Child without bed | X23: Child without bed | Y23: Child without bed | Z23: Child without bed | AA23: Child without bed | AB23: Child without bed | AC23: Child without bed | AD23: Child without bed | AE23: Child without bed | AF23: Child without bed | AG23: Child without bed
A24: =IF(B23="","",_xlfn.XLOOKUP(B24,'Raw'!C:C,'Raw'!B:B)) -> Thekkady | B24: KL12 | C24: =IF(B24="","",VLOOKUP(B24,RAW[[Hotel Code]:[Hotel / Resort Name ]],2,0)) -> Peppervine | H24: {=IF(H$23=0,"",_xlfn._xlws.FILTER(RAW[[#All],[Hotel / Resort Name ]],RAW[[#All],[Destination ]]=Sheet2!H$23))} -> Venice Iva Residency | I24: {=IF(I$23=0,"",_xlfn._xlws.FILTER(RAW[[#All],[Hotel / Resort Name ]],RAW[[#All],[Destination ]]=Sheet2!I$23))} -> The Elephant Court | J24: {=IF(J$23=0,"",_xlfn._xlws.FILTER(RAW[[#All],[Hotel / Resort Name ]],RAW[[#All],[Destination ]]=Sheet2!J$23))} -> Uday Samudra Beach Hotel | K24: {=IF(K$23=0,"",_xlfn._xlws.FILTER(RAW[[#All],[Hotel / Resort Name ]],RAW[[#All],[Destination ]]=Sheet2!K$23))} -> Uday Suites, The Airport Hotel | L24: {=IF(L$23=0,"",_xlfn._xlws.FILTER(RAW[[#All],[Hotel / Resort Name ]],RAW[[#All],[Destination ]]=Sheet2!L$23))} -> Tea castle resort | M24: {=IF(M$23=0,"",_xlfn._xlws.FILTER(RAW[[#All],[Hotel / Resort Name ]],RAW[[#All],[Destination ]]=Sheet2!M$23))} -> Sunview Beach Resort & Spa by Citrine | N24: {=IF(N$23=0,"",_xlfn._xlws.FILTER(RAW[[#All],[Hotel / Resort Name ]],RAW[[#All],[Destination ]]=Sheet2!N$23))} -> Broad Bean Hotel | O24: {=IF(O$23=0,"",_xlfn._xlws.FILTER(RAW[[#All],[Hotel / Resort Name ]],RAW[[#All],[Destination ]]=Sheet2!O$23))} | ... Z24: {=IF(Z$23=0,"",_xlfn._xlws.FILTER(RAW[[#All],[Hotel / Resort Name ]],RAW[[#All],[Destination ]]=Sheet2!Z$23))} -> #VALUE!
A25: =IF(B24="","",_xlfn.XLOOKUP(B25,'Raw'!C:C,'Raw'!B:B)) -> Thekkady | B25: KL13 | C25: =IF(B25="","",VLOOKUP(B25,RAW[[Hotel Code]:[Hotel / Resort Name ]],2,0)) -> Peppervine | H25: Uday Backwater Resort | I25: The Elephant Court | J25: Uday Samudra Leisure Beach Hotel | K25: Uday Suites, The Airport Hotel | L25: Tea castle resort | M25: Sunview Beach Resort & Spa by Citrine | N25: Broad Bean Hotel
A26: =IF(B25="","",_xlfn.XLOOKUP(B26,'Raw'!C:C,'Raw'!B:B)) -> Thekkady | B26: KL14 | C26: =IF(B26="","",VLOOKUP(B26,RAW[[Hotel Code]:[Hotel / Resort Name ]],2,0)) -> Peppervine | H26: Uday Backwater Resort | I26: The Elephant Court | J26: Uday Samudra Leisure Beach Hotel | K26: Uday Suites, The Airport Hotel | L26: Tea castle resort | M26: Sunview Beach Resort & Spa by Citrine | N26: Broad Bean Hotel
A27: =IF(B26="","",_xlfn.XLOOKUP(B27,'Raw'!C:C,'Raw'!B:B)) -> Kovalam | B27: KL15 | C27: =IF(B27="","",VLOOKUP(B27,RAW[[Hotel Code]:[Hotel / Resort Name ]],2,0)) -> Uday Samudra Beach Hotel | H27: Uday Backwater Resort | I27: The Elephant Court | J27: Uday Samudra Leisure Beach Hotel | K27: Uday Suites, The Airport Hotel | L27: Tea castle resort | M27: Sunview Beach Resort & Spa by Citrine | N27: Broad Bean Hotel
A28: =IF(B27="","",_xlfn.XLOOKUP(B28,'Raw'!C:C,'Raw'!B:B)) -> Kovalam | B28: KL16 | C28: =IF(B28="","",VLOOKUP(B28,RAW[[Hotel Code]:[Hotel / Resort Name ]],2,0)) -> Uday Samudra Leisure Beach Hotel | H28: Uday Backwater Resort | I28: The Elephant Court | J28: Uday Samudra Leisure Beach Hotel | K28: Uday Suites, The Airport Hotel | L28: Tea castle resort | M28: Sunview Beach Resort & Spa by Citrine | N28: Broad Bean Hotel
A29: =IF(B28="","",_xlfn.XLOOKUP(B29,'Raw'!C:C,'Raw'!B:B)) -> Kovalam | B29: KL17 | C29: =IF(B29="","",VLOOKUP(B29,RAW[[Hotel Code]:[Hotel / Resort Name ]],2,0)) -> Uday Samudra Leisure Beach Hotel | H29: Uday Backwater Resort | I29: The Elephant Court | J29: Uday Samudra Leisure Beach Hotel | K29: Uday Suites, The Airport Hotel | L29: Tea castle resort | M29: Sunview Beach Resort & Spa by Citrine | N29: Broad Bean Hotel
A30: =IF(B29="","",_xlfn.XLOOKUP(B30,'Raw'!C:C,'Raw'!B:B)) -> Kovalam | B30: KL18 | C30: =IF(B30="","",VLOOKUP(B30,RAW[[Hotel Code]:[Hotel / Resort Name ]],2,0)) -> Uday Samudra Leisure Beach Hotel | H30: Uday Backwater Resort | I30: The Elephant Court | J30: Uday Samudra Leisure Beach Hotel | K30: Uday Suites, The Airport Hotel | L30: The Breeze Resort | M30: Sunview Beach Resort & Spa by Citrine | N30: Broad Bean Hotel
A31: =IF(B30="","",_xlfn.XLOOKUP(B31,'Raw'!C:C,'Raw'!B:B)) -> Kovalam | B31: KL19 | C31: =IF(B31="","",VLOOKUP(B31,RAW[[Hotel Code]:[Hotel / Resort Name ]],2,0)) -> Uday Samudra Leisure Beach Hotel | H31: Uday Backwater Resort | I31: Peppervine | J31: Uday Samudra Leisure Beach Hotel | K31: Uday Suites, The Airport Hotel | L31: The Breeze Resort | N31: Broad Bean Hotel
A32: =IF(B31="","",_xlfn.XLOOKUP(B32,'Raw'!C:C,'Raw'!B:B)) -> Kovalam | B32: KL20 | C32: =IF(B32="","",VLOOKUP(B32,RAW[[Hotel Code]:[Hotel / Resort Name ]],2,0)) -> Uday Samudra Leisure Beach Hotel | H32: Uday Backwater Resort | I32: Peppervine | J32: Uday Samudra Leisure Beach Hotel | L32: The Whispering Meadows | N32: Napier Heritage Fort
A33: =IF(B32="","",_xlfn.XLOOKUP(B33,'Raw'!C:C,'Raw'!B:B)) -> Kovalam | B33: KL21 | C33: =IF(B33="","",VLOOKUP(B33,RAW[[Hotel Code]:[Hotel / Resort Name ]],2,0)) -> Uday Samudra Leisure Beach Hotel | H33: Uday Backwater Resort | I33: Peppervine | J33: Uday Samudra Leisure Beach Hotel | L33: The Whispering Meadows | N33: Napier Heritage Fort
A34: =IF(B33="","",_xlfn.XLOOKUP(B34,'Raw'!C:C,'Raw'!B:B)) -> Kovalam | B34: KL22 | C34: =IF(B34="","",VLOOKUP(B34,RAW[[Hotel Code]:[Hotel / Resort Name ]],2,0)) -> Uday Samudra Leisure Beach Hotel | H34: Venice Iva Residency | I34: Peppervine | J34: Uday Samudra Leisure Beach Hotel | L34: Blossom Hill Resort | N34: Napier Heritage Fort
A35: =IF(B34="","",_xlfn.XLOOKUP(B35,'Raw'!C:C,'Raw'!B:B)) -> Kovalam | B35: KL23 | C35: =IF(B35="","",VLOOKUP(B35,RAW[[Hotel Code]:[Hotel / Resort Name ]],2,0)) -> Uday Samudra Leisure Beach Hotel | H35: Venice Iva Residency | I35: Peppervine | J35: Uday Samudra Leisure Beach Hotel | L35: Blossom Hill Resort | N35: Napier Heritage Fort
A36: =IF(B35="","",_xlfn.XLOOKUP(B36,'Raw'!C:C,'Raw'!B:B)) -> Kovalam | B36: KL24 | C36: =IF(B36="","",VLOOKUP(B36,RAW[[Hotel Code]:[Hotel / Resort Name ]],2,0)) -> Uday Samudra Leisure Beach Hotel | H36: Casino Houseboats | I36: Peppervine | J36: The Byke Heritage - Puja Samudra | L36: Seven Springs Plantation Resort | N36: Napier Heritage Fort
A37: =IF(B36="","",_xlfn.XLOOKUP(B37,'Raw'!C:C,'Raw'!B:B)) -> Kovalam | B37: KL25 | C37: =IF(B37="","",VLOOKUP(B37,RAW[[Hotel Code]:[Hotel / Resort Name ]],2,0)) -> Uday Samudra Leisure Beach Hotel | H37: Casino Houseboats | I37: Pagoda Plantation Resort | J37: The Byke Heritage - Puja Samudra | L37: Seven Springs Plantation Resort | N37: Napier Heritage Fort
A38: =IF(B37="","",_xlfn.XLOOKUP(B38,'Raw'!C:C,'Raw'!B:B)) -> Kovalam | B38: KL26 | C38: =IF(B38="","",VLOOKUP(B38,RAW[[Hotel Code]:[Hotel / Resort Name ]],2,0)) -> Uday Samudra Leisure Beach Hotel | H38: Haveli Backwater Resort | I38: Pagoda Plantation Resort | J38: Jeevan Beach Resort | L38: Seven Springs Plantation Resort | N38: Napier Heritage Fort
A39: =IF(B38="","",_xlfn.XLOOKUP(B39,'Raw'!C:C,'Raw'!B:B)) -> Kovalam | B39: KL27 | C39: =IF(B39="","",VLOOKUP(B39,RAW[[Hotel Code]:[Hotel / Resort Name ]],2,0)) -> The Byke Heritage - Puja Samudra | H39: Haveli Backwater Resort | I39: Pagoda Plantation Resort | J39: Jeevan Beach Resort | L39: Seven Springs Plantation Resort | N39: Napier Heritage Fort
A40: =IF(B39="","",_xlfn.XLOOKUP(B40,'Raw'!C:C,'Raw'!B:B)) -> Kovalam | B40: KL28 | C40: =IF(B40="","",VLOOKUP(B40,RAW[[Hotel Code]:[Hotel / Resort Name ]],2,0)) -> The Byke Heritage - Puja Samudra | H40: Haveli Backwater Resort | I40: Pagoda Plantation Resort | J40: Jeevan Beach Resort | L40: Seven Springs Plantation Resort | N40: Napier Heritage Fort
A41: =IF(B40="","",_xlfn.XLOOKUP(B41,'Raw'!C:C,'Raw'!B:B)) -> Alleppey | B41: KL29 | C41: =IF(B41="","",VLOOKUP(B41,RAW[[Hotel Code]:[Hotel / Resort Name ]],2,0)) -> Uday Backwater Resort | H41: Haveli Backwater Resort | I41: Pagoda Plantation Resort | J41: Jeevan Beach Resort | L41: The Breeze Resort | N41: Napier Heritage Fort
A42: =IF(B41="","",_xlfn.XLOOKUP(B42,'Raw'!C:C,'Raw'!B:B)) -> Alleppey | B42: KL30 | C42: =IF(B42="","",VLOOKUP(B42,RAW[[Hotel Code]:[Hotel / Resort Name ]],2,0)) -> Uday Backwater Resort | H42: Haveli Backwater Resort | I42: Pagoda Plantation Resort | J42: Jeevan Beach Resort | L42: Blossom Hill Resort
A43: =IF(B42="","",_xlfn.XLOOKUP(B43,'Raw'!C:C,'Raw'!B:B)) -> Alleppey | B43: KL31 | C43: =IF(B43="","",VLOOKUP(B43,RAW[[Hotel Code]:[Hotel / Resort Name ]],2,0)) -> Uday Backwater Resort | H43: Haveli Backwater Resort | I43: Pagoda Plantation Resort | J43: Jeevan Beach Resort | L43: Sprise Munnar Resort & Spa
A44: =IF(B43="","",_xlfn.XLOOKUP(B44,'Raw'!C:C,'Raw'!B:B)) -> Alleppey | B44: KL32 | C44: =IF(B44="","",VLOOKUP(B44,RAW[[Hotel Code]:[Hotel / Resort Name ]],2,0)) -> Uday Backwater Resort | H44: Pagoda Resorts | I44: Pagoda Plantation Resort | J44: Jeevan Beach Resort | L44: Sprise Munnar Resort & Spa
A45: =IF(B44="","",_xlfn.XLOOKUP(B45,'Raw'!C:C,'Raw'!B:B)) -> Alleppey | B45: KL33 | C45: =IF(B45="","",VLOOKUP(B45,RAW[[Hotel Code]:[Hotel / Resort Name ]],2,0)) -> Uday Backwater Resort | H45: Pagoda Resorts | I45: Pagoda Plantation Resort | J45: Jeevan Beach Resort | L45: Sprise Munnar Resort & Spa
A46: =IF(B45="","",_xlfn.XLOOKUP(B46,'Raw'!C:C,'Raw'!B:B)) -> Alleppey | B46: KL34 | C46: =IF(B46="","",VLOOKUP(B46,RAW[[Hotel Code]:[Hotel / Resort Name ]],2,0)) -> Uday Backwater Resort | H46: Pagoda Resorts | I46: Jungle Park Resort | J46: Jeevan Beach Resort | L46: Sprise Munnar Resort & Spa
A47: =IF(B46="","",_xlfn.XLOOKUP(B47,'Raw'!C:C,'Raw'!B:B)) -> Alleppey | B47: KL35 | C47: =IF(B47="","",VLOOKUP(B47,RAW[[Hotel Code]:[Hotel / Resort Name ]],2,0)) -> Uday Backwater Resort | H47: Pagoda Resorts | I47: Jungle Park Resort | J47: Lagoona Beach Resort | L47: Sprise Munnar Resort & Spa
A48: =IF(B47="","",_xlfn.XLOOKUP(B48,'Raw'!C:C,'Raw'!B:B)) -> Alleppey | B48: KL36 | C48: =IF(B48="","",VLOOKUP(B48,RAW[[Hotel Code]:[Hotel / Resort Name ]],2,0)) -> Uday Backwater Resort | H48: Pagoda Resorts | I48: Jungle Park Resort | J48: Lagoona Beach Resort | L48: Sprise Munnar Resort & Spa
A49: =IF(B48="","",_xlfn.XLOOKUP(B49,'Raw'!C:C,'Raw'!B:B)) -> Alleppey | B49: KL37 | C49: =IF(B49="","",VLOOKUP(B49,RAW[[Hotel Code]:[Hotel / Resort Name ]],2,0)) -> Uday Backwater Resort | H49: Pagoda Resorts | I49: Jungle Park Resort | J49: Lagoona Beach Resort | L49: Sprise Munnar Resort & Spa
A50: =IF(B49="","",_xlfn.XLOOKUP(B50,'Raw'!C:C,'Raw'!B:B)) -> Thiruvananthapuram | B50: KL38 | C50: =IF(B50="","",VLOOKUP(B50,RAW[[Hotel Code]:[Hotel / Resort Name ]],2,0)) -> Uday Suites, The Airport Hotel | H50: Pagoda Resorts | I50: Jungle Park Resort | J50: Lagoona Beach Resort | L50: The Breeze Resort
A51: =IF(B50="","",_xlfn.XLOOKUP(B51,'Raw'!C:C,'Raw'!B:B)) -> Thiruvananthapuram | B51: KL39 | C51: =IF(B51="","",VLOOKUP(B51,RAW[[Hotel Code]:[Hotel / Resort Name ]],2,0)) -> Uday Suites, The Airport Hotel | H51: Symphony Houseboats | I51: Jungle Park Resort | J51: Lagoona Beach Resort | L51: The Breeze Resort
A52: =IF(B51="","",_xlfn.XLOOKUP(B52,'Raw'!C:C,'Raw'!B:B)) -> Thiruvananthapuram | B52: KL40 | C52: =IF(B52="","",VLOOKUP(B52,RAW[[Hotel Code]:[Hotel / Resort Name ]],2,0)) -> Uday Suites, The Airport Hotel | H52: Venice Iva Residency | I52: Jungle Park Resort | J52: Lagoona Beach Resort | L52: Blossom Hill Resort
A53: =IF(B52="","",_xlfn.XLOOKUP(B53,'Raw'!C:C,'Raw'!B:B)) -> Thiruvananthapuram | B53: KL41 | C53: =IF(B53="","",VLOOKUP(B53,RAW[[Hotel Code]:[Hotel / Resort Name ]],2,0)) -> Uday Suites, The Airport Hotel | H53: Venice Iva Residency | I53: Jungle Park Resort | J53: Lagoona Beach Resort | L53: Blossom Hill Resort
A54: =IF(B53="","",_xlfn.XLOOKUP(B54,'Raw'!C:C,'Raw'!B:B)) -> Thiruvananthapuram | B54: KL42 | C54: =IF(B54="","",VLOOKUP(B54,RAW[[Hotel Code]:[Hotel / Resort Name ]],2,0)) -> Uday Suites, The Airport Hotel | H54: Venice Iva Residency | J54: Lagoona Beach Resort | L54: The Whispering Meadows
A55: =IF(B54="","",_xlfn.XLOOKUP(B55,'Raw'!C:C,'Raw'!B:B)) -> Thiruvananthapuram | B55: KL43 | C55: =IF(B55="","",VLOOKUP(B55,RAW[[Hotel Code]:[Hotel / Resort Name ]],2,0)) -> Uday Suites, The Airport Hotel | H55: Trium Resort & Houseboats | J55: Lagoona Beach Resort | L55: The Whispering Meadows
A56: =IF(B55="","",_xlfn.XLOOKUP(B56,'Raw'!C:C,'Raw'!B:B)) -> Thiruvananthapuram | B56: KL44 | C56: =IF(B56="","",VLOOKUP(B56,RAW[[Hotel Code]:[Hotel / Resort Name ]],2,0)) -> Uday Suites, The Airport Hotel | H56: Trium Resort & Houseboats | J56: Ocean Bay Ayurvedic Beach Resort | L56: The Whispering Meadows
A57: =IF(B56="","",_xlfn.XLOOKUP(B57,'Raw'!C:C,'Raw'!B:B)) -> Thiruvananthapuram | B57: KL45 | C57: =IF(B57="","",VLOOKUP(B57,RAW[[Hotel Code]:[Hotel / Resort Name ]],2,0)) -> Uday Suites, The Airport Hotel | H57: Trium Resort & Houseboats | J57: Ocean Bay Ayurvedic Beach Resort
A58: =IF(B57="","",_xlfn.XLOOKUP(B58,'Raw'!C:C,'Raw'!B:B)) -> Munnar | B58: KL48 | C58: =IF(B58="","",VLOOKUP(B58,RAW[[Hotel Code]:[Hotel / Resort Name ]],2,0)) -> Tea castle resort | H58: Trium Resort & Houseboats | J58: Ocean Bay Ayurvedic Beach Resort
A59: =IF(B58="","",_xlfn.XLOOKUP(B59,'Raw'!C:C,'Raw'!B:B)) -> Munnar | B59: KL49 | C59: =IF(B59="","",VLOOKUP(B59,RAW[[Hotel Code]:[Hotel / Resort Name ]],2,0)) -> Tea castle resort | H59: Trium Resort & Houseboats | J59: Ocean Bay Ayurvedic Beach Resort
A60: =IF(B59="","",_xlfn.XLOOKUP(B60,'Raw'!C:C,'Raw'!B:B)) -> Munnar | B60: KL50 | C60: =IF(B60="","",VLOOKUP(B60,RAW[[Hotel Code]:[Hotel / Resort Name ]],2,0)) -> Tea castle resort | H60: Trium Resort & Houseboats | J60: Ocean Bay Ayurvedic Beach Resort
A61: =IF(B60="","",_xlfn.XLOOKUP(B61,'Raw'!C:C,'Raw'!B:B)) -> Munnar | B61: KL51 | C61: =IF(B61="","",VLOOKUP(B61,RAW[[Hotel Code]:[Hotel / Resort Name ]],2,0)) -> Tea castle resort | H61: Trium Deluxe Houseboats | J61: Aadisaktthi Resort
A62: =IF(B61="","",_xlfn.XLOOKUP(B62,'Raw'!C:C,'Raw'!B:B)) -> Munnar | B62: KL52 | C62: =IF(B62="","",VLOOKUP(B62,RAW[[Hotel Code]:[Hotel / Resort Name ]],2,0)) -> Tea castle resort | H62: Trium Deluxe Houseboats | J62: Aadisaktthi Resort
A63: =IF(B62="","",_xlfn.XLOOKUP(B63,'Raw'!C:C,'Raw'!B:B)) -> Munnar | B63: KL53 | C63: =IF(B63="","",VLOOKUP(B63,RAW[[Hotel Code]:[Hotel / Resort Name ]],2,0)) -> Tea castle resort | H63: Trium Preimum Houseboats | J63: Aadisaktthi Resort
A64: =IF(B63="","",_xlfn.XLOOKUP(B64,'Raw'!C:C,'Raw'!B:B)) -> Munnar | B64: KL54 | C64: =IF(B64="","",VLOOKUP(B64,RAW[[Hotel Code]:[Hotel / Resort Name ]],2,0)) -> The Breeze Resort | H64: Trium Preimum Houseboats | J64: Aadisaktthi Resort
A65: =IF(B64="","",_xlfn.XLOOKUP(B65,'Raw'!C:C,'Raw'!B:B)) -> Munnar | B65: KL55 | C65: =IF(B65="","",VLOOKUP(B65,RAW[[Hotel Code]:[Hotel / Resort Name ]],2,0)) -> The Breeze Resort | H65: Miraaya Sundara Island Villa | J65: Aadisaktthi Resort
A66: =IF(B65="","",_xlfn.XLOOKUP(B66,'Raw'!C:C,'Raw'!B:B)) -> Munnar | B66: KL56 | C66: =IF(B66="","",VLOOKUP(B66,RAW[[Hotel Code]:[Hotel / Resort Name ]],2,0)) -> The Whispering Meadows | H66: Miraaya Sundara Island Villa | J66: Aadisaktthi Resort
A67: =IF(B66="","",_xlfn.XLOOKUP(B67,'Raw'!C:C,'Raw'!B:B)) -> Munnar | B67: KL57 | C67: =IF(B67="","",VLOOKUP(B67,RAW[[Hotel Code]:[Hotel / Resort Name ]],2,0)) -> The Whispering Meadows | H67: Miraaya Sundara Island Villa | J67: Aadisaktthi Resort
A68: =IF(B67="","",_xlfn.XLOOKUP(B68,'Raw'!C:C,'Raw'!B:B)) -> Munnar | B68: KL58 | C68: =IF(B68="","",VLOOKUP(B68,RAW[[Hotel Code]:[Hotel / Resort Name ]],2,0)) -> Blossom Hill Resort | H68: Miraaya Sundara Island Villa | J68: Aadisaktthi Resort
A69: =IF(B68="","",_xlfn.XLOOKUP(B69,'Raw'!C:C,'Raw'!B:B)) -> Munnar | B69: KL59 | C69: =IF(B69="","",VLOOKUP(B69,RAW[[Hotel Code]:[Hotel / Resort Name ]],2,0)) -> Blossom Hill Resort | H69: Miraaya Sundara Island Villa | J69: Aadisaktthi Resort
A70: =IF(B69="","",_xlfn.XLOOKUP(B70,'Raw'!C:C,'Raw'!B:B)) -> Alleppey | B70: KL62 | C70: =IF(B70="","",VLOOKUP(B70,RAW[[Hotel Code]:[Hotel / Resort Name ]],2,0)) -> Venice Iva Residency
A71: =IF(B70="","",_xlfn.XLOOKUP(B71,'Raw'!C:C,'Raw'!B:B)) -> Alleppey | B71: KL63 | C71: =IF(B71="","",VLOOKUP(B71,RAW[[Hotel Code]:[Hotel / Resort Name ]],2,0)) -> Venice Iva Residency
A72: =IF(B71="","",_xlfn.XLOOKUP(B72,'Raw'!C:C,'Raw'!B:B)) -> Munnar | B72: KL64 | C72: =IF(B72="","",VLOOKUP(B72,RAW[[Hotel Code]:[Hotel / Resort Name ]],2,0)) -> Seven Springs Plantation Resort
A73: =IF(B72="","",_xlfn.XLOOKUP(B73,'Raw'!C:C,'Raw'!B:B)) -> Munnar | B73: KL65 | C73: =IF(B73="","",VLOOKUP(B73,RAW[[Hotel Code]:[Hotel / Resort Name ]],2,0)) -> Seven Springs Plantation Resort
A74: =IF(B73="","",_xlfn.XLOOKUP(B74,'Raw'!C:C,'Raw'!B:B)) -> Munnar | B74: KL66 | C74: =IF(B74="","",VLOOKUP(B74,RAW[[Hotel Code]:[Hotel / Resort Name ]],2,0)) -> Seven Springs Plantation Resort
A75: =IF(B74="","",_xlfn.XLOOKUP(B75,'Raw'!C:C,'Raw'!B:B)) -> Munnar | B75: KL67 | C75: =IF(B75="","",VLOOKUP(B75,RAW[[Hotel Code]:[Hotel / Resort Name ]],2,0)) -> Seven Springs Plantation Resort
A76: =IF(B75="","",_xlfn.XLOOKUP(B76,'Raw'!C:C,'Raw'!B:B)) -> Munnar | B76: KL68 | C76: =IF(B76="","",VLOOKUP(B76,RAW[[Hotel Code]:[Hotel / Resort Name ]],2,0)) -> Seven Springs Plantation Resort
A77: =IF(B76="","",_xlfn.XLOOKUP(B77,'Raw'!C:C,'Raw'!B:B)) -> Alleppey | B77: KL69 | C77: =IF(B77="","",VLOOKUP(B77,RAW[[Hotel Code]:[Hotel / Resort Name ]],2,0)) -> Casino Houseboats
A78: =IF(B77="","",_xlfn.XLOOKUP(B78,'Raw'!C:C,'Raw'!B:B)) -> Alleppey | B78: KL70 | C78: =IF(B78="","",VLOOKUP(B78,RAW[[Hotel Code]:[Hotel / Resort Name ]],2,0)) -> Casino Houseboats
A79: =IF(B78="","",_xlfn.XLOOKUP(B79,'Raw'!C:C,'Raw'!B:B)) -> Alleppey | B79: KL72 | C79: =IF(B79="","",VLOOKUP(B79,RAW[[Hotel Code]:[Hotel / Resort Name ]],2,0)) -> Haveli Backwater Resort
A80: =IF(B79="","",_xlfn.XLOOKUP(B80,'Raw'!C:C,'Raw'!B:B)) -> Alleppey | B80: KL73 | C80: =IF(B80="","",VLOOKUP(B80,RAW[[Hotel Code]:[Hotel / Resort Name ]],2,0)) -> Haveli Backwater Resort
A81: =IF(B80="","",_xlfn.XLOOKUP(B81,'Raw'!C:C,'Raw'!B:B)) -> Alleppey | B81: KL74 | C81: =IF(B81="","",VLOOKUP(B81,RAW[[Hotel Code]:[Hotel / Resort Name ]],2,0)) -> Haveli Backwater Resort
... A200: =IF(B199="","",_xlfn.XLOOKUP(B200,'Raw'!C:C,'Raw'!B:B)) -> Alleppey | B200: KL193 | C200: =IF(B200="","",VLOOKUP(B200,RAW[[Hotel Code]:[Hotel / Resort Name ]],2,0)) -> Miraaya Sundara Island Villa
A201: =IF(B200="","",_xlfn.XLOOKUP(B201,'Raw'!C:C,'Raw'!B:B)) -> 0 | C201: =IF(B201="","",VLOOKUP(B201,RAW[[Hotel Code]:[Hotel / Resort Name ]],2,0))
A202: =IF(B201="","",_xlfn.XLOOKUP(B202,'Raw'!C:C,'Raw'!B:B)) | C202: =IF(B202="","",VLOOKUP(B202,RAW[[Hotel Code]:[Hotel / Resort Name ]],2,0))
A203: =IF(B202="","",_xlfn.XLOOKUP(B203,'Raw'!C:C,'Raw'!B:B)) | C203: =IF(B203="","",VLOOKUP(B203,RAW[[Hotel Code]:[Hotel / Resort Name ]],2,0))
A204: =IF(B203="","",_xlfn.XLOOKUP(B204,'Raw'!C:C,'Raw'!B:B)) | C204: =IF(B204="","",VLOOKUP(B204,RAW[[Hotel Code]:[Hotel / Resort Name ]],2,0))
A205: =IF(B204="","",_xlfn.XLOOKUP(B205,'Raw'!C:C,'Raw'!B:B)) | C205: =IF(B205="","",VLOOKUP(B205,RAW[[Hotel Code]:[Hotel / Resort Name ]],2,0))
A206: =IF(B205="","",_xlfn.XLOOKUP(B206,'Raw'!C:C,'Raw'!B:B)) | C206: =IF(B206="","",VLOOKUP(B206,RAW[[Hotel Code]:[Hotel / Resort Name ]],2,0))
A207: =IF(B206="","",_xlfn.XLOOKUP(B207,'Raw'!C:C,'Raw'!B:B)) | C207: =IF(B207="","",VLOOKUP(B207,RAW[[Hotel Code]:[Hotel / Resort Name ]],2,0))
A208: =IF(B207="","",_xlfn.XLOOKUP(B208,'Raw'!C:C,'Raw'!B:B)) | C208: =IF(B208="","",VLOOKUP(B208,RAW[[Hotel Code]:[Hotel / Resort Name ]],2,0))
A209: =IF(B208="","",_xlfn.XLOOKUP(B209,'Raw'!C:C,'Raw'!B:B)) | C209: =IF(B209="","",VLOOKUP(B209,RAW[[Hotel Code]:[Hotel / Resort Name ]],2,0))
A210: =IF(B209="","",_xlfn.XLOOKUP(B210,'Raw'!C:C,'Raw'!B:B)) | C210: =IF(B210="","",VLOOKUP(B210,RAW[[Hotel Code]:[Hotel / Resort Name ]],2,0))
A211: =IF(B210="","",_xlfn.XLOOKUP(B211,'Raw'!C:C,'Raw'!B:B)) | C211: =IF(B211="","",VLOOKUP(B211,RAW[[Hotel Code]:[Hotel / Resort Name ]],2,0))
A212: =IF(B211="","",_xlfn.XLOOKUP(B212,'Raw'!C:C,'Raw'!B:B)) | C212: =IF(B212="","",VLOOKUP(B212,RAW[[Hotel Code]:[Hotel / Resort Name ]],2,0))
... A522: =IF(B521="","",_xlfn.XLOOKUP(B522,'Raw'!C:C,'Raw'!B:B)) | C522: =IF(B522="","",VLOOKUP(B522,RAW[[Hotel Code]:[Hotel / Resort Name ]],2,0))
C523: =IF(B523="","",VLOOKUP(B523,RAW[[Hotel Code]:[Hotel / Resort Name ]],2,0))
C524: =IF(B524="","",VLOOKUP(B524,RAW[[Hotel Code]:[Hotel / Resort Name ]],2,0))
C525: =IF(B525="","",VLOOKUP(B525,RAW[[Hotel Code]:[Hotel / Resort Name ]],2,0))
C526: =IF(B526="","",VLOOKUP(B526,RAW[[Hotel Code]:[Hotel / Resort Name ]],2,0))
C527: =IF(B527="","",VLOOKUP(B527,RAW[[Hotel Code]:[Hotel / Resort Name ]],2,0))
C528: =IF(B528="","",VLOOKUP(B528,RAW[[Hotel Code]:[Hotel / Resort Name ]],2,0))
C529: =IF(B529="","",VLOOKUP(B529,RAW[[Hotel Code]:[Hotel / Resort Name ]],2,0))
C530: =IF(B530="","",VLOOKUP(B530,RAW[[Hotel Code]:[Hotel / Resort Name ]],2,0))
...
